Workbook
Name Dia_A: 'Rentabilidad x Cedi'!$G$9
Name EERR_Año: '[1]BD Llenado'!$U$6:$U$20102

Sheet analisis segmento
A1: Region | B1: Territorio | C1: Cedis | D1: Ruta | E1: Mix de categoría por región (target Conservador) | F1: % utilización OP (Venta CU) | G1: % utilización GFN (Venta CU) | H1: OP incremental (CU/día) | I1: GFN incremental (CU/día)
A2: =IF('[3]Motor Rutas SKU_Cons'!C6="","",'[3]Motor Rutas SKU_Cons'!C6) -> Norte | B2: =IF('[3]Motor Rutas SKU_Cons'!D6="","",'[3]Motor Rutas SKU_Cons'!D6) -> Comarca | C2: =IF('[3]Motor Rutas SKU_Cons'!B6="","",'[3]Motor Rutas SKU_Cons'!B6) -> Suc. San Pedro | D2: ='[3]Motor Rutas SKU_Cons'!A6 -> 219340 | E2: =IF('[3]Motor Rutas SKU_Cons'!N6="","s/d","Agua "&TEXT('[3]Motor Rutas SKU_Cons'!N6,"0%")&" · Colas "&TEXT('[3]Motor Rutas SKU_Cons'!O6,"0%")&" · Resto "&TEXT('[3]Motor Rutas SKU_Cons'!P6,"0%")) -> Agua 85% · Colas 8% · Resto 7% | F2: ='[3]Motor Rutas SKU_Cons'!CH6 -> 0.16100098 | G2: ='[3]Motor Rutas SKU_Cons'!CG6 -> 0.49329849 | H2: ='[3]Motor Rutas SKU_Cons'!BX6 -> 0 | I2: ='[3]Motor Rutas SKU_Cons'!BW6 -> 0
A3: =IF('[3]Motor Rutas SKU_Cons'!C7="","",'[3]Motor Rutas SKU_Cons'!C7) -> Norte | B3: =IF('[3]Motor Rutas SKU_Cons'!D7="","",'[3]Motor Rutas SKU_Cons'!D7) -> Juárez | C3: =IF('[3]Motor Rutas SKU_Cons'!B7="","",'[3]Motor Rutas SKU_Cons'!B7) -> Suc. Casas Grandes | D3: ='[3]Motor Rutas SKU_Cons'!A7 -> 305400 | E3: =IF('[3]Motor Rutas SKU_Cons'!N7="","s/d","Agua "&TEXT('[3]Motor Rutas SKU_Cons'!N7,"0%")&" · Colas "&TEXT('[3]Motor Rutas SKU_Cons'!O7,"0%")&" · Resto "&TEXT('[3]Motor Rutas SKU_Cons'!P7,"0%")) -> Agua 85% · Colas 8% · Resto 7% | F3: ='[3]Motor Rutas SKU_Cons'!CH7 -> 0.10448758 | G3: ='[3]Motor Rutas SKU_Cons'!CG7 -> 0.48448109 | H3: ='[3]Motor Rutas SKU_Cons'!BX7 -> 0 | I3: ='[3]Motor Rutas SKU_Cons'!BW7 -> 0
A4: =IF('[3]Motor Rutas SKU_Cons'!C8="","",'[3]Motor Rutas SKU_Cons'!C8) -> Sin región | B4: =IF('[3]Motor Rutas SKU_Cons'!D8="","",'[3]Motor Rutas SKU_Cons'!D8) -> Sin territorio | C4: =IF('[3]Motor Rutas SKU_Cons'!B8="","",'[3]Motor Rutas SKU_Cons'!B8) -> Sin CeDi | D4: ='[3]Motor Rutas SKU_Cons'!A8 -> 309399 | E4: =IF('[3]Motor Rutas SKU_Cons'!N8="","s/d","Agua "&TEXT('[3]Motor Rutas SKU_Cons'!N8,"0%")&" · Colas "&TEXT('[3]Motor Rutas SKU_Cons'!O8,"0%")&" · Resto "&TEXT('[3]Motor Rutas SKU_Cons'!P8,"0%")) -> s/d | F4: ='[3]Motor Rutas SKU_Cons'!CH8 | G4: ='[3]Motor Rutas SKU_Cons'!CG8 | H4: ='[3]Motor Rutas SKU_Cons'!BX8 -> 0 | I4: ='[3]Motor Rutas SKU_Cons'!BW8 -> 0
A5: =IF('[3]Motor Rutas SKU_Cons'!C9="","",'[3]Motor Rutas SKU_Cons'!C9) -> Sin región | B5: =IF('[3]Motor Rutas SKU_Cons'!D9="","",'[3]Motor Rutas SKU_Cons'!D9) -> Sin territorio | C5: =IF('[3]Motor Rutas SKU_Cons'!B9="","",'[3]Motor Rutas SKU_Cons'!B9) -> Sin CeDi | D5: ='[3]Motor Rutas SKU_Cons'!A9 -> 312399 | E5: =IF('[3]Motor Rutas SKU_Cons'!N9="","s/d","Agua "&TEXT('[3]Motor Rutas SKU_Cons'!N9,"0%")&" · Colas "&TEXT('[3]Motor Rutas SKU_Cons'!O9,"0%")&" · Resto "&TEXT('[3]Motor Rutas SKU_Cons'!P9,"0%")) -> s/d | F5: ='[3]Motor Rutas SKU_Cons'!CH9 | G5: ='[3]Motor Rutas SKU_Cons'!CG9 | H5: ='[3]Motor Rutas SKU_Cons'!BX9 -> 0 | I5: ='[3]Motor Rutas SKU_Cons'!BW9 -> 0
A6: =IF('[3]Motor Rutas SKU_Cons'!C10="","",'[3]Motor Rutas SKU_Cons'!C10) -> Pacifico | B6: =IF('[3]Motor Rutas SKU_Cons'!D10="","",'[3]Motor Rutas SKU_Cons'!D10) -> Hermosillo | C6: =IF('[3]Motor Rutas SKU_Cons'!B10="","",'[3]Motor Rutas SKU_Cons'!B10) -> Planta Hermosillo | D6: ='[3]Motor Rutas SKU_Cons'!A10 -> 401300 | E6: =IF('[3]Motor Rutas SKU_Cons'!N10="","s/d","Agua "&TEXT('[3]Motor Rutas SKU_Cons'!N10,"0%")&" · Colas "&TEXT('[3]Motor Rutas SKU_Cons'!O10,"0%")&" · Resto "&TEXT('[3]Motor Rutas SKU_Cons'!P10,"0%")) -> Agua 85% · Colas 8% · Resto 7% | F6: ='[3]Motor Rutas SKU_Cons'!CH10 -> 0.20658303 | G6: ='[3]Motor Rutas SKU_Cons'!CG10 | H6: ='[3]Motor Rutas SKU_Cons'!BX10 -> 0 | I6: ='[3]Motor Rutas SKU_Cons'!BW10 -> 0
A7: =IF('[3]Motor Rutas SKU_Cons'!C11="","",'[3]Motor Rutas SKU_Cons'!C11) -> Pacifico | B7: =IF('[3]Motor Rutas SKU_Cons'!D11="","",'[3]Motor Rutas SKU_Cons'!D11) -> Hermosillo | C7: =IF('[3]Motor Rutas SKU_Cons'!B11="","",'[3]Motor Rutas SKU_Cons'!B11) -> Planta Hermosillo | D7: ='[3]Motor Rutas SKU_Cons'!A11 -> 401301 | E7: =IF('[3]Motor Rutas SKU_Cons'!N11="","s/d","Agua "&TEXT('[3]Motor Rutas SKU_Cons'!N11,"0%")&" · Colas "&TEXT('[3]Motor Rutas SKU_Cons'!O11,"0%")&" · Resto "&TEXT('[3]Motor Rutas SKU_Cons'!P11,"0%")) -> Agua 85% · Colas 8% · Resto 7% | F7: ='[3]Motor Rutas SKU_Cons'!CH11 -> 0.073576436 | G7: ='[3]Motor Rutas SKU_Cons'!CG11 | H7: ='[3]Motor Rutas SKU_Cons'!BX11 -> 0 | I7: ='[3]Motor Rutas SKU_Cons'!BW11 -> 0
A8: =IF('[3]Motor Rutas SKU_Cons'!C12="","",'[3]Motor Rutas SKU_Cons'!C12) -> Pacifico | B8: =IF('[3]Motor Rutas SKU_Cons'!D12="","",'[3]Motor Rutas SKU_Cons'!D12) -> Hermosillo | C8: =IF('[3]Motor Rutas SKU_Cons'!B12="","",'[3]Motor Rutas SKU_Cons'!B12) -> Planta Hermosillo | D8: ='[3]Motor Rutas SKU_Cons'!A12 -> 401302 | E8: =IF('[3]Motor Rutas SKU_Cons'!N12="","s/d","Agua "&TEXT('[3]Motor Rutas SKU_Cons'!N12,"0%")&" · Colas "&TEXT('[3]Motor Rutas SKU_Cons'!O12,"0%")&" · Resto "&TEXT('[3]Motor Rutas SKU_Cons'!P12,"0%")) -> Agua 85% · Colas 8% · Resto 7% | F8: ='[3]Motor Rutas SKU_Cons'!CH12 -> 0.14911054 | G8: ='[3]Motor Rutas SKU_Cons'!CG12 | H8: ='[3]Motor Rutas SKU_Cons'!BX12 -> 0 | I8: ='[3]Motor Rutas SKU_Cons'!BW12 -> 0
A9: =IF('[3]Motor Rutas SKU_Cons'!C13="","",'[3]Motor Rutas SKU_Cons'!C13) -> Pacifico | B9: =IF('[3]Motor Rutas SKU_Cons'!D13="","",'[3]Motor Rutas SKU_Cons'!D13) -> Hermosillo | C9: =IF('[3]Motor Rutas SKU_Cons'!B13="","",'[3]Motor Rutas SKU_Cons'!B13) -> Planta Hermosillo | D9: ='[3]Motor Rutas SKU_Cons'!A13 -> 401307 | E9: =IF('[3]Motor Rutas SKU_Cons'!N13="","s/d","Agua "&TEXT('[3]Motor Rutas SKU_Cons'!N13,"0%")&" · Colas "&TEXT('[3]Motor Rutas SKU_Cons'!O13,"0%")&" · Resto "&TEXT('[3]Motor Rutas SKU_Cons'!P13,"0%")) -> Agua 85% · Colas 8% · Resto 7% | F9: ='[3]Motor Rutas SKU_Cons'!CH13 -> 0.00066498062 | G9: ='[3]Motor Rutas SKU_Cons'!CG13 | H9: ='[3]Motor Rutas SKU_Cons'!BX13 -> 0 | I9: ='[3]Motor Rutas SKU_Cons'!BW13 -> 0
A10: =IF('[3]Motor Rutas SKU_Cons'!C14="","",'[3]Motor Rutas SKU_Cons'!C14) -> Pacifico | B10: =IF('[3]Motor Rutas SKU_Cons'!D14="","",'[3]Motor Rutas SKU_Cons'!D14) -> No está en EERR | C10: =IF('[3]Motor Rutas SKU_Cons'!B14="","",'[3]Motor Rutas SKU_Cons'!B14) -> Sucursal Cajeme | D10: ='[3]Motor Rutas SKU_Cons'!A14 -> 404304 | E10: =IF('[3]Motor Rutas SKU_Cons'!N14="","s/d","Agua "&TEXT('[3]Motor Rutas SKU_Cons'!N14,"0%")&" · Colas "&TEXT('[3]Motor Rutas SKU_Cons'!O14,"0%")&" · Resto "&TEXT('[3]Motor Rutas SKU_Cons'!P14,"0%")) -> Agua 85% · Colas 8% · Resto 7% | F10: ='[3]Motor Rutas SKU_Cons'!CH14 | G10: ='[3]Motor Rutas SKU_Cons'!CG14 | H10: ='[3]Motor Rutas SKU_Cons'!BX14 -> 0 | I10: ='[3]Motor Rutas SKU_Cons'!BW14 -> 0
A11: =IF('[3]Motor Rutas SKU_Cons'!C15="","",'[3]Motor Rutas SKU_Cons'!C15) -> Pacifico | B11: =IF('[3]Motor Rutas SKU_Cons'!D15="","",'[3]Motor Rutas SKU_Cons'!D15) -> No está en EERR | C11: =IF('[3]Motor Rutas SKU_Cons'!B15="","",'[3]Motor Rutas SKU_Cons'!B15) -> Sucursal Guaymas | D11: ='[3]Motor Rutas SKU_Cons'!A15 -> 406300 | E11: =IF('[3]Motor Rutas SKU_Cons'!N15="","s/d","Agua "&TEXT('[3]Motor Rutas SKU_Cons'!N15,"0%")&" · Colas "&TEXT('[3]Motor Rutas SKU_Cons'!O15,"0%")&" · Resto "&TEXT('[3]Motor Rutas SKU_Cons'!P15,"0%")) -> Agua 85% · Colas 8% · Resto 7% | F11: ='[3]Motor Rutas SKU_Cons'!CH15 | G11: ='[3]Motor Rutas SKU_Cons'!CG15 | H11: ='[3]Motor Rutas SKU_Cons'!BX15 -> 0 | I11: ='[3]Motor Rutas SKU_Cons'!BW15 -> 0
A12: =IF('[3]Motor Rutas SKU_Cons'!C16="","",'[3]Motor Rutas SKU_Cons'!C16) -> Pacifico | B12: =IF('[3]Motor Rutas SKU_Cons'!D16="","",'[3]Motor Rutas SKU_Cons'!D16) -> Mexicali | C12: =IF('[3]Motor Rutas SKU_Cons'!B16="","",'[3]Motor Rutas SKU_Cons'!B16) -> Planta Mexicali | D12: ='[3]Motor Rutas SKU_Cons'!A16 -> 407300 | E12: =IF('[3]Motor Rutas SKU_Cons'!N16="","s/d","Agua "&TEXT('[3]Motor Rutas SKU_Cons'!N16,"0%")&" · Colas "&TEXT('[3]Motor Rutas SKU_Cons'!O16,"0%")&" · Resto "&TEXT('[3]Motor Rutas SKU_Cons'!P16,"0%")) -> Agua 85% · Colas 8% · Resto 7% | F12: ='[3]Motor Rutas SKU_Cons'!CH16 -> 0.093449719 | G12: ='[3]Motor Rutas SKU_Cons'!CG16 | H12: ='[3]Motor Rutas SKU_Cons'!BX16 -> 0 | I12: ='[3]Motor Rutas SKU_Cons'!BW16 -> 0
A13: =IF('[3]Motor Rutas SKU_Cons'!C17="","",'[3]Motor Rutas SKU_Cons'!C17) -> Pacifico | B13: =IF('[3]Motor Rutas SKU_Cons'!D17="","",'[3]Motor Rutas SKU_Cons'!D17) -> Mexicali | C13: =IF('[3]Motor Rutas SKU_Cons'!B17="","",'[3]Motor Rutas SKU_Cons'!B17) -> Planta Mexicali | D13: ='[3]Motor Rutas SKU_Cons'!A17 -> 407301 | E13: =IF('[3]Motor Rutas SKU_Cons'!N17="","s/d","Agua "&TEXT('[3]Motor Rutas SKU_Cons'!N17,"0%")&" · Colas "&TEXT('[3]Motor Rutas SKU_Cons'!O17,"0%")&" · Resto "&TEXT('[3]Motor Rutas SKU_Cons'!P17,"0%")) -> Agua 85% · Colas 8% · Resto 7% | F13: ='[3]Motor Rutas SKU_Cons'!CH17 -> 0.17389948 | G13: ='[3]Motor Rutas SKU_Cons'!CG17 | H13: ='[3]Motor Rutas SKU_Cons'!BX17 -> 0 | I13: ='[3]Motor Rutas SKU_Cons'!BW17 -> 0
... A717: =IF('[3]Motor Rutas SKU_Cons'!C721="","",'[3]Motor Rutas SKU_Cons'!C721) -> Occidente | B717: =IF('[3]Motor Rutas SKU_Cons'!D721="","",'[3]Motor Rutas SKU_Cons'!D721) -> San Luis | C717: =IF('[3]Motor Rutas SKU_Cons'!B721="","",'[3]Motor Rutas SKU_Cons'!B721) -> Planta San Luis | D717: ='[3]Motor Rutas SKU_Cons'!A721 -> 916399 | E717: =IF('[3]Motor Rutas SKU_Cons'!N721="","s/d","Agua "&TEXT('[3]Motor Rutas SKU_Cons'!N721,"0%")&" · Colas "&TEXT('[3]Motor Rutas SKU_Cons'!O721,"0%")&" · Resto "&TEXT('[3]Motor Rutas SKU_Cons'!P721,"0%")) -> Agua 85% · Colas 8% · Resto 7% | F717: ='[3]Motor Rutas SKU_Cons'!CH721 -> 0.0060561904 | G717: ='[3]Motor Rutas SKU_Cons'!CG721 -> 0 | H717: ='[3]Motor Rutas SKU_Cons'!BX721 -> 0 | I717: ='[3]Motor Rutas SKU_Cons'!BW721 -> 3.3682753

Sheet Base de datos Rutas
A1: Base Maestra Rutas — Canal Hogar (789 rutas, ventana ene-2025 a may-2026)
AC2: Agregar | DB2: Incremental | DD2: Incremental | DJ2: Incremental | DL2: Incremental | DR2: Incremental | DT2: Incremental
A3: Identificación | I3: Rentabilidad y volumen (Costo de Servir) | AK3: Potencial y palancas de crecimiento | BD3: Saturación de rutas | BR3: Descripción de Mercado (+NSE) | CK3: Saturación | CW3: Atractividad Caso 90 | DE3: Atractividad Caso 85 | DM3: Atractividad Caso 70
A4: Llaves de cruce y calidad de dato | I4: Rutas | J4: Volumen [CU] | N4: Venta por producto y productividad | R4: Costos (heredado del CeDi) | W4: Venta, CDS y cuadrante | Z4: Operación de ruta | AB4: Mezcla (%) | AK4: Clientes | AM4: Efectividad vs. benchmark | AO4: Brecha de Efectividad (escenario) | AR4: Ingreso y uplift | AU4: Potencial anualizado — Efectividad | AX4: Palanca de ticket | BC4: Total palancas | BD4: Elegibilidad y comparación vs. estándar de su Territorio EERR | BN4: Resultado | BQ4: Capacidad | BR4: Descripción de Mercado (+NSE) | CK4: Potencial | CQ4: Capacidades
A5: Región | B5: Territorio EERR | C5: CeDi | D5: Ruta | E5: Ruta ID | F5: Estatus de ruta | G5: Código de ruta válido | H5: Elegible para estándar | I5: Rutas Hogar del CeDi | J5: Cajas Unidad Garrafón | K5: Cajas Unidad Otros Productos | L5: Volumen Total en Cajas Unidad [CU] | M5: Venta Ingreso | N5: Venta GFN [MXN] | O5: Venta OP [MXN] | P5: Venta MC [MXN] | Q5: Ingreso / Ruta | R5: Costos de Venta Variable | S5: GOD | T5: GOC | U5: Costo-De-Servir (Cedis) (miles) | V5: CDS / Ruta | W5: Venta ruta (promedio cedis) | X5: %CDS vs. Venta Neta | Y5: Cuadrante | Z5: Número de clientes x ruta | AA5: Frecuencia Conv. [/semana] | AB5: % Venta Conv. | AC5: % Venta Web. | AD5: CU conv | AE5: CU web | AF5: Ing conv | AG5: Ing web | AH5: % Venta GFN (ingreso) | AI5: % Venta OP (ingreso) | AJ5: % Venta MC (ingreso) | AK5: Ctes. programados (periodo) | AL5: Ctes. con compra (periodo) | AM5: Efectividad actual | AN5: Benchmark p75 del CeDi | AO5: Ctes. increm. (100%) | AP5: Ctes. increm. (escenario) | AQ5: Efectividad objetivo (escenario) | AR5: Ingreso actual (periodo) | AS5: Ingreso increm. Efectividad (periodo) | AT5: Uplift Efectividad % | AU5: Anualizado Efectividad | AV5: % del potencial del canal | AW5: Ranking por potencial | AX5: Ticket $ / CC | AY5: Ticket p75 de su CeDi | AZ5: Brecha de ticket ($/CC) | BA5: Ruta con brecha de ticket | BB5: Anualizado ticket | BC5: Anualizado ambas palancas | BD5: Elegible (saturación) | BE5: Clientes atiende/día (real) | BF5: Estándar territorio (ideal) — clientes | BG5: Cumple (clientes) | BH5: Efectividad de compra (real) | BI5: Estándar territorio (ideal) — efectividad | BJ5: Cumple (efectividad) | BK5: Volumen CU/día (real) | BL5: Estándar territorio (ideal) — volumen | BM5: Cumple (volumen) | BN5: # Indicadores cumplidos (0-3) | BO5: Zona de saturación | BP5: Saturada (Sí/No) | BQ5: Capacidad adicional (clientes) | BR5: Manzanas | BS5: Población | BT5: Hogares | BU5: Personas por hogar | BV5: Hogares por manzana | BW5: Hogares A/B | BX5: Hogares C+ | BY5: Hogares A/B + C+ | BZ5: % A/B + C+ | CA5: % NSE A/B | CB5: % NSE C+ | CC5: % NSE C | CD5: % NSE C- | CE5: % NSE D+ | CF5: % NSE D | CG5: % NSE E | CH5: % NSE N/D | CI5: Comercio detalle / 1000 hab | CJ5: Comercio proximidad / 1000 hab | CK5: Clientes actuales (Total) | CL5: Clientes potencial | CM5: Delta clientes | CN5: Horas actuales | CO5: Jornada completa | CP5: Delta Horas | CQ5: Capacidad instalada | CR5: Capacidad Utilizada | CS5: Delta Capacidad | CT5: Saturada | CU5: Que tan saturada | CV5: Clientes actuales (Foco) | CW5: Hogares totales ABC+ | CX5: % Hogares totales ABC+ | CY5: Hogares potenciales a captutrar | CZ5: Hogares actual + potencial | DA5: potencial Ingreso /horar | DB5: Potencial de Ingreso | DC5: potencial CU/ hogar | DD5: Potencial CU | DE5: Hogares totales ABC+ | DF5: % Hogares totales ABC+ | DG5: Hogares potenciales a captutrar | DH5: Hogares actual + potencial | DI5: potencial Ingreso /horar | DJ5: Potencial de Ingreso | DK5: potencial CU/ hogar | DL5: Potencial CU | DM5: Hogares totales ABC+ | DN5: % Hogares totales ABC+ | DO5: Hogares potenciales a captutrar | DP5: Hogares actual + potencial | DQ5: potencial Ingreso /horar | DR5: Potencial de Ingreso | DS5: potencial CU/ hogar | DT5: Potencial CU
A6: Noreste | B6: Laredo | C6: Suc. Nuevo Laredo | D6: 105300 | E6: Noreste|Suc. Nuevo Laredo|105300 | F6: Activa | G6: Sí | H6: Sí | I6: 3 | J6: 35033.79 | K6: 30787.417 | L6: 65821.208 | M6: 4663587 | N6: 521961 | O6: 4141626 | P6: 0 | Q6: 11077.4 | R6: 688.35454 | S6: 2836.8939 | T6: 464.31479 | U6: =IFERROR(INDEX('Rentabilidad datos'!$N$2:$N$61,MATCH($C6,'Rentabilidad datos'!$C$2:$C$61,0)),"") -> 3989.5633 | V6: =IFERROR(INDEX('Rentabilidad datos'!$O$2:$O$61,MATCH($C6,'Rentabilidad datos'!$C$2:$C$61,0)),"") -> 1329.8544 | W6: =IFERROR(INDEX('Rentabilidad datos'!$M$2:$M$61,MATCH($C6,'Rentabilidad datos'!$C$2:$C$61,0)),"") -> 2708.9427 | X6: =IFERROR(INDEX('Rentabilidad datos'!$P$2:$P$61,MATCH($C6,'Rentabilidad datos'!$C$2:$C$61,0)),"") -> 0.49091271 | Y6: C4 | Z6: 36 | AA6: 1 | AB6: 1 | AC6: 0 | AD6: =_xlfn.XLOOKUP(Table1[[#This Row],[Ruta]],#REF!,#REF!) -> #REF! | AE6: =_xlfn.XLOOKUP(Table1[[#This Row],[Ruta]],#REF!,#REF!) -> #REF! | AF6: =_xlfn.XLOOKUP(Table1[[#This Row],[Ruta]],#REF!,#REF!) -> #REF! | AG6: =_xlfn.XLOOKUP(Table1[[#This Row],[Ruta]],#REF!,#REF!) -> #REF! | AH6: 0.11192265 | AI6: 0.88807735 | AJ6: 0 | AK6: 15156 | AL6: 5829 | AM6: 0.38460016 | AN6: 0.51668553 | AO6: 2001.8858 | AP6: 1000.9429 | AQ6: 0.45064284 | AR6: 4663585.2 | AS6: 800820.48 | AT6: 0.17171778 | AU6: 562738.72 | AV6: 0.0025599517 | AW6: 132 | AX6: 800.06608 | AY6: 754.63815 | AZ6: 0 | BA6: No | BB6: 0 | BC6: 562738.72 | BD6: Sí | BE6: 36 | BF6: 36 | BG6: Sí | BH6: 0.38460016 | BI6: 0.38460016 | BJ6: Sí | BK6: 156.34491 | BL6: 156.34491 | BM6: Sí | BN6: 3 | BO6: Rojo - Saturada | BP6: Sí | BQ6: 584.47039 | BR6: #N/A | BS6: #N/A | BT6: #N/A | BU6: #N/A | BV6: #N/A | BW6: #N/A | BX6: #N/A | BY6: #N/A | BZ6: #N/A | CA6: #N/A | CB6: #N/A | CC6: #N/A | CD6: #N/A | CE6: #N/A | CF6: #N/A | CG6: #N/A | CH6: #N/A | CI6: #N/A | CJ6: #N/A | CM6: =CL6-CK6 -> 0 | CP6: =CO6-CN6 -> 0 | CS6: =CQ6-CR6 -> 0 | CX6: =((CW6-CY6)/BT6)*100 -> #N/A | CZ6: =((CW6)/BT6)*100 -> #N/A | DA6: =DB6/(CY6+BT6) -> #N/A | DC6: =DD6/(CY6+BT6) -> #N/A
A7: Noreste | B7: Laredo | C7: Suc. Nuevo Laredo | D7: 105301 | E7: Noreste|Suc. Nuevo Laredo|105301 | F7: Activa | G7: Sí | H7: Sí | I7: 3 | J7: 40563.958 | K7: 13839.586 | L7: 54403.545 | M7: 2780293 | N7: 624714 | O7: 2155579 | P7: 0 | Q7: 6864.9177 | R7: 688.35454 | S7: 2836.8939 | T7: 464.31479 | U7: =IFERROR(INDEX('Rentabilidad datos'!$N$2:$N$61,MATCH($C7,'Rentabilidad datos'!$C$2:$C$61,0)),"") -> 3989.5633 | V7: =IFERROR(INDEX('Rentabilidad datos'!$O$2:$O$61,MATCH($C7,'Rentabilidad datos'!$C$2:$C$61,0)),"") -> 1329.8544 | W7: =IFERROR(INDEX('Rentabilidad datos'!$M$2:$M$61,MATCH($C7,'Rentabilidad datos'!$C$2:$C$61,0)),"") -> 2708.9427 | X7: =IFERROR(INDEX('Rentabilidad datos'!$P$2:$P$61,MATCH($C7,'Rentabilidad datos'!$C$2:$C$61,0)),"") -> 0.49091271 | Y7: C4 | Z7: 25.111111 | AA7: 1 | AB7: 1 | AC7: 0 | AD7: =_xlfn.XLOOKUP(Table1[[#This Row],[Ruta]],#REF!,#REF!) -> #REF! | AE7: =_xlfn.XLOOKUP(Table1[[#This Row],[Ruta]],#REF!,#REF!) -> #REF! | AF7: =_xlfn.XLOOKUP(Table1[[#This Row],[Ruta]],#REF!,#REF!) -> #REF! | AG7: =_xlfn.XLOOKUP(Table1[[#This Row],[Ruta]],#REF!,#REF!) -> #REF! | AH7: 0.22469358 | AI7: 0.77530642 | AJ7: 0 | AK7: 10170 | AL7: 6598 | AM7: 0.64877089 | AN7: 0.51668553 | AO7: 0 | AP7: 0 | AQ7: 0.64877089 | AR7: 2780291.7 | AS7: 0 | AT7: 0 | AU7: 0 | AV7: 0 | AW7: 490 | AX7: 421.38401 | AY7: 754.63815 | AZ7: 333.25414 | BA7: Sí | BB7: 772555.15 | BC7: 772555.15 | BD7: Sí | BE7: 25.111111 | BF7: 36 | BG7: No | BH7: 0.64877089 | BI7: 0.38460016 | BJ7: Sí | BK7: 134.32974 | BL7: 156.34491 | BM7: No | BN7: 1 | BO7: Verde - Con espacio | BP7: No | BQ7: 0 | BR7: #N/A | BS7: #N/A | BT7: #N/A | BU7: #N/A | BV7: #N/A | BW7: #N/A | BX7: #N/A | BY7: #N/A | BZ7: #N/A | CA7: #N/A | CB7: #N/A | CC7: #N/A | CD7: #N/A | CE7: #N/A | CF7: #N/A | CG7: #N/A | CH7: #N/A | CI7: #N/A | CJ7: #N/A | CM7: =CL7-CK7 -> 0 | CP7: =CO7-CN7 -> 0 | CS7: =CQ7-CR7 -> 0 | CX7: =((CW7-CY7)/BT7)*100 -> #N/A | CZ7: =((CW7)/BT7)*100 -> #N/A | DA7: =DB7/(CY7+BT7) -> #N/A | DC7: =DD7/(CY7+BT7) -> #N/A
A8: Noreste | B8: Laredo | C8: Suc. Nuevo Laredo | D8: 105302 | E8: Noreste|Suc. Nuevo Laredo|105302 | F8: Activa | G8: Sí | H8: Sí | I8: 3 | J8: 27946.722 | K8: 14840.407 | L8: 42787.129 | M8: 2616989 | N8: 414264 | O8: 2202725 | P8: 0 | Q8: 6260.7313 | R8: 688.35454 | S8: 2836.8939 | T8: 464.31479 | U8: =IFERROR(INDEX('Rentabilidad datos'!$N$2:$N$61,MATCH($C8,'Rentabilidad datos'!$C$2:$C$61,0)),"") -> 3989.5633 | V8: =IFERROR(INDEX('Rentabilidad datos'!$O$2:$O$61,MATCH($C8,'Rentabilidad datos'!$C$2:$C$61,0)),"") -> 1329.8544 | W8: =IFERROR(INDEX('Rentabilidad datos'!$M$2:$M$61,MATCH($C8,'Rentabilidad datos'!$C$2:$C$61,0)),"") -> 2708.9427 | X8: =IFERROR(INDEX('Rentabilidad datos'!$P$2:$P$61,MATCH($C8,'Rentabilidad datos'!$C$2:$C$61,0)),"") -> 0.49091271 | Y8: C4 | Z8: 41.992823 | AA8: 1 | AB8: 1 | AC8: 0 | AD8: =_xlfn.XLOOKUP(Table1[[#This Row],[Ruta]],#REF!,#REF!) -> #REF! | AE8: =_xlfn.XLOOKUP(Table1[[#This Row],[Ruta]],#REF!,#REF!) -> #REF! | AF8: =_xlfn.XLOOKUP(Table1[[#This Row],[Ruta]],#REF!,#REF!) -> #REF! | AG8: =_xlfn.XLOOKUP(Table1[[#This Row],[Ruta]],#REF!,#REF!) -> #REF! | AH8: 0.15829795 | AI8: 0.84170205 | AJ8: 0 | AK8: 17553 | AL8: 3690 | AM8: 0.21022048 | AN8: 0.51668553 | AO8: 5379.381 | AP8: 2689.6905 | AQ8: 0.363453 | AR8: 2616985.7 | AS8: 1907556 | AT8: 0.72891342 | AU8: 1340444.7 | AV8: 0.00609781 | AW8: 19 | AX8: 709.21021 | AY8: 754.63815 | AZ8: 45.427937 | BA8: Sí | BB8: 58896.707 | BC8: 1399341.4 | BD8: Sí | BE8: 41.992823 | BF8: 36 | BG8: Sí | BH8: 0.21022048 | BI8: 0.38460016 | BJ8: No | BK8: 102.36155 | BL8: 156.34491 | BM8: No | BN8: 1 | BO8: Verde - Con espacio | BP8: No | BQ8: 2642.6796 | BR8: #N/A | BS8: #N/A | BT8: #N/A | BU8: #N/A | BV8: #N/A | BW8: #N/A | BX8: #N/A | BY8: #N/A | BZ8: #N/A | CA8: #N/A | CB8: #N/A | CC8: #N/A | CD8: #N/A | CE8: #N/A | CF8: #N/A | CG8: #N/A | CH8: #N/A | CI8: #N/A | CJ8: #N/A | CM8: =CL8-CK8 -> 0 | CP8: =CO8-CN8 -> 0 | CS8: =CQ8-CR8 -> 0 | CX8: =((CW8-CY8)/BT8)*100 -> #N/A | CZ8: =((CW8)/BT8)*100 -> #N/A | DA8: =DB8/(CY8+BT8) -> #N/A | DC8: =DD8/(CY8+BT8) -> #N/A
A9: Noreste | B9: Matamoros | C9: Planta Matamoros | D9: 101340 | E9: Noreste|Planta Matamoros|101340 | F9: Activa | G9: Sí | H9: Sí | I9: 2 | J9: 35378.986 | K9: 11093.503 | L9: 46472.488 | M9: 2161457 | N9: 538003 | O9: 1623454 | P9: 0 | Q9: 4901.1325 | R9: 688.34136 | S9: 2977.2563 | T9: 315.23993 | U9: =IFERROR(INDEX('Rentabilidad datos'!$N$2:$N$61,MATCH($C9,'Rentabilidad datos'!$C$2:$C$61,0)),"") -> 3980.8376 | V9: =IFERROR(INDEX('Rentabilidad datos'!$O$2:$O$61,MATCH($C9,'Rentabilidad datos'!$C$2:$C$61,0)),"") -> 1990.4188 | W9: =IFERROR(INDEX('Rentabilidad datos'!$M$2:$M$61,MATCH($C9,'Rentabilidad datos'!$C$2:$C$61,0)),"") -> 2934.503 | X9: =IFERROR(INDEX('Rentabilidad datos'!$P$2:$P$61,MATCH($C9,'Rentabilidad datos'!$C$2:$C$61,0)),"") -> 0.67828139 | Y9: C3 | Z9: 30.244898 | AA9: 1 | AB9: 1 | AC9: 0 | AD9: =_xlfn.XLOOKUP(Table1[[#This Row],[Ruta]],#REF!,#REF!) -> #REF! | AE9: =_xlfn.XLOOKUP(Table1[[#This Row],[Ruta]],#REF!,#REF!) -> #REF! | AF9: =_xlfn.XLOOKUP(Table1[[#This Row],[Ruta]],#REF!,#REF!) -> #REF! | AG9: =_xlfn.XLOOKUP(Table1[[#This Row],[Ruta]],#REF!,#REF!) -> #REF! | AH9: 0.24890757 | AI9: 0.75109243 | AJ9: 0 | AK9: 13338 | AL9: 7421 | AM9: 0.55638027 | AN9: 0.50471056 | AO9: 0 | AP9: 0 | AQ9: 0.55638027 | AR9: 2161399.5 | AS9: 0 | AT9: 0 | AU9: 0 | AV9: 0 | AW9: 490 | AX9: 291.25447 | AY9: 1096.2918 | AZ9: 805.03735 | BA9: Sí | BB9: 2099037 | BC9: 2099037 | BD9: Sí | BE9: 30.244898 | BF9: 25.444444 | BG9: Sí | BH9: 0.55638027 | BI9: 0.34970145 | BJ9: Sí | BK9: 105.37979 | BL9: 174.22352 | BM9: No | BN9: 2 | BO9: Amarillo - Cerca del tope | BP9: No | BQ9: 0 | BR9: 2716 | BS9: 154754 | BT9: 47495 | BU9: 3.2583219 | BV9: 17.487113 | BW9: 1668 | BX9: 6941 | BY9: 8609 | BZ9: 0.18126119 | CA9: 0.035119486 | CB9: 0.1461417 | CC9: 0.21842299 | CD9: 0.042109696 | CE9: 0.033519318 | CF9: 0.52447626 | CG9: 0.00021054848 | CH9: 0 | CI9: 3.9611254 | CJ9: 0.83358104 | CK9: 168 | CL9: 370.78 | CM9: =CL9-CK9 -> 202.78 | CN9: 3.89 | CO9: 9.45 | CP9: =CO9-CN9 -> 5.56 | CQ9: 677.25 | CR9: 105.38 | CS9: =CQ9-CR9 -> 571.87 | CT9: No | CU9: 41.18 | CV9: 66 | CW9: 8609 | CX9: =((CW9-CY9)/BT9)*100 -> 17.699168 | CY9: 202.78 | CZ9: =((CW9)/BT9)*100 -> 18.126119 | DA9: =DB9/(CY9+BT9) -> 58.952016 | DB9: 2811880.3 | DC9: =DD9/(CY9+BT9) -> 1.0568639 | DD9: 50410.06 | DE9: 8609 | DF9: 17.866 | DG9: 123.4 | DH9: 18.126 | DI9: 115.262 | DJ9: 5488571 | DK9: 1.824 | DL9: 86870.6 | DM9: 8609 | DN9: 17.904 | DO9: 105.6 | DP9: 18.126 | DQ9: 112.011 | DR9: 5331784 | DS9: 1.767 | DT9: 84097.6
A10: Noreste | B10: Matamoros | C10: Planta Matamoros | D10: 101341 | E10: Noreste|Planta Matamoros|101341 | F10: Activa | G10: Sí | H10: Sí | I10: 2 | J10: 37876.367 | K10: 38956.206 | L10: 76832.573 | M10: 5354783 | N10: 557988 | O10: 4796795 | P10: 0 | Q10: 12142.49 | R10: 688.34136 | S10: 2977.2563 | T10: 315.23993 | U10: =IFERROR(INDEX('Rentabilidad datos'!$N$2:$N$61,MATCH($C10,'Rentabilidad datos'!$C$2:$C$61,0)),"") -> 3980.8376 | V10: =IFERROR(INDEX('Rentabilidad datos'!$O$2:$O$61,MATCH($C10,'Rentabilidad datos'!$C$2:$C$61,0)),"") -> 1990.4188 | W10: =IFERROR(INDEX('Rentabilidad datos'!$M$2:$M$61,MATCH($C10,'Rentabilidad datos'!$C$2:$C$61,0)),"") -> 2934.503 | X10: =IFERROR(INDEX('Rentabilidad datos'!$P$2:$P$61,MATCH($C10,'Rentabilidad datos'!$C$2:$C$61,0)),"") -> 0.67828139 | Y10: C3 | Z10: 25.444444 | AA10: 1 | AB10: 1 | AC10: 0 | AD10: =_xlfn.XLOOKUP(Table1[[#This Row],[Ruta]],#REF!,#REF!) -> #REF! | AE10: =_xlfn.XLOOKUP(Table1[[#This Row],[Ruta]],#REF!,#REF!) -> #REF! | AF10: =_xlfn.XLOOKUP(Table1[[#This Row],[Ruta]],#REF!,#REF!) -> #REF! | AG10: =_xlfn.XLOOKUP(Table1[[#This Row],[Ruta]],#REF!,#REF!) -> #REF! | AH10: 0.10420366 | AI10: 0.89579634 | AJ10: 0 | AK10: 11221 | AL10: 3924 | AM10: 0.34970145 | AN10: 0.50471056 | AO10: 1739.3572 | AP10: 869.67862 | AQ10: 0.42720601 | AR10: 5354838 | AS10: 1186796.1 | AT10: 0.22163064 | AU10: 833964.86 | AV10: 0.0037937851 | AW10: 69 | AX10: 1364.6376 | AY10: 1096.2918 | AZ10: 0 | BA10: No | BB10: 0 | BC10: 833964.86 | BD10: Sí | BE10: 25.444444 | BF10: 25.444444 | BG10: Sí | BH10: 0.34970145 | BI10: 0.34970145 | BJ10: Sí | BK10: 174.22352 | BL10: 174.22352 | BM10: Sí | BN10: 3 | BO10: Rojo - Saturada | BP10: Sí | BQ10: 1004.1185 | BR10: 3972 | BS10: 293716 | BT10: 85066 | BU10: 3.4528014 | BV10: 21.416415 | BW10: 1310 | BX10: 5532 | BY10: 6842 | BZ10: 0.080431665 | CA10: 0.015399807 | CB10: 0.065031858 | CC10: 0.22031129 | CD10: 0.08491054 | CE10: 0.036089625 | CF10: 0.57825688 | CG10: 0 | CH10: 0 | CI10: 4.4669 | CJ10: 0.45622302 | CK10: 149 | CL10: 347.64 | CM10: =CL10-CK10 -> 198.64 | CN10: 3.55 | CO10: 9.45 | CP10: =CO10-CN10 -> 5.9 | CQ10: 677.25 | CR10: 174.22 | CS10: =CQ10-CR10 -> 503.03 | CT10: No | CU10: 37.59 | CV10: 60 | CW10: 6842 | CX10: =((CW10-CY10)/BT10)*100 -> 7.8096537 | CY10: 198.64 | CZ10: =((CW10)/BT10)*100 -> 8.0431665 | DA10: =DB10/(CY10+BT10) -> 14.96277 | DB10: 1275795.2 | DC10: =DD10/(CY10+BT10) -> 0.44938336 | DD10: 38316.51 | DE10: 6842 | DF10: 7.899 | DG10: 122.7 | DH10: 8.043 | DI10: 20.724 | DJ10: 1765465 | DK10: 0.624 | DL10: 53134.6 | DM10: 6842 | DN10: 7.923 | DO10: 102.5 | DP10: 8.043 | DQ10: 19.251 | DR10: 1639556 | DS10: 0.58 | DT10: 49393.4
A11: Noreste | B11: Monclova | C11: Sucursal Monclova | D11: 206300 | E11: Noreste|Sucursal Monclova|206300 | F11: Activa | G11: Sí | H11: Sí | I11: 3 | J11: 201333.34 | K11: 5841.6235 | L11: 207174.96 | M11: 3983960 | N11: 3131217 | O11: 852743 | P11: 0 | Q11: 9075.0807 | R11: 1365.8094 | S11: 3238.6465 | T11: 415.65553 | U11: =IFERROR(INDEX('Rentabilidad datos'!$N$2:$N$61,MATCH($C11,'Rentabilidad datos'!$C$2:$C$61,0)),"") -> 5020.1114 | V11: =IFERROR(INDEX('Rentabilidad datos'!$O$2:$O$61,MATCH($C11,'Rentabilidad datos'!$C$2:$C$61,0)),"") -> 1673.3705 | W11: =IFERROR(INDEX('Rentabilidad datos'!$M$2:$M$61,MATCH($C11,'Rentabilidad datos'!$C$2:$C$61,0)),"") -> 2926.366 | X11: =IFERROR(INDEX('Rentabilidad datos'!$P$2:$P$61,MATCH($C11,'Rentabilidad datos'!$C$2:$C$61,0)),"") -> 0.57182542 | Y11: C3 | Z11: 26.476082 | AA11: 1 | AB11: 1 | AC11: 0 | AD11: =_xlfn.XLOOKUP(Table1[[#This Row],[Ruta]],#REF!,#REF!) -> #REF! | AE11: =_xlfn.XLOOKUP(Table1[[#This Row],[Ruta]],#REF!,#REF!) -> #REF! | AF11: =_xlfn.XLOOKUP(Table1[[#This Row],[Ruta]],#REF!,#REF!) -> #REF! | AG11: =_xlfn.XLOOKUP(Table1[[#This Row],[Ruta]],#REF!,#REF!) -> #REF! | AH11: 0.78595593 | AI11: 0.21404407 | AJ11: 0 | AK11: 11623 | AL11: 7614 | AM11: 0.65508044 | AN11: 0.70543489 | AO11: 585.26974 | AP11: 292.63487 | AQ11: 0.68025767 | AR11: 3983960.4 | AS11: 153118.69 | AT11: 0.038433789 | AU11: 107596.92 | AV11: 0.00048946857 | AW11: 389 | AX11: 523.24145 | AY11: 433.47414 | AZ11: 0 | BA11: No | BB11: 0 | BC11: 107596.92 | BD11: Sí | BE11: 26.476082 | BF11: 35.429545 | BG11: No | BH11: 0.65508044 | BI11: 0.75578934 | BJ11: No | BK11: 471.92474 | BL11: 393.27663 | BM11: Sí | BN11: 1 | BO11: Verde - Con espacio | BP11: No | BQ11: 4036.9159 | BR11: 1355 | BS11: 62940 | BT11: 19168 | BU11: 3.2835977 | BV11: 14.146125 | BW11: 2813 | BX11: 6425 | BY11: 9238 | BZ11: 0.48194908 | CA11: 0.14675501 | CB11: 0.33519407 | CC11: 0.11133139 | CD11: 0.014398998 | CE11: 0.023789649 | CF11: 0.36472245 | CG11: 0.0037562604 | CH11: 5.2170284e-05 | CI11: 3.6224976 | CJ11: 0.69907849 | CK11: 116 | CL11: 183.91 | CM11: =CL11-CK11 -> 67.91 | CN11: 2.33 | CO11: 9.45 | CP11: =CO11-CN11 -> 7.12 | CQ11: 846.56 | CR11: 471.92 | CS11: =CQ11-CR11 -> 374.64 | CT11: No | CU11: 55.75 | CV11: 70 | CW11: 9238 | CX11: =((CW11-CY11)/BT11)*100 -> 47.84062 | CY11: 67.91 | CZ11: =((CW11)/BT11)*100 -> 48.194908 | DA11: =DB11/(CY11+BT11) -> 74.466137 | DB11: 1432423.9 | DC11: =DD11/(CY11+BT11) -> 3.6825141 | DD11: 70836.51 | DE11: 9238 | DF11: 47.848 | DG11: 66.5 | DH11: 48.195 | DI11: 190.143 | DJ11: 3657308 | DK11: 9.564 | DL11: 183955.8 | DM11: 9238 | DN11: 47.871 | DO11: 62.2 | DP11: 48.195 | DQ11: 187.332 | DR11: 3602419 | DS11: 9.447 | DT11: 181661.1
A12: Noreste | B12: Monclova | C12: Sucursal Monclova | D12: 206301 | E12: Noreste|Sucursal Monclova|206301 | F12: Activa | G12: Sí | H12: Sí | I12: 3 | J12: 180853.68 | K12: 10231.389 | L12: 191085.07 | M12: 3675477 | N12: 2748420 | O12: 924835 | P12: 2222 | Q12: 8273.0898 | R12: 1365.8094 | S12: 3238.6465 | T12: 415.65553 | U12: =IFERROR(INDEX('Rentabilidad datos'!$N$2:$N$61,MATCH($C12,'Rentabilidad datos'!$C$2:$C$61,0)),"") -> 5020.1114 | V12: =IFERROR(INDEX('Rentabilidad datos'!$O$2:$O$61,MATCH($C12,'Rentabilidad datos'!$C$2:$C$61,0)),"") -> 1673.3705 | W12: =IFERROR(INDEX('Rentabilidad datos'!$M$2:$M$61,MATCH($C12,'Rentabilidad datos'!$C$2:$C$61,0)),"") -> 2926.366 | X12: =IFERROR(INDEX('Rentabilidad datos'!$P$2:$P$61,MATCH($C12,'Rentabilidad datos'!$C$2:$C$61,0)),"") -> 0.57182542 | Y12: C3 | Z12: 39.218468 | AA12: 1 | AB12: 1 | AC12: 0 | AD12: =_xlfn.XLOOKUP(Table1[[#This Row],[Ruta]],#REF!,#REF!) -> #REF! | AE12: =_xlfn.XLOOKUP(Table1[[#This Row],[Ruta]],#REF!,#REF!) -> #REF! | AF12: =_xlfn.XLOOKUP(Table1[[#This Row],[Ruta]],#REF!,#REF!) -> #REF! | AG12: =_xlfn.XLOOKUP(Table1[[#This Row],[Ruta]],#REF!,#REF!) -> #REF! | AH12: 0.74777233 | AI12: 0.25162312 | AJ12: 0.00060454738 | AK12: 17413 | AL12: 10706 | AM12: 0.614828 | AN12: 0.70543489 | AO12: 1577.7378 | AP12: 788.86888 | AQ12: 0.66013145 | AR12: 3673251.9 | AS12: 270662.63 | AT12: 0.073684745 | AU12: 190195.36 | AV12: 0.00086521669 | AW12: 317 | AX12: 343.10217 | AY12: 433.47414 | AZ12: 90.371968 | BA12: Sí | BB12: 339940.26 | BC12: 530135.62 | BD12: Sí | BE12: 39.218468 | BF12: 35.429545 | BG12: Sí | BH12: 0.614828 | BI12: 0.75578934 | BJ12: No | BK12: 430.37178 | BL12: 393.27663 | BM12: Sí | BN12: 2 | BO12: Amarillo - Cerca del tope | BP12: No | BQ12: 217.85402 | BR12: 2167 | BS12: 110786 | BT12: 31718 | BU12: 3.4928432 | BV12: 14.636825 | BW12: 197 | BX12: 3940 | BY12: 4137 | BZ12: 0.13043067 | CA12: 0.0062109843 | CB12: 0.12421969 | CC12: 0.054637745 | CD12: 0.074815562 | CE12: 0 | CF12: 0.7390756 | CG12: 0.0010404187 | CH12: 0 | CI12: 5.8400881 | CJ12: 0.59574314 | CK12: 161 | CL12: 229.27 | CM12: =CL12-CK12 -> 68.27 | CN12: 3.62 | CO12: 9.45 | CP12: =CO12-CN12 -> 5.83 | CQ12: 846.56 | CR12: 430.37 | CS12: =CQ12-CR12 -> 416.19 | CT12: No | CU12: 50.84 | CV12: 66 | CW12: 4137 | CX12: =((CW12-CY12)/BT12)*100 -> 12.827826 | CY12: 68.27 | CZ12: =((CW12)/BT12)*100 -> 13.043067 | DA12: =DB12/(CY12+BT12) -> 37.752934 | DB12: 1200025 | DC12: =DD12/(CY12+BT12) -> 1.6840837 | DD12: 53530.74 | DE12: 4137 | DF12: 12.84 | DG12: 64.5 | DH12: 13.043 | DI12: 127.221 | DJ12: 4043396 | DK12: 6.138 | DL12: 195089.6 | DM12: 4137 | DN12: 12.876 | DO12: 53.1 | DP12: 13.043 | DQ12: 121.27 | DR12: 3852866 | DS12: 5.872 | DT12: 186568.9
A13: Noreste | B13: Monclova | C13: Sucursal Monclova | D13: 206302 | E13: Noreste|Sucursal Monclova|206302 | F13: Activa | G13: Sí | H13: Sí | I13: 3 | J13: 161734.52 | K13: 11307.197 | L13: 173041.72 | M13: 4049556 | N13: 2506515 | O13: 1543041 | P13: 0 | Q13: 9203.5315 | R13: 1365.8094 | S13: 3238.6465 | T13: 415.65553 | U13: =IFERROR(INDEX('Rentabilidad datos'!$N$2:$N$61,MATCH($C13,'Rentabilidad datos'!$C$2:$C$61,0)),"") -> 5020.1114 | V13: =IFERROR(INDEX('Rentabilidad datos'!$O$2:$O$61,MATCH($C13,'Rentabilidad datos'!$C$2:$C$61,0)),"") -> 1673.3705 | W13: =IFERROR(INDEX('Rentabilidad datos'!$M$2:$M$61,MATCH($C13,'Rentabilidad datos'!$C$2:$C$61,0)),"") -> 2926.366 | X13: =IFERROR(INDEX('Rentabilidad datos'!$P$2:$P$61,MATCH($C13,'Rentabilidad datos'!$C$2:$C$61,0)),"") -> 0.57182542 | Y13: C3 | Z13: 35.429545 | AA13: 1 | AB13: 1 | AC13: 0 | AD13: =_xlfn.XLOOKUP(Table1[[#This Row],[Ruta]],#REF!,#REF!) -> #REF! | AE13: =_xlfn.XLOOKUP(Table1[[#This Row],[Ruta]],#REF!,#REF!) -> #REF! | AF13: =_xlfn.XLOOKUP(Table1[[#This Row],[Ruta]],#REF!,#REF!) -> #REF! | AG13: =_xlfn.XLOOKUP(Table1[[#This Row],[Ruta]],#REF!,#REF!) -> #REF! | AH13: 0.61896045 | AI13: 0.38103955 | AJ13: 0 | AK13: 15589 | AL13: 11782 | AM13: 0.75578934 | AN13: 0.70543489 | AO13: 0 | AP13: 0 | AQ13: 0.75578934 | AR13: 4049553.9 | AS13: 0 | AT13: 0 | AU13: 0 | AV13: 0 | AW13: 490 | AX13: 343.70683 | AY13: 433.47414 | AZ13: 89.767311 | BA13: Sí | BB13: 371602.7 | BC13: 371602.7 | BD13: Sí | BE13: 35.429545 | BF13: 35.429545 | BG13: Sí | BH13: 0.75578934 | BI13: 0.75578934 | BJ13: Sí | BK13: 393.27663 | BL13: 393.27663 | BM13: Sí | BN13: 3 | BO13: Rojo - Saturada | BP13: Sí | BQ13: 0 | BR13: 3002 | BS13: 161465 | BT13: 46741 | BU13: 3.4544618 | BV13: 15.569953 | BW13: 1070 | BX13: 5923 | BY13: 6993 | BZ13: 0.14961169 | CA13: 0.022892108 | CB13: 0.12671958 | CC13: 0.12325367 | CD13: 0.15241437 | CE13: 0.0039579812 | CF13: 0.57076229 | CG13: 0 | CH13: 0 | CI13: 5.3076518 | CJ13: 0.47688354 | CK13: 165 | CL13: 313.52 | CM13: =CL13-CK13 -> 148.52 | CN13: 3.54 | CO13: 9.45 | CP13: =CO13-CN13 -> 5.91 | CQ13: 846.56 | CR13: 393.28 | CS13: =CQ13-CR13 -> 453.28 | CT13: No | CU13: 47.44 | CV13: 102 | CW13: 6993 | CX13: =((CW13-CY13)/BT13)*100 -> 14.643418 | CY13: 148.52 | CZ13: =((CW13)/BT13)*100 -> 14.961169 | DA13: =DB13/(CY13+BT13) -> 81.489118 | DB13: 3820985.6 | DC13: =DD13/(CY13+BT13) -> 3.6734311 | DD13: 172245.42 | DE13: 6993 | DF13: 14.659 | DG13: 141.1 | DH13: 14.961 | DI13: 134.22 | DJ13: 6292506 | DK13: 6.075 | DL13: 284786.9 | DM13: 6993 | DN13: 14.707 | DO13: 118.9 | DP13: 14.961 | DQ13: 125.758 | DR13: 5892995 | DS13: 5.69 | DT13: 266613.7
A14: Noreste | B14: Monterrey | C14: Planta Guadalupe | D14: 701300 | E14: Noreste|Planta Guadalupe|701300 | F14: Activa | G14: Sí | H14: Sí | I14: 22 | J14: 121360.77 | K14: 55272.918 | L14: 176633.69 | M14: 8811435 | N14: 1852259 | O14: 6957834 | P14: 1342 | Q14: 19797.953 | R14: 6394.5727 | S14: 22541.519 | T14: 2275.8097 | U14: =IFERROR(INDEX('Rentabilidad datos'!$N$2:$N$61,MATCH($C14,'Rentabilidad datos'!$C$2:$C$61,0)),"") -> 31211.901 | V14: =IFERROR(INDEX('Rentabilidad datos'!$O$2:$O$61,MATCH($C14,'Rentabilidad datos'!$C$2:$C$61,0)),"") -> 1486.281 | W14: =IFERROR(INDEX('Rentabilidad datos'!$M$2:$M$61,MATCH($C14,'Rentabilidad datos'!$C$2:$C$61,0)),"") -> 3561.4148 | X14: =IFERROR(INDEX('Rentabilidad datos'!$P$2:$P$61,MATCH($C14,'Rentabilidad datos'!$C$2:$C$61,0)),"") -> 0.41732881 | Y14: C2 | Z14: 74.595506 | AA14: 1 | AB14: 0.99938455 | AC14: 0.00061545026 | AD14: =_xlfn.XLOOKUP(Table1[[#This Row],[Ruta]],#REF!,#REF!) -> #REF! | AE14: =_xlfn.XLOOKUP(Table1[[#This Row],[Ruta]],#REF!,#REF!) -> #REF! | AF14: =_xlfn.XLOOKUP(Table1[[#This Row],[Ruta]],#REF!,#REF!) -> #REF! | AG14: =_xlfn.XLOOKUP(Table1[[#This Row],[Ruta]],#REF!,#REF!) -> #REF! | AH14: 0.21021082 | AI14: 0.78963688 | AJ14: 0.00015230209 | AK14: 33195 | AL14: 27229 | AM14: 0.82027414 | AN14: 0.76950938 | AO14: 0 | AP14: 0 | AQ14: 0.82027414 | AR14: 8810089 | AS14: 0 | AT14: 0 | AU14: 0 | AV14: 0 | AW14: 490 | AX14: 323.55536 | AY14: 436.55824 | AZ14: 113.00288 | BA14: Sí | BB14: 1081092.5 | BC14: 1081092.5 | BD14: Sí | BE14: 74.595506 | BF14: 48.897321 | BG14: Sí | BH14: 0.82027414 | BI14: 0.79215712 | BJ14: Sí | BK14: 396.92963 | BL14: 326.54714 | BM14: Sí | BN14: 3 | BO14: Rojo - Saturada | BP14: Sí | BQ14: 0 | BR14: 128 | BS14: 8227 | BT14: 2823 | BU14: 2.9142756 | BV14: 22.054688 | BW14: 1555 | BX14: 1268 | BY14: 2823 | BZ14: 1 | CA14: 0.55083245 | CB14: 0.44916755 | CC14: 0 | CD14: 0 | CE14: 0 | CF14: 0 | CG14: 0 | CH14: 0 | CI14: 0.85085693 | CJ14: 1.7017139 | CK14: 417 | CL14: 739.88 | CM14: =CL14-CK14 -> 322.88 | CN14: 6.46 | CO14: 9.45 | CP14: =CO14-CN14 -> 2.99 | CQ14: 1269.84 | CR14: 396.93 | CS14: =CQ14-CR14 -> 872.91 | CT14: No | CU14: 69.26 | CV14: 474 | CW14: 2823 | CX14: =((CW14-CY14)/BT14)*100 -> 88.562522 | CY14: 322.88 | CZ14: =((CW14)/BT14)*100 -> 100 | DA14: =DB14/(CY14+BT14) -> 1051.2866 | DB14: 3307221.4 | DC14: =DD14/(CY14+BT14) -> 22.084663 | DD14: 69475.7 | DE14: 2823 | DF14: 91.563 | DG14: 238.2 | DH14: 100 | DI14: 2264.077 | DJ14: 6930746 | DK14: 47.362 | DL14: 144982.2 | DM14: 2823 | DN14: 93.052 | DO14: 196.1 | DP14: 100 | DQ14: 2184.689 | DR14: 6595900 | DS14: 45.668 | DT14: 137877.2
A15: Noreste | B15: Monterrey | C15: Planta Guadalupe | D15: 701301 | E15: Noreste|Planta Guadalupe|701301 | F15: Activa | G15: Sí | H15: Sí | I15: 22 | J15: 81082.126 | K15: 40142.275 | L15: 121224.4 | M15: 6501356 | N15: 1227962 | O15: 5273266 | P15: 128 | Q15: 14809.18 | R15: 6394.5727 | S15: 22541.519 | T15: 2275.8097 | U15: =IFERROR(INDEX('Rentabilidad datos'!$N$2:$N$61,MATCH($C15,'Rentabilidad datos'!$C$2:$C$61,0)),"") -> 31211.901 | V15: =IFERROR(INDEX('Rentabilidad datos'!$O$2:$O$61,MATCH($C15,'Rentabilidad datos'!$C$2:$C$61,0)),"") -> 1486.281 | W15: =IFERROR(INDEX('Rentabilidad datos'!$M$2:$M$61,MATCH($C15,'Rentabilidad datos'!$C$2:$C$61,0)),"") -> 3561.4148 | X15: =IFERROR(INDEX('Rentabilidad datos'!$P$2:$P$61,MATCH($C15,'Rentabilidad datos'!$C$2:$C$61,0)),"") -> 0.41732881 | Y15: C2 | Z15: 83.91344 | AA15: 1 | AB15: 0.99880271 | AC15: 0.0011972887 | AD15: =_xlfn.XLOOKUP(Table1[[#This Row],[Ruta]],#REF!,#REF!) -> #REF! | AE15: =_xlfn.XLOOKUP(Table1[[#This Row],[Ruta]],#REF!,#REF!) -> #REF! | AF15: =_xlfn.XLOOKUP(Table1[[#This Row],[Ruta]],#REF!,#REF!) -> #REF! | AG15: =_xlfn.XLOOKUP(Table1[[#This Row],[Ruta]],#REF!,#REF!) -> #REF! | AH15: 0.18887783 | AI15: 0.81110248 | AJ15: 1.96882e-05 | AK15: 36838 | AL15: 21521 | AM15: 0.58420653 | AN15: 0.76950938 | AO15: 6826.1867 | AP15: 3413.0933 | AQ15: 0.67685796 | AR15: 6501229.9 | AS15: 1031053.6 | AT15: 0.15859362 | AU15: 724524.15 | AV15: 0.0032959289 | AW15: 89 | AX15: 302.08772 | AY15: 436.55824 | AZ15: 134.47052 | BA15: Sí | BB15: 1016789.8 | BC15: 1741313.9 | BD15: Sí | BE15: 83.91344 | BF15: 48.897321 | BG15: Sí | BH15: 0.58420653 | BI15: 0.79215712 | BJ15: No | BK15: 276.13759 | BL15: 326.54714 | BM15: No | BN15: 1 | BO15: Verde - Con espacio | BP15: No | BQ15: 0 | BR15: 110 | BS15: 6160 | BT15: 1960 | BU15: 3.1428571 | BV15: 17.818182 | BW15: 1960 | BX15: 0 | BY15: 1960 | BZ15: 1 | CA15: 1 | CB15: 0 | CC15: 0 | CD15: 0 | CE15: 0 | CF15: 0 | CG15: 0 | CH15: 0 | CI15: 0.16233766 | CJ15: 0.64935065 | CK15: 375 | CL15: 515.32 | CM15: =CL15-CK15 -> 140.32 | CN15: 6.98 | CO15: 9.45 | CP15: =CO15-CN15 -> 2.47 | CQ15: 1269.84 | CR15: 276.14 | CS15: =CQ15-CR15 -> 993.7 | CT15: No | CU15: 73.81 | CV15: 401 | CW15: 1960 | CX15: =((CW15-CY15)/BT15)*100 -> 92.840816 | CY15: 140.32 | CZ15: =((CW15)/BT15)*100 -> 100 | DA15: =DB15/(CY15+BT15) -> 1238.9229 | DB15: 2602134.6 | DC15: =DD15/(CY15+BT15) -> 23.434015 | DD15: 49218.93 | DE15: 1960 | DF15: 93.944 | DG15: 118.7 | DH15: 100 | DI15: 3065.636 | DJ15: 6372502 | DK15: 57.899 | DL15: 120354.5 | DM15: 1960 | DN15: 95.013 | DO15: 97.7 | DP15: 100 | DQ15: 2989.292 | DR15: 6151196 | DS15: 56.451 | DT15: 116161
A16: Noreste | B16: Monterrey | C16: Planta Guadalupe | D16: 701302 | E16: Noreste|Planta Guadalupe|701302 | F16: Activa | G16: Sí | H16: Sí | I16: 22 | J16: 56273.862 | K16: 31872.574 | L16: 88146.437 | M16: 4786351 | N16: 813869 | O16: 3972482 | P16: 0 | Q16: 10706.109 | R16: 6394.5727 | S16: 22541.519 | T16: 2275.8097 | U16: =IFERROR(INDEX('Rentabilidad datos'!$N$2:$N$61,MATCH($C16,'Rentabilidad datos'!$C$2:$C$61,0)),"") -> 31211.901 | V16: =IFERROR(INDEX('Rentabilidad datos'!$O$2:$O$61,MATCH($C16,'Rentabilidad datos'!$C$2:$C$61,0)),"") -> 1486.281 | W16: =IFERROR(INDEX('Rentabilidad datos'!$M$2:$M$61,MATCH($C16,'Rentabilidad datos'!$C$2:$C$61,0)),"") -> 3561.4148 | X16: =IFERROR(INDEX('Rentabilidad datos'!$P$2:$P$61,MATCH($C16,'Rentabilidad datos'!$C$2:$C$61,0)),"") -> 0.41732881 | Y16: C2 | Z16: 75.371365 | AA16: 1 | AB16: 0.99933854 | AC16: 0.00066146423 | AD16: =_xlfn.XLOOKUP(Table1[[#This Row],[Ruta]],#REF!,#REF!) -> #REF! | AE16: =_xlfn.XLOOKUP(Table1[[#This Row],[Ruta]],#REF!,#REF!) -> #REF! | AF16: =_xlfn.XLOOKUP(Table1[[#This Row],[Ruta]],#REF!,#REF!) -> #REF! | AG16: =_xlfn.XLOOKUP(Table1[[#This Row],[Ruta]],#REF!,#REF!) -> #REF! | AH16: 0.17003956 | AI16: 0.82996044 | AJ16: 0 | AK16: 33691 | AL16: 16384 | AM16: 0.48630198 | AN16: 0.76950938 | AO16: 9541.5407 | AP16: 4770.7703 | AQ16: 0.62790568 | AR16: 4785630.6 | AS16: 1393502.5 | AT16: 0.29118471 | AU16: 979217.96 | AV16: 0.0044545552 | AW16: 49 | AX16: 292.09171 | AY16: 436.55824 | AZ16: 144.46653 | BA16: Sí | BB16: 831627.43 | BC16: 1810845.4 | BD16: Sí | BE16: 75.371365 | BF16: 48.897321 | BG16: Sí | BH16: 0.48630198 | BI16: 0.79215712 | BJ16: No | BK16: 197.19561 | BL16: 326.54714 | BM16: No | BN16: 1 | BO16: Verde - Con espacio | BP16: No | BQ16: 1188.3454 | BR16: 460 | BS16: 34849 | BT16: 11761 | BU16: 2.9630984 | BV16: 25.567391 | BW16: 44 | BX16: 8919 | BY16: 8963 | BZ16: 0.76209506 | CA16: 0.0037411785 | CB16: 0.75835388 | CC16: 0.084006462 | CD16: 0.07984015 | CE16: 0 | CF16: 0.074058328 | CG16: 0 | CH16: 0 | CI16: 1.4634566 | CJ16: 1.1765043 | CK16: 701 | CL16: 910.77 | CM16: =CL16-CK16 -> 209.77 | CN16: 8.72 | CO16: 9.45 | CP16: =CO16-CN16 -> 0.73 | CQ16: 634.92 | CR16: 197.2 | CS16: =CQ16-CR16 -> 437.72 | CT16: No | CU16: 92.23 | CV16: 819 | CW16: 8963 | CX16: =((CW16-CY16)/BT16)*100 -> 74.425899 | CY16: 209.77 | CZ16: =((CW16)/BT16)*100 -> 76.209506 | DA16: =DB16/(CY16+BT16) -> 286.79557 | DB16: 3433163.9 | DC16: =DD16/(CY16+BT16) -> 6.3716895 | DD16: 76274.03 | DE16: 8963 | DF16: 74.529 | DG16: 197.6 | DH16: 76.21 | DI16: 724.22 | DJ16: 8660693 | DK16: 16.396 | DL16: 196076.8 | DM16: 8963 | DN16: 74.675 | DO16: 180.4 | DP16: 76.21 | DQ16: 717.794 | DR16: 8571492 | DS16: 16.226 | DT16: 193756.2
A17: Noreste | B17: Monterrey | C17: Planta Guadalupe | D17: 701303 | E17: Noreste|Planta Guadalupe|701303 | F17: Activa | G17: Sí | H17: Sí | I17: 22 | J17: 96143.908 | K17: 49380.95 | L17: 145524.86 | M17: 7393780 | N17: 1369314 | O17: 6023284 | P17: 1182 | Q17: 16852.328 | R17: 6394.5727 | S17: 22541.519 | T17: 2275.8097 | U17: =IFERROR(INDEX('Rentabilidad datos'!$N$2:$N$61,MATCH($C17,'Rentabilidad datos'!$C$2:$C$61,0)),"") -> 31211.901 | V17: =IFERROR(INDEX('Rentabilidad datos'!$O$2:$O$61,MATCH($C17,'Rentabilidad datos'!$C$2:$C$61,0)),"") -> 1486.281 | W17: =IFERROR(INDEX('Rentabilidad datos'!$M$2:$M$61,MATCH($C17,'Rentabilidad datos'!$C$2:$C$61,0)),"") -> 3561.4148 | X17: =IFERROR(INDEX('Rentabilidad datos'!$P$2:$P$61,MATCH($C17,'Rentabilidad datos'!$C$2:$C$61,0)),"") -> 0.41732881 | Y17: C2 | Z17: 92.468182 | AA17: 1 | AB17: 0.98865127 | AC17: 0.011348728 | AD17: =_xlfn.XLOOKUP(Table1[[#This Row],[Ruta]],#REF!,#REF!) -> #REF! | AE17: =_xlfn.XLOOKUP(Table1[[#This Row],[Ruta]],#REF!,#REF!) -> #REF! | AF17: =_xlfn.XLOOKUP(Table1[[#This Row],[Ruta]],#REF!,#REF!) -> #REF! | AG17: =_xlfn.XLOOKUP(Table1[[#This Row],[Ruta]],#REF!,#REF!) -> #REF! | AH17: 0.1851981 | AI17: 0.81464204 | AJ17: 0.0001598641 | AK17: 40686 | AL17: 32196 | AM17: 0.79132871 | AN17: 0.76950938 | AO17: 0 | AP17: 0 | AQ17: 0.79132871 | AR17: 7415024.3 | AS17: 0 | AT17: 0 | AU17: 0 | AV17: 0 | AW17: 490 | AX17: 230.30887 | AY17: 436.55824 | AZ17: 206.24937 | BA17: Sí | BB17: 2333115.2 | BC17: 2333115.2 | BD17: Sí | BE17: 92.468182 | BF17: 48.897321 | BG17: Sí | BH17: 0.79132871 | BI17: 0.79215712 | BJ17: No | BK17: 330.73831 | BL17: 326.54714 | BM17: Sí | BN17: 2 | BO17: Amarillo - Cerca del tope | BP17: No | BQ17: 0 | BR17: 421 | BS17: 33528 | BT17: 10284 | BU17: 3.26021 | BV17: 24.427553 | BW17: 4048 | BX17: 4605 | BY17: 8653 | BZ17: 0.84140412 | CA17: 0.39362116 | CB17: 0.44778296 | CC17: 0 | CD17: 0.14420459 | CE17: 0 | CF17: 0.014391287 | CG17: 0 | CH17: 0 | CI17: 1.4018134 | CJ17: 0.62634216 | CK17: 568 | CL17: 1158.62 | CM17: =CL17-CK17 -> 590.62 | CN17: 7.1 | CO17: 9.45 | CP17: =CO17-CN17 -> 2.35 | CQ17: 1269.84 | CR17: 330.74 | CS17: =CQ17-CR17 -> 939.1 | CT17: No | CU17: 75.16 | CV17: 556 | CW17: 8653 | CX17: =((CW17-CY17)/BT17)*100 -> 78.397316 | CY17: 590.62 | CZ17: =((CW17)/BT17)*100 -> 84.140412 | DA17: =DB17/(CY17+BT17) -> 622.2247 | DB17: 6766457.2 | DC17: =DD17/(CY17+BT17) -> 13.256237 | DD17: 144156.54 | DE17: 8653 | DF17: 78.762 | DG17: 553.1 | DH17: 84.14 | DI17: 975.518 | DJ17: 10571806 | DK17: 20.796 | DL17: 225368.2 | DM17: 8653 | DN17: 78.933 | DO17: 535.6 | DP17: 84.14 | DQ17: 964.235 | DR17: 10432620 | DS17: 20.559 | DT17: 222440.5
A18: Noreste | B18: Monterrey | C18: Planta Guadalupe | D18: 701304 | E18: Noreste|Planta Guadalupe|701304 | F18: Activa | G18: Sí | H18: Sí | I18: 22 | J18: 89454.87 | K18: 33447.393 | L18: 122902.26 | M18: 5361383 | N18: 1275596 | O18: 4085689 | P18: 98 | Q18: 12167.089 | R18: 6394.5727 | S18: 22541.519 | T18: 2275.8097 | U18: =IFERROR(INDEX('Rentabilidad datos'!$N$2:$N$61,MATCH($C18,'Rentabilidad datos'!$C$2:$C$61,0)),"") -> 31211.901 | V18: =IFERROR(INDEX('Rentabilidad datos'!$O$2:$O$61,MATCH($C18,'Rentabilidad datos'!$C$2:$C$61,0)),"") -> 1486.281 | W18: =IFERROR(INDEX('Rentabilidad datos'!$M$2:$M$61,MATCH($C18,'Rentabilidad datos'!$C$2:$C$61,0)),"") -> 3561.4148 | X18: =IFERROR(INDEX('Rentabilidad datos'!$P$2:$P$61,MATCH($C18,'Rentabilidad datos'!$C$2:$C$61,0)),"") -> 0.41732881 | Y18: C2 | Z18: 56.29932 | AA18: 1 | AB18: 0.98568802 | AC18: 0.014311979 | AD18: =_xlfn.XLOOKUP(Table1[[#This Row],[Ruta]],#REF!,#REF!) -> #REF! | AE18: =_xlfn.XLOOKUP(Table1[[#This Row],[Ruta]],#REF!,#REF!) -> #REF! | AF18: =_xlfn.XLOOKUP(Table1[[#This Row],[Ruta]],#REF!,#REF!) -> #REF! | AG18: =_xlfn.XLOOKUP(Table1[[#This Row],[Ruta]],#REF!,#REF!) -> #REF! | AH18: 0.23792294 | AI18: 0.76205878 | AJ18: 1.8278866e-05 | AK18: 24828 | AL18: 15093 | AM18: 0.60790237 | AN18: 0.76950938 | AO18: 4012.379 | AP18: 2006.1895 | AQ18: 0.68870588 | AR18: 5365686 | AS18: 713216.92 | AT18: 0.13292185 | AU18: 501179.46 | AV18: 0.0022799128 | AW18: 147 | AX18: 355.50825 | AY18: 436.55824 | AZ18: 81.049992 | BA18: Sí | BB18: 429803.72 | BC18: 930983.18 | BD18: Sí | BE18: 56.29932 | BF18: 48.897321 | BG18: Sí | BH18: 0.60790237 | BI18: 0.79215712 | BJ18: No | BK18: 278.68994 | BL18: 326.54714 | BM18: No | BN18: 1 | BO18: Verde - Con espacio | BP18: No | BQ18: 3881.8703 | BR18: 438 | BS18: 39340 | BT18: 12028 | BU18: 3.2707017 | BV18: 27.461187 | BW18: 871 | BX18: 6721 | BY18: 7592 | BZ18: 0.63119388 | CA18: 0.072414366 | CB18: 0.55877951 | CC18: 0.35384104 | CD18: 0 | CE18: 0 | CF18: 0.014965081 | CG18: 0 | CH18: 0 | CI18: 2.4911032 | CJ18: 0.73716319 | CK18: 315 | CL18: 857.81 | CM18: =CL18-CK18 -> 542.81 | CN18: 6.28 | CO18: 9.45 | CP18: =CO18-CN18 -> 3.17 | CQ18: 634.92 | CR18: 278.69 | CS18: =CQ18-CR18 -> 356.23 | CT18: No | CU18: 71.8 | CV18: 316 | CW18: 7592 | CX18: =((CW18-CY18)/BT18)*100 -> 58.606501 | CY18: 542.81 | CZ18: =((CW18)/BT18)*100 -> 63.119388 | DA18: =DB18/(CY18+BT18) -> 303.11466 | DB18: 3810396.8 | DC18: =DD18/(CY18+BT18) -> 7.3932253 | DD18: 92938.83 | DE18: 7592 | DF18: 58.838 | DG18: 515 | DH18: 63.119 | DI18: 502.537 | DJ18: 6303323 | DK18: 12.383 | DL18: 155323.3 | DM18: 7592 | DN18: 58.964 | DO18: 499.8 | DP18: 63.119 | DQ18: 493.352 | DR18: 6180615 | DS18: 12.2 | DT18: 152835.9
A19: Noreste | B19: Monterrey | C19: Planta Guadalupe | D19: 701305 | E19: Noreste|Planta Guadalupe|701305 | F19: Activa | G19: Sí | H19: Sí | I19: 22 | J19: 91800.789 | K19: 32526.984 | L19: 124327.77 | M19: 5837867 | N19: 1405782 | O19: 4432020 | P19: 65 | Q19: 13237.005 | R19: 6394.5727 | S19: 22541.519 | T19: 2275.8097 | U19: =IFERROR(INDEX('Rentabilidad datos'!$N$2:$N$61,MATCH($C19,'Rentabilidad datos'!$C$2:$C$61,0)),"") -> 31211.901 | V19: =IFERROR(INDEX('Rentabilidad datos'!$O$2:$O$61,MATCH($C19,'Rentabilidad datos'!$C$2:$C$61,0)),"") -> 1486.281 | W19: =IFERROR(INDEX('Rentabilidad datos'!$M$2:$M$61,MATCH($C19,'Rentabilidad datos'!$C$2:$C$61,0)),"") -> 3561.4148 | X19: =IFERROR(INDEX('Rentabilidad datos'!$P$2:$P$61,MATCH($C19,'Rentabilidad datos'!$C$2:$C$61,0)),"") -> 0.41732881 | Y19: C2 | Z19: 69.360544 | AA19: 1 | AB19: 0.99208324 | AC19: 0.0079167614 | AD19: =_xlfn.XLOOKUP(Table1[[#This Row],[Ruta]],#REF!,#REF!) -> #REF! | AE19: =_xlfn.XLOOKUP(Table1[[#This Row],[Ruta]],#REF!,#REF!) -> #REF! | AF19: =_xlfn.XLOOKUP(Table1[[#This Row],[Ruta]],#REF!,#REF!) -> #REF! | AG19: =_xlfn.XLOOKUP(Table1[[#This Row],[Ruta]],#REF!,#REF!) -> #REF! | AH19: 0.24080405 | AI19: 0.75918482 | AJ19: 1.1134204e-05 | AK19: 30588 | AL19: 19260 | AM19: 0.62965869 | AN19: 0.76950938 | AO19: 4277.753 | AP19: 2138.8765 | AQ19: 0.69958404 | AR19: 5837519.4 | AS19: 648272.75 | AT19: 0.11105278 | AU19: 455543.01 | AV19: 0.0020723083 | AW19: 160 | AX19: 303.09031 | AY19: 436.55824 | AZ19: 133.46793 | BA19: Sí | BB19: 903181.1 | BC19: 1358724.1 | BD19: Sí | BE19: 69.360544 | BF19: 48.897321 | BG19: Sí | BH19: 0.62965869 | BI19: 0.79215712 | BJ19: No | BK19: 281.92239 | BL19: 326.54714 | BM19: No | BN19: 1 | BO19: Verde - Con espacio | BP19: No | BQ19: 0 | BR19: 164 | BS19: 9985 | BT19: 3234 | BU19: 3.0875077 | BV19: 19.719512 | BW19: 3234 | BX19: 0 | BY19: 3234 | BZ19: 1 | CA19: 1 | CB19: 0 | CC19: 0 | CD19: 0 | CE19: 0 | CF19: 0 | CG19: 0 | CH19: 0 | CI19: 0.70105158 | CJ19: 1.5022534 | CK19: 335 | CL19: 519.13 | CM19: =CL19-CK19 -> 184.13 | CN19: 12.17 | CO19: 9.45 | CP19: =CO19-CN19 -> -2.72 | CQ19: 1269.84 | CR19: 281.92 | CS19: =CQ19-CR19 -> 987.92 | CT19: Sí | CU19: 129 | CV19: 362 | CW19: 3234 | CX19: =((CW19-CY19)/BT19)*100 -> 94.306432 | CY19: 184.13 | CZ19: =((CW19)/BT19)*100 -> 100 | DA19: =DB19/(CY19+BT19) -> 678.8711 | DB19: 2320469.7 | DC19: =DD19/(CY19+BT19) -> 16.62227 | DD19: 56817.08 | DE19: 3234 | DF19: 95.94 | DG19: 131.3 | DH19: 100 | DI19: 1502.206 | DJ19: 5055393 | DK19: 33.723 | DL19: 113487.9 | DM19: 3234 | DN19: 96.187 | DO19: 123.3 | DP19: 100 | DQ19: 1490.843 | DR19: 5005229 | DS19: 33.326 | DT19: 111886.5
A20: Noreste | B20: Monterrey | C20: Planta Guadalupe | D20: 701306 | E20: Noreste|Planta Guadalupe|701306 | F20: Activa | G20: Sí | H20: Sí | I20: 22 | J20: 109613.57 | K20: 38136.486 | L20: 147750.05 | M20: 6477694 | N20: 1667637 | O20: 4810057 | P20: 0 | Q20: 14755.564 | R20: 6394.5727 | S20: 22541.519 | T20: 2275.8097 | U20: =IFERROR(INDEX('Rentabilidad datos'!$N$2:$N$61,MATCH($C20,'Rentabilidad datos'!$C$2:$C$61,0)),"") -> 31211.901 | V20: =IFERROR(INDEX('Rentabilidad datos'!$O$2:$O$61,MATCH($C20,'Rentabilidad datos'!$C$2:$C$61,0)),"") -> 1486.281 | W20: =IFERROR(INDEX('Rentabilidad datos'!$M$2:$M$61,MATCH($C20,'Rentabilidad datos'!$C$2:$C$61,0)),"") -> 3561.4148 | X20: =IFERROR(INDEX('Rentabilidad datos'!$P$2:$P$61,MATCH($C20,'Rentabilidad datos'!$C$2:$C$61,0)),"") -> 0.41732881 | Y20: C2 | Z20: 54.061503 | AA20: 1 | AB20: 0.99854315 | AC20: 0.0014568456 | AD20: =_xlfn.XLOOKUP(Table1[[#This Row],[Ruta]],#REF!,#REF!) -> #REF! | AE20: =_xlfn.XLOOKUP(Table1[[#This Row],[Ruta]],#REF!,#REF!) -> #REF! | AF20: =_xlfn.XLOOKUP(Table1[[#This Row],[Ruta]],#REF!,#REF!) -> #REF! | AG20: =_xlfn.XLOOKUP(Table1[[#This Row],[Ruta]],#REF!,#REF!) -> #REF! | AH20: 0.257443 | AI20: 0.742557 | AJ20: 0 | AK20: 23733 | AL20: 13813 | AM20: 0.5820166 | AN20: 0.76950938 | AO20: 4449.7662 | AP20: 2224.8831 | AQ20: 0.67576299 | AR20: 6477692.5 | AS20: 1043372.8 | AT20: 0.16107168 | AU20: 733180.89 | AV20: 0.0033353093 | AW20: 88 | AX20: 468.95623 | AY20: 436.55824 | AZ20: 0 | BA20: No | BB20: 0 | BC20: 733180.89 | BD20: Sí | BE20: 54.061503 | BF20: 48.897321 | BG20: Sí | BH20: 0.5820166 | BI20: 0.79215712 | BJ20: No | BK20: 336.56048 | BL20: 326.54714 | BM20: Sí | BN20: 2 | BO20: Amarillo - Cerca del tope | BP20: No | BQ20: 4216.501 | BR20: 198 | BS20: 14988 | BT20: 4599 | BU20: 3.2589693 | BV20: 23.227273 | BW20: 4599 | BX20: 0 | BY20: 4599 | BZ20: 1 | CA20: 1 | CB20: 0 | CC20: 0 | CD20: 0 | CE20: 0 | CF20: 0 | CG20: 0 | CH20: 0 | CI20: 0.60048038 | CJ20: 0.80064051 | CK20: 244 | CL20: 588.63 | CM20: =CL20-CK20 -> 344.63 | CN20: 6.4 | CO20: 9.45 | CP20: =CO20-CN20 -> 3.05 | CQ20: 1269.84 | CR20: 336.56 | CS20: =CQ20-CR20 -> 933.28 | CT20: No | CU20: 67.72 | CV20: 307 | CW20: 4599 | CX20: =((CW20-CY20)/BT20)*100 -> 92.506414 | CY20: 344.63 | CZ20: =((CW20)/BT20)*100 -> 100 | DA20: =DB20/(CY20+BT20) -> 506.93575 | DB20: 2506102.8 | DC20: =DD20/(CY20+BT20) -> 14.008526 | DD20: 69252.97 | DE20: 4599 | DF20: 92.737 | DG20: 334 | DH20: 100 | DI20: 1058.192 | DJ20: 5220090 | DK20: 28.906 | DL20: 142594.4 | DM20: 4599 | DN20: 92.764 | DO20: 332.8 | DP20: 100 | DQ20: 1056.429 | DR20: 5210059 | DS20: 28.862 | DT20: 142341.5
... A25: Noreste | B25: Monterrey | C25: Planta Guadalupe | D25: 701311 | E25: Noreste|Planta Guadalupe|701311 | F25: Activa | G25: Sí | H25: Sí | I25: 22 | J25: 77165.217 | K25: 44373.546 | L25: 121538.76 | M25: 6950472 | N25: 1176681 | O25: 5773791 | P25: 0 | Q25: 15760.708 | R25: 6394.5727 | S25: 22541.519 | T25: 2275.8097 | U25: =IFERROR(INDEX('Rentabilidad datos'!$N$2:$N$61,MATCH($C25,'Rentabilidad datos'!$C$2:$C$61,0)),"") -> 31211.901 | V25: =IFERROR(INDEX('Rentabilidad datos'!$O$2:$O$61,MATCH($C25,'Rentabilidad datos'!$C$2:$C$61,0)),"") -> 1486.281 | W25: =IFERROR(INDEX('Rentabilidad datos'!$M$2:$M$61,MATCH($C25,'Rentabilidad datos'!$C$2:$C$61,0)),"") -> 3561.4148 | X25: =IFERROR(INDEX('Rentabilidad datos'!$P$2:$P$61,MATCH($C25,'Rentabilidad datos'!$C$2:$C$61,0)),"") -> 0.41732881 | Y25: C2 | Z25: 71.004535 | AA25: 1 | AB25: 0.9974888 | AC25: 0.0025111964 | AD25: =_xlfn.XLOOKUP(Table1[[#This Row],[Ruta]],#REF!,#REF!) -> #REF! | AE25: =_xlfn.XLOOKUP(Table1[[#This Row],[Ruta]],#REF!,#REF!) -> #REF! | AF25: =_xlfn.XLOOKUP(Table1[[#This Row],[Ruta]],#REF!,#REF!) -> #REF! | AG25: =_xlfn.XLOOKUP(Table1[[#This Row],[Ruta]],#REF!,#REF!) -> #REF! | AH25: 0.16929512 | AI25: 0.83070488 | AJ25: 0 | AK25: 31313 | AL25: 23972 | AM25: 0.76556063 | AN25: 0.76950938 | AO25: 123.64735 | AP25: 61.823675 | AQ25: 0.76753501 | AR25: 6950472.3 | AS25: 17925.235 | AT25: 0.0025789953 | AU25: 12596.111 | AV25: 5.7300902e-05 | AW25: 469 | AX25: 289.94128 | AY25: 436.55824 | AZ25: 146.61697 | BA25: Sí | BB25: 1234895.3 | BC25: 1247491.4 | BD25: Sí | BE25: 71.004535 | BF25: 48.897321 | BG25: Sí | BH25: 0.76556063 | BI25: 0.79215712 | BJ25: No | BK25: 275.5981 | BL25: 326.54714 | BM25: No | BN25: 1 | BO25: Verde - Con espacio | BP25: No | BQ25: 0 | BR25: 388 | BS25: 28328 | BT25: 9433 | BU25: 3.0030743 | BV25: 24.311856 | BW25: 1872 | BX25: 4234 | BY25: 6106 | BZ25: 0.64730202 | CA25: 0.19845224 | CB25: 0.44884978 | CC25: 0 | CD25: 0.044100498 | CE25: 0 | CF25: 0.30859748 | CG25: 0 | CH25: 0 | CI25: 1.6591358 | CJ25: 1.0590229 | CK25: 359 | CL25: 638.44 | CM25: =CL25-CK25 -> 279.44 | CN25: 5.62 | CO25: 9.45 | CP25: =CO25-CN25 -> 3.83 | CQ25: 1269.84 | CR25: 275.6 | CS25: =CQ25-CR25 -> 994.24 | CT25: No | CU25: 59.52 | CV25: 433 | CW25: 5654 | CX25: =((CW25-CY25)/BT25)*100 -> 56.976148 | CY25: 279.44 | CZ25: =((CW25)/BT25)*100 -> 59.938514 | DA25: =DB25/(CY25+BT25) -> 275.02458 | DB25: 2671159.7 | DC25: =DD25/(CY25+BT25) -> 6.1511484 | DD25: 59742.66 | DE25: 5654 | DF25: 57.431 | DG25: 236.5 | DH25: 59.939 | DI25: 676.285 | DJ25: 6539336 | DK25: 14.39 | DL25: 139148.2 | DM25: 5654 | DN25: 57.654 | DO25: 215.5 | DP25: 59.939 | DQ25: 661.377 | DR25: 6381322 | DS25: 14.116 | DT25: 136203.4
A26: Noreste | B26: Monterrey | C26: Planta Guadalupe | D26: 701312 | E26: Noreste|Planta Guadalupe|701312 | F26: Activa | G26: Sí | H26: Sí | I26: 22 | J26: 58323.899 | K26: 23824.266 | L26: 82148.165 | M26: 3708488 | N26: 858124 | O26: 2850243 | P26: 121 | Q26: 9409.7782 | R26: 6394.5727 | S26: 22541.519 | T26: 2275.8097 | U26: =IFERROR(INDEX('Rentabilidad datos'!$N$2:$N$61,MATCH($C26,'Rentabilidad datos'!$C$2:$C$61,0)),"") -> 31211.901 | V26: =IFERROR(INDEX('Rentabilidad datos'!$O$2:$O$61,MATCH($C26,'Rentabilidad datos'!$C$2:$C$61,0)),"") -> 1486.281 | W26: =IFERROR(INDEX('Rentabilidad datos'!$M$2:$M$61,MATCH($C26,'Rentabilidad datos'!$C$2:$C$61,0)),"") -> 3561.4148 | X26: =IFERROR(INDEX('Rentabilidad datos'!$P$2:$P$61,MATCH($C26,'Rentabilidad datos'!$C$2:$C$61,0)),"") -> 0.41732881 | Y26: C2 | Z26: 55.694215 | AA26: 1 | AB26: 0.99979695 | AC26: 0.00020304771 | AD26: =_xlfn.XLOOKUP(Table1[[#This Row],[Ruta]],#REF!,#REF!) -> #REF! | AE26: =_xlfn.XLOOKUP(Table1[[#This Row],[Ruta]],#REF!,#REF!) -> #REF! | AF26: =_xlfn.XLOOKUP(Table1[[#This Row],[Ruta]],#REF!,#REF!) -> #REF! | AG26: =_xlfn.XLOOKUP(Table1[[#This Row],[Ruta]],#REF!,#REF!) -> #REF! | AH26: 0.23139457 | AI26: 0.7685728 | AJ26: 3.2627853e-05 | AK26: 13478 | AL26: 16266 | AM26: 0.7544888 | AN26: 0.76950938 | AO26: 202.44748 | AP26: 101.22374 | AQ26: 1.2143659 | AR26: 3707452.6 | AS26: 23071.574 | AT26: 0.006223026 | AU26: 16212.457 | AV26: 7.3752003e-05 | AW26: 463 | AX26: 227.92651 | AY26: 436.55824 | AZ26: 208.63173 | BA26: Sí | BB26: 1192347.3 | BC26: 1208559.7 | BD26: Sí | BE26: 55.694215 | BF26: 48.897321 | BG26: Sí | BH26: 0.7544888 | BI26: 0.79215712 | BJ26: No | BK26: 208.49788 | BL26: 326.54714 | BM26: No | BN26: 1 | BO26: Verde - Con espacio | BP26: No | BQ26: 0 | BR26: #N/A | BS26: #N/A | BT26: #N/A | BU26: #N/A | BV26: #N/A | BW26: #N/A | BX26: #N/A | BY26: #N/A | BZ26: #N/A | CA26: #N/A | CB26: #N/A | CC26: #N/A | CD26: #N/A | CE26: #N/A | CF26: #N/A | CG26: #N/A | CH26: #N/A | CI26: #N/A | CJ26: #N/A | CM26: =CL26-CK26 -> 0 | CP26: =CO26-CN26 -> 0 | CS26: =CQ26-CR26 -> 0 | CX26: =((CW26-CY26)/BT26)*100 -> #N/A | CZ26: =((CW26)/BT26)*100 -> #N/A | DA26: =DB26/(CY26+BT26) -> #N/A | DC26: =DD26/(CY26+BT26) -> #N/A
A27: Noreste | B27: Monterrey | C27: Planta Guadalupe | D27: 701313 | E27: Noreste|Planta Guadalupe|701313 | F27: Activa | G27: Sí | H27: Sí | I27: 22 | J27: 69687.162 | K27: 13658.734 | L27: 83345.896 | M27: 3073739 | N27: 1071382 | O27: 2002357 | P27: 0 | Q27: 7584.5374 | R27: 6394.5727 | S27: 22541.519 | T27: 2275.8097 | U27: =IFERROR(INDEX('Rentabilidad datos'!$N$2:$N$61,MATCH($C27,'Rentabilidad datos'!$C$2:$C$61,0)),"") -> 31211.901 | V27: =IFERROR(INDEX('Rentabilidad datos'!$O$2:$O$61,MATCH($C27,'Rentabilidad datos'!$C$2:$C$61,0)),"") -> 1486.281 | W27: =IFERROR(INDEX('Rentabilidad datos'!$M$2:$M$61,MATCH($C27,'Rentabilidad datos'!$C$2:$C$61,0)),"") -> 3561.4148 | X27: =IFERROR(INDEX('Rentabilidad datos'!$P$2:$P$61,MATCH($C27,'Rentabilidad datos'!$C$2:$C$61,0)),"") -> 0.41732881 | Y27: C2 | Z27: 30.527197 | AA27: 1 | AB27: 0.99994632 | AC27: 5.368055e-05 | AD27: =_xlfn.XLOOKUP(Table1[[#This Row],[Ruta]],#REF!,#REF!) -> #REF! | AE27: =_xlfn.XLOOKUP(Table1[[#This Row],[Ruta]],#REF!,#REF!) -> #REF! | AF27: =_xlfn.XLOOKUP(Table1[[#This Row],[Ruta]],#REF!,#REF!) -> #REF! | AG27: =_xlfn.XLOOKUP(Table1[[#This Row],[Ruta]],#REF!,#REF!) -> #REF! | AH27: 0.34855985 | AI27: 0.65144015 | AJ27: 0 | AK27: 7296 | AL27: 7932 | AM27: 0.81154057 | AN27: 0.76950938 | AO27: 0 | AP27: 0 | AQ27: 1.0871711 | AR27: 3071737.6 | AS27: 0 | AT27: 0 | AU27: 0 | AV27: 0 | AW27: 490 | AX27: 387.25891 | AY27: 436.55824 | AZ27: 49.299337 | BA27: Sí | BB27: 137393.26 | BC27: 137393.26 | BD27: Sí | BE27: 30.527197 | BF27: 48.897321 | BG27: No | BH27: 0.81154057 | BI27: 0.79215712 | BJ27: Sí | BK27: 205.79234 | BL27: 326.54714 | BM27: No | BN27: 1 | BO27: Verde - Con espacio | BP27: No | BQ27: 3735.4002 | BR27: 123 | BS27: 2953 | BT27: 863 | BU27: 3.4217845 | BV27: 7.0162602 | BW27: 498 | BX27: 0 | BY27: 498 | BZ27: 0.57705678 | CA27: 0.57705678 | CB27: 0 | CC27: 0 | CD27: 0 | CE27: 0 | CF27: 0.42294322 | CG27: 0 | CH27: 0 | CI27: 3.0477481 | CJ27: 2.031832 | CK27: 65 | CL27: 182.27 | CM27: =CL27-CK27 -> 117.27 | CN27: 3.36 | CO27: 9.45 | CP27: =CO27-CN27 -> 6.09 | CQ27: 634.92 | CR27: 205.79 | CS27: =CQ27-CR27 -> 429.13 | CT27: No | CU27: 37.5 | CV27: 53 | CW27: 498 | CX27: =((CW27-CY27)/BT27)*100 -> 44.117034 | CY27: 117.27 | CZ27: =((CW27)/BT27)*100 -> 57.705678 | DA27: =DB27/(CY27+BT27) -> 748.09391 | DB27: 733334.02 | DC27: =DD27/(CY27+BT27) -> 20.762892 | DD27: 20353.24 | DE27: 498 | DF27: 47.869 | DG27: 84.9 | DH27: 57.706 | DI27: 1404.572 | DJ27: 1331383 | DK27: 39.412 | DL27: 37358.8 | DM27: 498 | DN27: 49.054 | DO27: 74.7 | DP27: 57.706 | DQ27: 1360.667 | DR27: 1275844 | DS27: 38.224 | DT27: 35841.3
A28: Noreste | B28: Monterrey | C28: Planta Guadalupe | D28: 701314 | E28: Noreste|Planta Guadalupe|701314 | F28: Activa | G28: Sí | H28: Sí | I28: 22 | J28: 82040.218 | K28: 31899.304 | L28: 113939.52 | M28: 4769085 | N28: 1175733 | O28: 3591357 | P28: 1995 | Q28: 10895.62 | R28: 6394.5727 | S28: 22541.519 | T28: 2275.8097 | U28: =IFERROR(INDEX('Rentabilidad datos'!$N$2:$N$61,MATCH($C28,'Rentabilidad datos'!$C$2:$C$61,0)),"") -> 31211.901 | V28: =IFERROR(INDEX('Rentabilidad datos'!$O$2:$O$61,MATCH($C28,'Rentabilidad datos'!$C$2:$C$61,0)),"") -> 1486.281 | W28: =IFERROR(INDEX('Rentabilidad datos'!$M$2:$M$61,MATCH($C28,'Rentabilidad datos'!$C$2:$C$61,0)),"") -> 3561.4148 | X28: =IFERROR(INDEX('Rentabilidad datos'!$P$2:$P$61,MATCH($C28,'Rentabilidad datos'!$C$2:$C$61,0)),"") -> 0.41732881 | Y28: C2 | Z28: 85.111617 | AA28: 1 | AB28: 0.98517766 | AC28: 0.01482234 | AD28: =_xlfn.XLOOKUP(Table1[[#This Row],[Ruta]],#REF!,#REF!) -> #REF! | AE28: =_xlfn.XLOOKUP(Table1[[#This Row],[Ruta]],#REF!,#REF!) -> #REF! | AF28: =_xlfn.XLOOKUP(Table1[[#This Row],[Ruta]],#REF!,#REF!) -> #REF! | AG28: =_xlfn.XLOOKUP(Table1[[#This Row],[Ruta]],#REF!,#REF!) -> #REF! | AH28: 0.2465322 | AI28: 0.75304948 | AJ28: 0.00041831924 | AK28: 37364 | AL28: 7608 | AM28: 0.20361846 | AN28: 0.76950938 | AO28: 21143.949 | AP28: 10571.974 | AQ28: 0.48656392 | AR28: 4783177.1 | AS28: 6646638.4 | AT28: 1.3895865 | AU28: 4670610.8 | AV28: 0.02124705 | AW28: 3 | AX28: 628.70361 | AY28: 436.55824 | AZ28: 0 | BA28: No | BB28: 0 | BC28: 4670610.8 | BD28: Sí | BE28: 85.111617 | BF28: 48.897321 | BG28: Sí | BH28: 0.20361846 | BI28: 0.79215712 | BJ28: No | BK28: 259.54333 | BL28: 326.54714 | BM28: No | BN28: 1 | BO28: Verde - Con espacio | BP28: No | BQ28: 10850.246 | BR28: 4212 | BS28: 369319 | BT28: 102433 | BU28: 3.6054689 | BV28: 24.319326 | BW28: 2541 | BX28: 26445 | BY28: 28986 | BZ28: 0.28297521 | CA28: 0.024806459 | CB28: 0.25816875 | CC28: 0.25385374 | CD28: 0.11260043 | CE28: 0 | CF28: 0.3503656 | CG28: 0.00020501206 | CH28: 0 | CI28: 3.1219623 | CJ28: 0.50904503 | CK28: 418 | CL28: 1298.53 | CM28: =CL28-CK28 -> 880.53 | CN28: 8.11 | CO28: 9.45 | CP28: =CO28-CN28 -> 1.34 | CQ28: 1269.84 | CR28: 259.54 | CS28: =CQ28-CR28 -> 1010.3 | CT28: No | CU28: 85.79 | CV28: 309 | CW28: 16143 | CX28: =((CW28-CY28)/BT28)*100 -> 14.899954 | CY28: 880.53 | CZ28: =((CW28)/BT28)*100 -> 15.75957 | DA28: =DB28/(CY28+BT28) -> 48.516436 | DB28: 5012404.3 | DC28: =DD28/(CY28+BT28) -> 1.3985579 | DD28: 144489.95 | DE28: 16143 | DF28: 14.9 | DG28: 880.5 | DH28: 15.76 | DI28: 262.36 | DJ28: 27105366 | DK28: 5.576 | DL28: 576054.9 | DM28: 16143 | DN28: 14.9 | DO28: 880.5 | DP28: 15.76 | DQ28: 262.36 | DR28: 27105366 | DS28: 5.576 | DT28: 576054.9
A29: Noreste | B29: Monterrey | C29: Planta Guadalupe | D29: 701315 | E29: Noreste|Planta Guadalupe|701315 | F29: Activa | G29: Sí | H29: Sí | I29: 22 | J29: 63927.897 | K29: 26359.475 | L29: 90287.372 | M29: 4191798 | N29: 936776 | O29: 3254479 | P29: 543 | Q29: 9390.1489 | R29: 6394.5727 | S29: 22541.519 | T29: 2275.8097 | U29: =IFERROR(INDEX('Rentabilidad datos'!$N$2:$N$61,MATCH($C29,'Rentabilidad datos'!$C$2:$C$61,0)),"") -> 31211.901 | V29: =IFERROR(INDEX('Rentabilidad datos'!$O$2:$O$61,MATCH($C29,'Rentabilidad datos'!$C$2:$C$61,0)),"") -> 1486.281 | W29: =IFERROR(INDEX('Rentabilidad datos'!$M$2:$M$61,MATCH($C29,'Rentabilidad datos'!$C$2:$C$61,0)),"") -> 3561.4148 | X29: =IFERROR(INDEX('Rentabilidad datos'!$P$2:$P$61,MATCH($C29,'Rentabilidad datos'!$C$2:$C$61,0)),"") -> 0.41732881 | Y29: C2 | Z29: 97.181208 | AA29: 1 | AB29: 0.98435135 | AC29: 0.015648655 | AD29: =_xlfn.XLOOKUP(Table1[[#This Row],[Ruta]],#REF!,#REF!) -> #REF! | AE29: =_xlfn.XLOOKUP(Table1[[#This Row],[Ruta]],#REF!,#REF!) -> #REF! | AF29: =_xlfn.XLOOKUP(Table1[[#This Row],[Ruta]],#REF!,#REF!) -> #REF! | AG29: =_xlfn.XLOOKUP(Table1[[#This Row],[Ruta]],#REF!,#REF!) -> #REF! | AH29: 0.22347833 | AI29: 0.77639214 | AJ29: 0.00012953868 | AK29: 43440 | AL29: 12630 | AM29: 0.29074586 | AN29: 0.76950938 | AO29: 20797.488 | AP29: 10398.744 | AQ29: 0.53012762 | AR29: 4197396.6 | AS29: 3455871.1 | AT29: 0.8233368 | AU29: 2428449.9 | AV29: 0.011047249 | AW29: 5 | AX29: 332.33544 | AY29: 436.55824 | AZ29: 104.22281 | BA29: Sí | BB29: 462495.75 | BC29: 2890945.7 | BD29: Sí | BE29: 97.181208 | BF29: 48.897321 | BG29: Sí | BH29: 0.29074586 | BI29: 0.79215712 | BJ29: No | BK29: 201.98517 | BL29: 326.54714 | BM29: No | BN29: 1 | BO29: Verde - Con espacio | BP29: No | BQ29: 8402.9563 | BR29: 2918 | BS29: 244003 | BT29: 67766 | BU29: 3.60067 | BV29: 23.223441 | BW29: 4058 | BX29: 17003 | BY29: 21061 | BZ29: 0.31079007 | CA29: 0.059882537 | CB29: 0.25090753 | CC29: 0.39651152 | CD29: 0.066331199 | CE29: 0 | CF29: 0.2263672 | CG29: 0 | CH29: 0 | CI29: 2.8606206 | CJ29: 0.54917358 | CK29: 556 | CL29: 1651.65 | CM29: =CL29-CK29 -> 1095.65 | CN29: 9.3 | CO29: 9.45 | CP29: =CO29-CN29 -> 0.15 | CQ29: 1269.84 | CR29: 201.99 | CS29: =CQ29-CR29 -> 1067.85 | CT29: No | CU29: 98.36 | CV29: 466 | CW29: 21060 | CX29: =((CW29-CY29)/BT29)*100 -> 29.460718 | CY29: 1095.65 | CZ29: =((CW29)/BT29)*100 -> 31.077532 | DA29: =DB29/(CY29+BT29) -> 105.39475 | DB29: 7257656.6 | DC29: =DD29/(CY29+BT29) -> 2.9512467 | DD29: 203227.72 | DE29: 21060 | DF29: 29.461 | DG29: 1095.7 | DH29: 31.078 | DI29: 148.563 | DJ29: 10230287 | DK29: 4.242 | DL29: 292130.7 | DM29: 21060 | DN29: 29.461 | DO29: 1095.7 | DP29: 31.078 | DQ29: 148.563 | DR29: 10230287 | DS29: 4.242 | DT29: 292130.7
A30: Noreste | B30: Monterrey | C30: Planta Guadalupe | D30: 701316 | E30: Noreste|Planta Guadalupe|701316 | F30: Activa | G30: Sí | H30: Sí | I30: 22 | J30: 40056.733 | K30: 7424.2726 | L30: 47481.005 | M30: 1365956 | N30: 596133 | O30: 769702 | P30: 121 | Q30: 3830.1244 | R30: 6394.5727 | S30: 22541.519 | T30: 2275.8097 | U30: =IFERROR(INDEX('Rentabilidad datos'!$N$2:$N$61,MATCH($C30,'Rentabilidad datos'!$C$2:$C$61,0)),"") -> 31211.901 | V30: =IFERROR(INDEX('Rentabilidad datos'!$O$2:$O$61,MATCH($C30,'Rentabilidad datos'!$C$2:$C$61,0)),"") -> 1486.281 | W30: =IFERROR(INDEX('Rentabilidad datos'!$M$2:$M$61,MATCH($C30,'Rentabilidad datos'!$C$2:$C$61,0)),"") -> 3561.4148 | X30: =IFERROR(INDEX('Rentabilidad datos'!$P$2:$P$61,MATCH($C30,'Rentabilidad datos'!$C$2:$C$61,0)),"") -> 0.41732881 | Y30: C2 | Z30: 85.639594 | AA30: 1 | AB30: 0.9970819 | AC30: 0.0029181028 | AD30: =_xlfn.XLOOKUP(Table1[[#This Row],[Ruta]],#REF!,#REF!) -> #REF! | AE30: =_xlfn.XLOOKUP(Table1[[#This Row],[Ruta]],#REF!,#REF!) -> #REF! | AF30: =_xlfn.XLOOKUP(Table1[[#This Row],[Ruta]],#REF!,#REF!) -> #REF! | AG30: =_xlfn.XLOOKUP(Table1[[#This Row],[Ruta]],#REF!,#REF!) -> #REF! | AH30: 0.43642182 | AI30: 0.5634896 | AJ30: 8.8582648e-05 | AK30: 16871 | AL30: 3993 | AM30: 0.20058088 | AN30: 0.76950938 | AO30: 9598.3928 | AP30: 4799.1964 | AQ30: 0.52114258 | AR30: 1359694.1 | AS30: 1634219.7 | AT30: 1.2019024 | AU30: 1148370.6 | AV30: 0.0052240466 | AW30: 29 | AX30: 340.51945 | AY30: 436.55824 | AZ30: 96.038797 | BA30: Sí | BB30: 134737.24 | BC30: 1283107.8 | BD30: Sí | BE30: 85.639594 | BF30: 48.897321 | BG30: Sí | BH30: 0.20058088 | BI30: 0.79215712 | BJ30: No | BK30: 133.74931 | BL30: 326.54714 | BM30: No | BN30: 1 | BO30: Verde - Con espacio | BP30: No | BQ30: 4427.9531 | BR30: 3007 | BS30: 270398 | BT30: 75874 | BU30: 3.5637768 | BV30: 25.232458 | BW30: 575 | BX30: 10466 | BY30: 11041 | BZ30: 0.14551757 | CA30: 0.0075783536 | CB30: 0.13793922 | CC30: 0.24897857 | CD30: 0.16055566 | CE30: 0.059480191 | CF30: 0.38545483 | CG30: 0 | CH30: 1.3179745e-05 | CI30: 3.3986938 | CJ30: 0.43269551 | CK30: 497 | CL30: 650.52 | CM30: =CL30-CK30 -> 153.52 | CN30: 14.63 | CO30: 9.45 | CP30: =CO30-CN30 -> -5.18 | CQ30: 846.56 | CR30: 133.75 | CS30: =CQ30-CR30 -> 712.81 | CT30: Sí | CU30: 154.82 | CV30: 150 | CW30: 3009 | CX30: =((CW30-CY30)/BT30)*100 -> 3.7634499 | CY30: 153.52 | CZ30: =((CW30)/BT30)*100 -> 3.9657854 | DA30: =DB30/(CY30+BT30) -> 22.872083 | DB30: 1738907.8 | DC30: =DD30/(CY30+BT30) -> 0.82730622 | DD30: 62898.04 | DE30: 3009 | DF30: 3.77 | DG30: 148.3 | DH30: 3.966 | DI30: 35.95 | DJ30: 2733014 | DK30: 1.323 | DL30: 100550.1 | DM30: 3009 | DN30: 3.778 | DO30: 142.1 | DP30: 3.966 | DQ30: 35.694 | DR30: 2713303 | DS30: 1.311 | DT30: 99674.5
A31: Noreste | B31: Monterrey | C31: Planta Guadalupe | D31: 701317 | E31: Noreste|Planta Guadalupe|701317 | F31: Activa | G31: Sí | H31: Sí | I31: 22 | J31: 50669.724 | K31: 30029.117 | L31: 80698.841 | M31: 4476256 | N31: 740668 | O31: 3735251 | P31: 337 | Q31: 10119.526 | R31: 6394.5727 | S31: 22541.519 | T31: 2275.8097 | U31: =IFERROR(INDEX('Rentabilidad datos'!$N$2:$N$61,MATCH($C31,'Rentabilidad datos'!$C$2:$C$61,0)),"") -> 31211.901 | V31: =IFERROR(INDEX('Rentabilidad datos'!$O$2:$O$61,MATCH($C31,'Rentabilidad datos'!$C$2:$C$61,0)),"") -> 1486.281 | W31: =IFERROR(INDEX('Rentabilidad datos'!$M$2:$M$61,MATCH($C31,'Rentabilidad datos'!$C$2:$C$61,0)),"") -> 3561.4148 | X31: =IFERROR(INDEX('Rentabilidad datos'!$P$2:$P$61,MATCH($C31,'Rentabilidad datos'!$C$2:$C$61,0)),"") -> 0.41732881 | Y31: C2 | Z31: 73.654628 | AA31: 1 | AB31: 0.99291774 | AC31: 0.007082258 | AD31: =_xlfn.XLOOKUP(Table1[[#This Row],[Ruta]],#REF!,#REF!) -> #REF! | AE31: =_xlfn.XLOOKUP(Table1[[#This Row],[Ruta]],#REF!,#REF!) -> #REF! | AF31: =_xlfn.XLOOKUP(Table1[[#This Row],[Ruta]],#REF!,#REF!) -> #REF! | AG31: =_xlfn.XLOOKUP(Table1[[#This Row],[Ruta]],#REF!,#REF!) -> #REF! | AH31: 0.16546596 | AI31: 0.83445875 | AJ31: 7.5286132e-05 | AK31: 32629 | AL31: 6044 | AM31: 0.18523399 | AN31: 0.76950938 | AO31: 19064.322 | AP31: 9532.1608 | AQ31: 0.47737169 | AR31: 4482950 | AS31: 7070185.4 | AT31: 1.5771279 | AU31: 4968238.4 | AV31: 0.022600987 | AW31: 2 | AX31: 741.71906 | AY31: 436.55824 | AZ31: 0 | BA31: No | BB31: 0 | BC31: 4968238.4 | BD31: Sí | BE31: 73.654628 | BF31: 48.897321 | BG31: Sí | BH31: 0.18523399 | BI31: 0.79215712 | BJ31: No | BK31: 182.16443 | BL31: 326.54714 | BM31: No | BN31: 1 | BO31: Verde - Con espacio | BP31: No | BQ31: 13954.12 | BR31: 8714 | BS31: 638513 | BT31: 184503 | BU31: 3.4607188 | BV31: 21.17317 | BW31: 460 | BX31: 8350 | BY31: 8810 | BZ31: 0.047749901 | CA31: 0.0024931844 | CB31: 0.045256717 | CC31: 0.15146637 | CD31: 0.19856588 | CE31: 0.022015902 | CF31: 0.58007187 | CG31: 0.00012465922 | CH31: 5.4199661e-06 | CI31: 4.3507337 | CJ31: 0.40093154 | CK31: 524 | CL31: 905.22 | CM31: =CL31-CK31 -> 381.22 | CN31: 13.56 | CO31: 9.45 | CP31: =CO31-CN31 -> -4.11 | CQ31: 1269.84 | CR31: 182.16 | CS31: =CQ31-CR31 -> 1087.68 | CT31: Sí | CU31: 143.5 | CV31: 131 | CW31: 7287 | CX31: =((CW31-CY31)/BT31)*100 -> 3.7429093 | CY31: 381.22 | CZ31: =((CW31)/BT31)*100 -> 3.9495293 | DA31: =DB31/(CY31+BT31) -> 13.180685 | DB31: 2436900.6 | DC31: =DD31/(CY31+BT31) -> 0.49638622 | DD31: 91773.98 | DE31: 7287 | DF31: 3.761 | DG31: 348 | DH31: 3.95 | DI31: 22.155 | DJ31: 4095392 | DK31: 0.756 | DL31: 139797.2 | DM31: 7287 | DN31: 3.764 | DO31: 343.1 | DP31: 3.95 | DQ31: 22.036 | DR31: 4073353 | DS31: 0.754 | DT31: 139344.4
A32: Noreste | B32: Monterrey | C32: Planta Guadalupe | D32: 701318 | E32: Noreste|Planta Guadalupe|701318 | F32: Activa | G32: Sí | H32: Sí | I32: 22 | J32: 55981.503 | K32: 18786.253 | L32: 74767.756 | M32: 3483945 | N32: 828474 | O32: 2655471 | P32: 0 | Q32: 8272.8654 | R32: 6394.5727 | S32: 22541.519 | T32: 2275.8097 | U32: =IFERROR(INDEX('Rentabilidad datos'!$N$2:$N$61,MATCH($C32,'Rentabilidad datos'!$C$2:$C$61,0)),"") -> 31211.901 | V32: =IFERROR(INDEX('Rentabilidad datos'!$O$2:$O$61,MATCH($C32,'Rentabilidad datos'!$C$2:$C$61,0)),"") -> 1486.281 | W32: =IFERROR(INDEX('Rentabilidad datos'!$M$2:$M$61,MATCH($C32,'Rentabilidad datos'!$C$2:$C$61,0)),"") -> 3561.4148 | X32: =IFERROR(INDEX('Rentabilidad datos'!$P$2:$P$61,MATCH($C32,'Rentabilidad datos'!$C$2:$C$61,0)),"") -> 0.41732881 | Y32: C2 | Z32: 63.612319 | AA32: 1 | AB32: 0.99171313 | AC32: 0.0082868702 | AD32: =_xlfn.XLOOKUP(Table1[[#This Row],[Ruta]],#REF!,#REF!) -> #REF! | AE32: =_xlfn.XLOOKUP(Table1[[#This Row],[Ruta]],#REF!,#REF!) -> #REF! | AF32: =_xlfn.XLOOKUP(Table1[[#This Row],[Ruta]],#REF!,#REF!) -> #REF! | AG32: =_xlfn.XLOOKUP(Table1[[#This Row],[Ruta]],#REF!,#REF!) -> #REF! | AH32: 0.23779767 | AI32: 0.76220233 | AJ32: 0 | AK32: 17557 | AL32: 14043 | AM32: 0.5188244 | AN32: 0.76950938 | AO32: 4401.2763 | AP32: 2200.6381 | AQ32: 0.9251944 | AR32: 3499422.1 | AS32: 548384.36 | AT32: 0.15670712 | AU32: 385351.17 | AV32: 0.001752999 | AW32: 196 | AX32: 249.19334 | AY32: 436.55824 | AZ32: 187.3649 | BA32: Sí | BB32: 924463.5 | BC32: 1309814.7 | BD32: Sí | BE32: 63.612319 | BF32: 48.897321 | BG32: Sí | BH32: 0.5188244 | BI32: 0.79215712 | BJ32: No | BK32: 176.75593 | BL32: 326.54714 | BM32: No | BN32: 1 | BO32: Verde - Con espacio | BP32: No | BQ32: 385.63454 | BR32: 226 | BS32: 13303 | BT32: 4426 | BU32: 3.0056484 | BV32: 19.584071 | BW32: 1557 | BX32: 1721 | BY32: 3278 | BZ32: 0.74062359 | CA32: 0.35178491 | CB32: 0.38883868 | CC32: 0.13330321 | CD32: 0 | CE32: 0 | CF32: 0.1260732 | CG32: 0 | CH32: 0 | CI32: 1.3530783 | CJ32: 0.67653913 | CK32: 241 | CL32: 706.15 | CM32: =CL32-CK32 -> 465.15 | CN32: 3.21 | CO32: 9.45 | CP32: =CO32-CN32 -> 6.24 | CQ32: 634.92 | CR32: 176.76 | CS32: =CQ32-CR32 -> 458.16 | CT32: No | CU32: 34.78 | CV32: 258 | CW32: 1557 | CX32: =((CW32-CY32)/BT32)*100 -> 24.669001 | CY32: 465.15 | CZ32: =((CW32)/BT32)*100 -> 35.178491 | DA32: =DB32/(CY32+BT32) -> 991.35933 | DB32: 4848887.2 | DC32: =DD32/(CY32+BT32) -> 20.865584 | DD32: 102056.7 | DE32: 1557 | DF32: 27.775 | DG32: 327.7 | DH32: 35.178 | DI32: 1280.125 | DJ32: 6085296 | DK32: 26.874 | DL32: 127750.8 | DM32: 1557 | DN32: 29.063 | DO32: 270.7 | DP32: 35.178 | DQ32: 1180.098 | DR32: 5542537 | DS32: 24.771 | DT32: 116339
A33: Noreste | B33: Monterrey | C33: Planta Guadalupe | D33: 701319 | E33: Noreste|Planta Guadalupe|701319 | F33: Activa | G33: Sí | H33: Sí | I33: 22 | J33: 86929.31 | K33: 18369.995 | L33: 105299.3 | M33: 3945196 | N33: 1308316 | O33: 2636880 | P33: 0 | Q33: 9840.2676 | R33: 6394.5727 | S33: 22541.519 | T33: 2275.8097 | U33: =IFERROR(INDEX('Rentabilidad datos'!$N$2:$N$61,MATCH($C33,'Rentabilidad datos'!$C$2:$C$61,0)),"") -> 31211.901 | V33: =IFERROR(INDEX('Rentabilidad datos'!$O$2:$O$61,MATCH($C33,'Rentabilidad datos'!$C$2:$C$61,0)),"") -> 1486.281 | W33: =IFERROR(INDEX('Rentabilidad datos'!$M$2:$M$61,MATCH($C33,'Rentabilidad datos'!$C$2:$C$61,0)),"") -> 3561.4148 | X33: =IFERROR(INDEX('Rentabilidad datos'!$P$2:$P$61,MATCH($C33,'Rentabilidad datos'!$C$2:$C$61,0)),"") -> 0.41732881 | Y33: C2 | Z33: 29.273016 | AA33: 1 | AB33: 0.99796994 | AC33: 0.0020300639 | AD33: =_xlfn.XLOOKUP(Table1[[#This Row],[Ruta]],#REF!,#REF!) -> #REF! | AE33: =_xlfn.XLOOKUP(Table1[[#This Row],[Ruta]],#REF!,#REF!) -> #REF! | AF33: =_xlfn.XLOOKUP(Table1[[#This Row],[Ruta]],#REF!,#REF!) -> #REF! | AG33: =_xlfn.XLOOKUP(Table1[[#This Row],[Ruta]],#REF!,#REF!) -> #REF! | AH33: 0.33162256 | AI33: 0.66837744 | AJ33: 0 | AK33: 9221 | AL33: 13487 | AM33: 1.0566099 | AN33: 0.76950938 | AO33: 0 | AP33: 0 | AQ33: 1.4626396 | AR33: 3945947.3 | AS33: 0 | AT33: 0 | AU33: 0 | AV33: 0 | AW33: 490 | AX33: 292.57413 | AY33: 436.55824 | AZ33: 143.98411 | BA33: Sí | BB33: 682294.01 | BC33: 682294.01 | BD33: Sí | BE33: 29.273016 | BF33: 48.897321 | BG33: No | BH33: 1.0566099 | BI33: 0.79215712 | BJ33: Sí | BK33: 262.59178 | BL33: 326.54714 | BM33: No | BN33: 1 | BO33: Verde - Con espacio | BP33: No | BQ33: 1369.2315 | BR33: 164 | BS33: 10493 | BT33: 3045 | BU33: 3.445977 | BV33: 18.567073 | BW33: 3044 | BX33: 0 | BY33: 3044 | BZ33: 0.99967159 | CA33: 0.99967159 | CB33: 0 | CC33: 0 | CD33: 0 | CE33: 0 | CF33: 0 | CG33: 0 | CH33: 0.00032840722 | CI33: 0.09530163 | CJ33: 0.85771467 | CK33: 250 | CL33: 509.62 | CM33: =CL33-CK33 -> 259.62 | CN33: 5.28 | CO33: 9.45 | CP33: =CO33-CN33 -> 4.17 | CQ33: 634.92 | CR33: 262.59 | CS33: =CQ33-CR33 -> 372.33 | CT33: No | CU33: 58.32 | CV33: 275 | CW33: 2939 | CX33: =((CW33-CY33)/BT33)*100 -> 87.992775 | CY33: 259.62 | CZ33: =((CW33)/BT33)*100 -> 96.518883 | DA33: =DB33/(CY33+BT33) -> 630.33866 | DB33: 2083029.7 | DC33: =DD33/(CY33+BT33) -> 16.955792 | DD33: 56032.45 | DE33: 3044 | DF33: 90.483 | DG33: 288.8 | DH33: 99.967 | DI33: 1658.274 | DJ33: 5528360 | DK33: 43.247 | DL33: 144177 | DM33: 3044 | DN33: 91.288 | DO33: 264.3 | DP33: 99.967 | DQ33: 1607.494 | DR33: 5319661 | DS33: 41.963 | DT33: 138868.2
A34: Noreste | B34: Monterrey | C34: Planta Guadalupe | D34: 701320 | E34: Noreste|Planta Guadalupe|701320 | F34: Activa | G34: Sí | H34: Sí | I34: 22 | J34: 60331.667 | K34: 16939.756 | L34: 77271.423 | M34: 3147169 | N34: 904594 | O34: 2242575 | P34: 0 | Q34: 8482.9393 | R34: 6394.5727 | S34: 22541.519 | T34: 2275.8097 | U34: =IFERROR(INDEX('Rentabilidad datos'!$N$2:$N$61,MATCH($C34,'Rentabilidad datos'!$C$2:$C$61,0)),"") -> 31211.901 | V34: =IFERROR(INDEX('Rentabilidad datos'!$O$2:$O$61,MATCH($C34,'Rentabilidad datos'!$C$2:$C$61,0)),"") -> 1486.281 | W34: =IFERROR(INDEX('Rentabilidad datos'!$M$2:$M$61,MATCH($C34,'Rentabilidad datos'!$C$2:$C$61,0)),"") -> 3561.4148 | X34: =IFERROR(INDEX('Rentabilidad datos'!$P$2:$P$61,MATCH($C34,'Rentabilidad datos'!$C$2:$C$61,0)),"") -> 0.41732881 | Y34: C2 | Z34: 37.9625 | AA34: 1 | AB34: 0.9981879 | AC34: 0.0018121048 | AD34: =_xlfn.XLOOKUP(Table1[[#This Row],[Ruta]],#REF!,#REF!) -> #REF! | AE34: =_xlfn.XLOOKUP(Table1[[#This Row],[Ruta]],#REF!,#REF!) -> #REF! | AF34: =_xlfn.XLOOKUP(Table1[[#This Row],[Ruta]],#REF!,#REF!) -> #REF! | AG34: =_xlfn.XLOOKUP(Table1[[#This Row],[Ruta]],#REF!,#REF!) -> #REF! | AH34: 0.28743102 | AI34: 0.71256898 | AJ34: 0 | AK34: 6074 | AL34: 11919 | AM34: 0.76950938 | AN34: 0.76950938 | AO34: 0 | AP34: 0 | AQ34: 1.9622983 | AR34: 3147170.5 | AS34: 0 | AT34: 0 | AU34: 0 | AV34: 0 | AW34: 490 | AX34: 264.04652 | AY34: 436.55824 | AZ34: 172.51172 | BA34: Sí | BB34: 722437.13 | BC34: 722437.13 | BD34: Sí | BE34: 37.9625 | BF34: 48.897321 | BG34: No | BH34: 0.76950938 | BI34: 0.79215712 | BJ34: No | BK34: 208.27877 | BL34: 326.54714 | BM34: No | BN34: 0 | BO34: Verde - Con espacio | BP34: No | BQ34: 1096.1304 | BR34: 415 | BS34: 37018 | BT34: 10252 | BU34: 3.6108076 | BV34: 24.703614 | BW34: 2562 | BX34: 1651 | BY34: 4213 | BZ34: 0.41094421 | CA34: 0.24990246 | CB34: 0.16104175 | CC34: 0 | CD34: 0.11509949 | CE34: 0 | CF34: 0.4739563 | CG34: 0 | CH34: 0 | CI34: 3.5118051 | CJ34: 0.27013885 | CK34: 247 | CL34: 641.43 | CM34: =CL34-CK34 -> 394.43 | CN34: 4.13 | CO34: 9.45 | CP34: =CO34-CN34 -> 5.32 | CQ34: 634.92 | CR34: 208.28 | CS34: =CQ34-CR34 -> 426.64 | CT34: No | CU34: 47.29 | CV34: 308 | CW34: 4213 | CX34: =((CW34-CY34)/BT34)*100 -> 37.247074 | CY34: 394.43 | CZ34: =((CW34)/BT34)*100 -> 41.094421 | DA34: =DB34/(CY34+BT34) -> 222.26276 | DB34: 2366304.9 | DC34: =DD34/(CY34+BT34) -> 6.9662168 | DD34: 74165.34 | DE34: 4213 | DF34: 38.008 | DG34: 316.4 | DH34: 41.094 | DI34: 352.195 | DJ34: 3722129 | DK34: 11.086 | DL34: 117157.8 | DM34: 4213 | DN34: 38.285 | DO34: 288 | DP34: 41.094 | DQ34: 340.221 | DR34: 3585933 | DS34: 10.702 | DT34: 112799.7
A35: Noreste | B35: Monterrey | C35: Planta Guadalupe | D35: 701321 | E35: Noreste|Planta Guadalupe|701321 | F35: Inactiva | G35: Sí | H35: No | I35: 22 | J35: 14.0896 | K35: 0.063021 | L35: 14.152621 | M35: 9579 | N35: 216 | O35: 9 | P35: 9354 | Q35: 0 | R35: 6394.5727 | S35: 22541.519 | T35: 2275.8097 | U35: =IFERROR(INDEX('Rentabilidad datos'!$N$2:$N$61,MATCH($C35,'Rentabilidad datos'!$C$2:$C$61,0)),"") -> 31211.901 | V35: =IFERROR(INDEX('Rentabilidad datos'!$O$2:$O$61,MATCH($C35,'Rentabilidad datos'!$C$2:$C$61,0)),"") -> 1486.281 | W35: =IFERROR(INDEX('Rentabilidad datos'!$M$2:$M$61,MATCH($C35,'Rentabilidad datos'!$C$2:$C$61,0)),"") -> 3561.4148 | X35: =IFERROR(INDEX('Rentabilidad datos'!$P$2:$P$61,MATCH($C35,'Rentabilidad datos'!$C$2:$C$61,0)),"") -> 0.41732881 | Y35: C2 | Z35: 0 | AA35: 1 | AB35: 1 | AC35: 0 | AD35: =_xlfn.XLOOKUP(Table1[[#This Row],[Ruta]],#REF!,#REF!) -> #REF! | AE35: =_xlfn.XLOOKUP(Table1[[#This Row],[Ruta]],#REF!,#REF!) -> #REF! | AF35: =_xlfn.XLOOKUP(Table1[[#This Row],[Ruta]],#REF!,#REF!) -> #REF! | AG35: =_xlfn.XLOOKUP(Table1[[#This Row],[Ruta]],#REF!,#REF!) -> #REF! | AH35: 0.022549327 | AI35: 0.00093955528 | AJ35: 0.97651112 | AK35: 0 | AL35: 5 | AM35: 0 | AN35: 0.76950938 | AO35: 0 | AP35: 0 | AR35: 225.48 | AS35: 0 | AT35: 0 | AU35: 0 | AV35: 0 | AW35: 490 | AX35: 45.096 | AY35: 436.55824 | AZ35: 391.46224 | BA35: Sí | BB35: 687.70394 | BC35: 687.70394 | BD35: No | BE35: N/D | BF35: N/D | BG35: N/D | BH35: N/D | BI35: N/D | BJ35: N/D | BK35: N/D | BL35: N/D | BM35: N/D | BN35: N/D | BO35: N/D | BP35: No | BQ35: 0 | BR35: #N/A | BS35: #N/A | BT35: #N/A | BU35: #N/A | BV35: #N/A | BW35: #N/A | BX35: #N/A | BY35: #N/A | BZ35: #N/A | CA35: #N/A | CB35: #N/A | CC35: #N/A | CD35: #N/A | CE35: #N/A | CF35: #N/A | CG35: #N/A | CH35: #N/A | CI35: #N/A | CJ35: #N/A | CM35: =CL35-CK35 -> 0 | CP35: =CO35-CN35 -> 0 | CS35: =CQ35-CR35 -> 0 | CX35: =((CW35-CY35)/BT35)*100 -> #N/A | CZ35: =((CW35)/BT35)*100 -> #N/A | DA35: =DB35/(CY35+BT35) -> #N/A | DC35: =DD35/(CY35+BT35) -> #N/A
A36: Noreste | B36: Monterrey | C36: Sucursal Juventud | D36: 704300 | E36: Noreste|Sucursal Juventud|704300 | F36: Activa | G36: Sí | H36: Sí | I36: 12 | J36: 64896.698 | K36: 40489.787 | L36: 105386.48 | M36: 6012460 | N36: 931008 | O36: 5081452 | P36: 0 | Q36: 13603.569 | R36: 3255.9797 | S36: 12862.529 | T36: 1300.4627 | U36: =IFERROR(INDEX('Rentabilidad datos'!$N$2:$N$61,MATCH($C36,'Rentabilidad datos'!$C$2:$C$61,0)),"") -> 17418.971 | V36: =IFERROR(INDEX('Rentabilidad datos'!$O$2:$O$61,MATCH($C36,'Rentabilidad datos'!$C$2:$C$61,0)),"") -> 1451.5809 | W36: =IFERROR(INDEX('Rentabilidad datos'!$M$2:$M$61,MATCH($C36,'Rentabilidad datos'!$C$2:$C$61,0)),"") -> 3282.4549 | X36: =IFERROR(INDEX('Rentabilidad datos'!$P$2:$P$61,MATCH($C36,'Rentabilidad datos'!$C$2:$C$61,0)),"") -> 0.44222418 | Y36: C2 | Z36: 55.710407 | AA36: 1 | AB36: 0.99954977 | AC36: 0.00045023169 | AD36: =_xlfn.XLOOKUP(Table1[[#This Row],[Ruta]],#REF!,#REF!) -> #REF! | AE36: =_xlfn.XLOOKUP(Table1[[#This Row],[Ruta]],#REF!,#REF!) -> #REF! | AF36: =_xlfn.XLOOKUP(Table1[[#This Row],[Ruta]],#REF!,#REF!) -> #REF! | AG36: =_xlfn.XLOOKUP(Table1[[#This Row],[Ruta]],#REF!,#REF!) -> #REF! | AH36: 0.15484644 | AI36: 0.84515356 | AJ36: 0 | AK36: 24624 | AL36: 18213 | AM36: 0.73964425 | AN36: 0.74419035 | AO36: 111.94309 | AP36: 55.971546 | AQ36: 0.7419173 | AR36: 6012777.3 | AS36: 18478.254 | AT36: 0.0030731646 | AU36: 12984.719 | AV36: 5.9068716e-05 | AW36: 468 | AX36: 330.13657 | AY36: 366.04512 | AZ36: 35.908552 | BA36: Sí | BB36: 229784.65 | BC36: 242769.37 | BD36: Sí | BE36: 55.710407 | BF36: 48.897321 | BG36: Sí | BH36: 0.73964425 | BI36: 0.79215712 | BJ36: No | BK36: 238.43096 | BL36: 326.54714 | BM36: No | BN36: 1 | BO36: Verde - Con espacio | BP36: No | BQ36: 0 | BR36: 592 | BS36: 56176 | BT36: 16936 | BU36: 3.316958 | BV36: 28.608108 | BW36: 0 | BX36: 16652 | BY36: 16652 | BZ36: 0.98323099 | CA36: 0 | CB36: 0.98323099 | CC36: 0.0011218706 | CD36: 0.015647142 | CE36: 0 | CF36: 0 | CG36: 0 | CH36: 0 | CI36: 1.174879 | CJ36: 0.64084306 | CK36: 281 | CL36: 1040.31 | CM36: =CL36-CK36 -> 759.31 | CN36: 5.09 | CO36: 9.45 | CP36: =CO36-CN36 -> 4.36 | CQ36: 1481.48 | CR36: 238.43 | CS36: =CQ36-CR36 -> 1243.05 | CT36: No | CU36: 53.91 | CV36: 355 | CW36: 14913 | CX36: =((CW36-CY36)/BT36)*100 -> 83.571623 | CY36: 759.31 | CZ36: =((CW36)/BT36)*100 -> 88.055031 | DA36: =DB36/(CY36+BT36) -> 667.2216 | DB36: 11806693 | DC36: =DD36/(CY36+BT36) -> 11.777224 | DD36: 208401.63 | DE36: 14913 | DF36: 83.87 | DG36: 708.9 | DH36: 88.055 | DI36: 861.723 | DJ36: 15204973 | DK36: 15.206 | DL36: 268301.3 | DM36: 14913 | DN36: 83.913 | DO36: 701.5 | DP36: 88.055 | DQ36: 856.898 | DR36: 15113549 | DS36: 15.116 | DT36: 266604
A37: Noreste | B37: Monterrey | C37: Sucursal Juventud | D37: 704301 | E37: Noreste|Sucursal Juventud|704301 | F37: Activa | G37: Sí | H37: Sí | I37: 12 | J37: 82403.026 | K37: 29859.09 | L37: 112262.12 | M37: 5160118 | N37: 1250146 | O37: 3909972 | P37: 0 | Q37: 11674.475 | R37: 3255.9797 | S37: 12862.529 | T37: 1300.4627 | U37: =IFERROR(INDEX('Rentabilidad datos'!$N$2:$N$61,MATCH($C37,'Rentabilidad datos'!$C$2:$C$61,0)),"") -> 17418.971 | V37: =IFERROR(INDEX('Rentabilidad datos'!$O$2:$O$61,MATCH($C37,'Rentabilidad datos'!$C$2:$C$61,0)),"") -> 1451.5809 | W37: =IFERROR(INDEX('Rentabilidad datos'!$M$2:$M$61,MATCH($C37,'Rentabilidad datos'!$C$2:$C$61,0)),"") -> 3282.4549 | X37: =IFERROR(INDEX('Rentabilidad datos'!$P$2:$P$61,MATCH($C37,'Rentabilidad datos'!$C$2:$C$61,0)),"") -> 0.44222418 | Y37: C2 | Z37: 59.873303 | AA37: 1 | AB37: 0.99724076 | AC37: 0.0027592392 | AD37: =_xlfn.XLOOKUP(Table1[[#This Row],[Ruta]],#REF!,#REF!) -> #REF! | AE37: =_xlfn.XLOOKUP(Table1[[#This Row],[Ruta]],#REF!,#REF!) -> #REF! | AF37: =_xlfn.XLOOKUP(Table1[[#This Row],[Ruta]],#REF!,#REF!) -> #REF! | AG37: =_xlfn.XLOOKUP(Table1[[#This Row],[Ruta]],#REF!,#REF!) -> #REF! | AH37: 0.24227082 | AI37: 0.75772918 | AJ37: 0 | AK37: 26464 | AL37: 16643 | AM37: 0.62889208 | AN37: 0.74419035 | AO37: 3051.2533 | AP37: 1525.6267 | AQ37: 0.68654121 | AR37: 5160118 | AS37: 473016.5 | AT37: 0.091667768 | AU37: 332389.97 | AV37: 0.0015120734 | AW37: 223 | AX37: 310.04735 | AY37: 366.04512 | AZ37: 55.99777 | BA37: Sí | BB37: 327449.23 | BC37: 659839.2 | BD37: Sí | BE37: 59.873303 | BF37: 48.897321 | BG37: Sí | BH37: 0.62889208 | BI37: 0.79215712 | BJ37: No | BK37: 253.98669 | BL37: 326.54714 | BM37: No | BN37: 1 | BO37: Verde - Con espacio | BP37: No | BQ37: 163.74074 | BR37: 768 | BS37: 67014 | BT37: 19418 | BU37: 3.4511278 | BV37: 25.283854 | BW37: 4144 | BX37: 10356 | BY37: 14500 | BZ37: 0.74672984 | CA37: 0.21341024 | CB37: 0.5333196 | CC37: 0.2184571 | CD37: 0.03481306 | CE37: 0 | CF37: 0 | CG37: 0 | CH37: 0 | CI37: 1.8652819 | CJ37: 0.5968902 | CK37: 311 | CL37: 815.96 | CM37: =CL37-CK37 -> 504.96 | CN37: 5.04 | CO37: 9.45 | CP37: =CO37-CN37 -> 4.41 | CQ37: 1269.84 | CR37: 253.99 | CS37: =CQ37-CR37 -> 1015.85 | CT37: No | CU37: 53.7 | CV37: 333 | CW37: 14500 | CX37: =((CW37-CY37)/BT37)*100 -> 72.07251 | CY37: 504.96 | CZ37: =((CW37)/BT37)*100 -> 74.672984 | DA37: =DB37/(CY37+BT37) -> 286.0296 | DB37: 5698556.2 | DC37: =DD37/(CY37+BT37) -> 6.365402 | DD37: 126817.65 | DE37: 14500 | DF37: 72.291 | DG37: 462.6 | DH37: 74.673 | DI37: 452.056 | DJ37: 8987143 | DK37: 10.303 | DL37: 204823.4 | DM37: 14500 | DN37: 72.362 | DO37: 448.7 | DP37: 74.673 | DQ37: 446.818 | DR37: 8876801 | DS37: 10.173 | DT37: 202106.1
A38: Noreste | B38: Monterrey | C38: Sucursal Juventud | D38: 704302 | E38: Noreste|Sucursal Juventud|704302 | F38: Activa | G38: Sí | H38: Sí | I38: 12 | J38: 57956.302 | K38: 18855.883 | L38: 76812.185 | M38: 3299157 | N38: 835889 | O38: 2463136 | P38: 132 | Q38: 7533.1487 | R38: 3255.9797 | S38: 12862.529 | T38: 1300.4627 | U38: =IFERROR(INDEX('Rentabilidad datos'!$N$2:$N$61,MATCH($C38,'Rentabilidad datos'!$C$2:$C$61,0)),"") -> 17418.971 | V38: =IFERROR(INDEX('Rentabilidad datos'!$O$2:$O$61,MATCH($C38,'Rentabilidad datos'!$C$2:$C$61,0)),"") -> 1451.5809 | W38: =IFERROR(INDEX('Rentabilidad datos'!$M$2:$M$61,MATCH($C38,'Rentabilidad datos'!$C$2:$C$61,0)),"") -> 3282.4549 | X38: =IFERROR(INDEX('Rentabilidad datos'!$P$2:$P$61,MATCH($C38,'Rentabilidad datos'!$C$2:$C$61,0)),"") -> 0.44222418 | Y38: C2 | Z38: 77.002283 | AA38: 1 | AB38: 0.9741243 | AC38: 0.025875701 | AD38: =_xlfn.XLOOKUP(Table1[[#This Row],[Ruta]],#REF!,#REF!) -> #REF! | AE38: =_xlfn.XLOOKUP(Table1[[#This Row],[Ruta]],#REF!,#REF!) -> #REF! | AF38: =_xlfn.XLOOKUP(Table1[[#This Row],[Ruta]],#REF!,#REF!) -> #REF! | AG38: =_xlfn.XLOOKUP(Table1[[#This Row],[Ruta]],#REF!,#REF!) -> #REF! | AH38: 0.25336442 | AI38: 0.74659557 | AJ38: 4.0010221e-05 | AK38: 33727 | AL38: 14160 | AM38: 0.41984167 | AN38: 0.74419035 | AO38: 10939.308 | AP38: 5469.6539 | AQ38: 0.58201601 | AR38: 3299519.1 | AS38: 1274521.7 | AT38: 0.38627499 | AU38: 895609.86 | AV38: 0.004074214 | AW38: 59 | AX38: 233.01689 | AY38: 366.04512 | AZ38: 133.02823 | BA38: Sí | BB38: 661833.43 | BC38: 1557443.3 | BD38: Sí | BE38: 77.002283 | BF38: 48.897321 | BG38: Sí | BH38: 0.41984167 | BI38: 0.79215712 | BJ38: No | BK38: 175.37029 | BL38: 326.54714 | BM38: No | BN38: 1 | BO38: Verde - Con espacio | BP38: No | BQ38: 1967.0111 | BR38: 1733 | BS38: 183729 | BT38: 50907 | BU38: 3.6091107 | BV38: 29.375072 | BW38: 2670 | BX38: 16686 | BY38: 19356 | BZ38: 0.38022276 | CA38: 0.052448583 | CB38: 0.32777418 | CC38: 0.45940637 | CD38: 0.13536449 | CE38: 0 | CF38: 0.025006384 | CG38: 0 | CH38: 0 | CI38: 1.921308 | CJ38: 0.39732432 | CK38: 852 | CL38: 1050.58 | CM38: =CL38-CK38 -> 198.58 | CN38: 13.08 | CO38: 9.45 | CP38: =CO38-CN38 -> -3.63 | CQ38: 846.56 | CR38: 175.37 | CS38: =CQ38-CR38 -> 671.19 | CT38: Sí | CU38: 138.54 | CV38: 646 | CW38: 19356 | CX38: =((CW38-CY38)/BT38)*100 -> 37.632192 | CY38: 198.58 | CZ38: =((CW38)/BT38)*100 -> 38.022276 | DA38: =DB38/(CY38+BT38) -> 142.69133 | DB38: 7292323.2 | DC38: =DD38/(CY38+BT38) -> 3.7239298 | DD38: 190313.59 | DE38: 19356 | DF38: 37.728 | DG38: 149.8 | DH38: 38.022 | DI38: 208.962 | DJ38: 10668927 | DK38: 5.395 | DL38: 275452.2 | DM38: 19356 | DN38: 37.745 | DO38: 140.9 | DP38: 38.022 | DQ38: 207.76 | DR38: 10605700 | DS38: 5.362 | DT38: 273729.3
A39: Noreste | B39: Monterrey | C39: Sucursal Juventud | D39: 704303 | E39: Noreste|Sucursal Juventud|704303 | F39: Activa | G39: Sí | H39: Sí | I39: 12 | J39: 86784.891 | K39: 41036.783 | L39: 127821.67 | M39: 6823521 | N39: 1304126 | O39: 5519395 | P39: 0 | Q39: 15231.078 | R39: 3255.9797 | S39: 12862.529 | T39: 1300.4627 | U39: =IFERROR(INDEX('Rentabilidad datos'!$N$2:$N$61,MATCH($C39,'Rentabilidad datos'!$C$2:$C$61,0)),"") -> 17418.971 | V39: =IFERROR(INDEX('Rentabilidad datos'!$O$2:$O$61,MATCH($C39,'Rentabilidad datos'!$C$2:$C$61,0)),"") -> 1451.5809 | W39: =IFERROR(INDEX('Rentabilidad datos'!$M$2:$M$61,MATCH($C39,'Rentabilidad datos'!$C$2:$C$61,0)),"") -> 3282.4549 | X39: =IFERROR(INDEX('Rentabilidad datos'!$P$2:$P$61,MATCH($C39,'Rentabilidad datos'!$C$2:$C$61,0)),"") -> 0.44222418 | Y39: C2 | Z39: 48.897321 | AA39: 1 | AB39: 0.99989419 | AC39: 0.00010581048 | AD39: =_xlfn.XLOOKUP(Table1[[#This Row],[Ruta]],#REF!,#REF!) -> #REF! | AE39: =_xlfn.XLOOKUP(Table1[[#This Row],[Ruta]],#REF!,#REF!) -> #REF! | AF39: =_xlfn.XLOOKUP(Table1[[#This Row],[Ruta]],#REF!,#REF!) -> #REF! | AG39: =_xlfn.XLOOKUP(Table1[[#This Row],[Ruta]],#REF!,#REF!) -> #REF! | AH39: 0.19112215 | AI39: 0.80887785 | AJ39: 0 | AK39: 21906 | AL39: 19344 | AM39: 0.88304574 | AN39: 0.74419035 | AO39: 0 | AP39: 0 | AQ39: 0.88304574 | AR39: 6823522.8 | AS39: 0 | AT39: 0 | AU39: 0 | AV39: 0 | AW39: 490 | AX39: 352.74622 | AY39: 366.04512 | AZ39: 13.2989 | BA39: Sí | BB39: 90386.515 | BC39: 90386.515 | BD39: Sí | BE39: 48.897321 | BF39: 48.897321 | BG39: Sí | BH39: 0.88304574 | BI39: 0.79215712 | BJ39: Sí | BK39: 285.31624 | BL39: 326.54714 | BM39: No | BN39: 2 | BO39: Amarillo - Cerca del tope | BP39: No | BQ39: 0 | BR39: 596 | BS39: 51754 | BT39: 16148 | BU39: 3.2049789 | BV39: 27.09396 | BW39: 711 | BX39: 8151 | BY39: 8862 | BZ39: 0.54879861 | CA39: 0.04403022 | CB39: 0.50476839 | CC39: 0.28176864 | CD39: 0.16943275 | CE39: 0 | CF39: 0 | CG39: 0 | CH39: 0 | CI39: 1.8356069 | CJ39: 0.59898752 | CK39: 298 | CL39: 741.53 | CM39: =CL39-CK39 -> 443.53 | CN39: 4.26 | CO39: 9.45 | CP39: =CO39-CN39 -> 5.19 | CQ39: 846.56 | CR39: 285.32 | CS39: =CQ39-CR39 -> 561.24 | CT39: No | CU39: 47.86 | CV39: 277 | CW39: 8862 | CX39: =((CW39-CY39)/BT39)*100 -> 52.133205 | CY39: 443.53 | CZ39: =((CW39)/BT39)*100 -> 54.879861 | DA39: =DB39/(CY39+BT39) -> 301.13063 | DB39: 4996217.8 | DC39: =DD39/(CY39+BT39) -> 6.2331846 | DD39: 103418.07 | DE39: 8862 | DF39: 52.667 | DG39: 357.4 | DH39: 54.88 | DI39: 547.662 | DJ39: 9039365 | DK39: 11.222 | DL39: 185225.6 | DM39: 8862 | DN39: 52.853 | DO39: 327.4 | DP39: 54.88 | DQ39: 530.517 | DR39: 8740452 | DS39: 10.87 | DT39: 179090.8
A40: Noreste | B40: Monterrey | C40: Sucursal Juventud | D40: 704304 | E40: Noreste|Sucursal Juventud|704304 | F40: Activa | G40: Sí | H40: Sí | I40: 12 | J40: 90624.307 | K40: 28193.608 | L40: 118817.92 | M40: 4462385 | N40: 1303983 | O40: 3158402 | P40: 0 | Q40: 10118.787 | R40: 3255.9797 | S40: 12862.529 | T40: 1300.4627 | U40: =IFERROR(INDEX('Rentabilidad datos'!$N$2:$N$61,MATCH($C40,'Rentabilidad datos'!$C$2:$C$61,0)),"") -> 17418.971 | V40: =IFERROR(INDEX('Rentabilidad datos'!$O$2:$O$61,MATCH($C40,'Rentabilidad datos'!$C$2:$C$61,0)),"") -> 1451.5809 | W40: =IFERROR(INDEX('Rentabilidad datos'!$M$2:$M$61,MATCH($C40,'Rentabilidad datos'!$C$2:$C$61,0)),"") -> 3282.4549 | X40: =IFERROR(INDEX('Rentabilidad datos'!$P$2:$P$61,MATCH($C40,'Rentabilidad datos'!$C$2:$C$61,0)),"") -> 0.44222418 | Y40: C2 | Z40: 60.437642 | AA40: 1 | AB40: 0.99708026 | AC40: 0.0029197391 | AD40: =_xlfn.XLOOKUP(Table1[[#This Row],[Ruta]],#REF!,#REF!) -> #REF! | AE40: =_xlfn.XLOOKUP(Table1[[#This Row],[Ruta]],#REF!,#REF!) -> #REF! | AF40: =_xlfn.XLOOKUP(Table1[[#This Row],[Ruta]],#REF!,#REF!) -> #REF! | AG40: =_xlfn.XLOOKUP(Table1[[#This Row],[Ruta]],#REF!,#REF!) -> #REF! | AH40: 0.29221661 | AI40: 0.70778339 | AJ40: 0 | AK40: 26653 | AL40: 11890 | AM40: 0.44610363 | AN40: 0.74419035 | AO40: 7944.9053 | AP40: 3972.4527 | AQ40: 0.59514699 | AR40: 4462385.2 | AS40: 1490884.3 | AT40: 0.33410031 | AU40: 1047648.4 | AV40: 0.0047658518 | AW40: 36 | AX40: 375.30574 | AY40: 366.04512 | AZ40: 0 | BA40: No | BB40: 0 | BC40: 1047648.4 | BD40: Sí | BE40: 60.437642 | BF40: 48.897321 | BG40: Sí | BH40: 0.44610363 | BI40: 0.79215712 | BJ40: No | BK40: 269.42838 | BL40: 326.54714 | BM40: No | BN40: 1 | BO40: Verde - Con espacio | BP40: No | BQ40: 3674.0361 | BR40: 1367 | BS40: 110909 | BT40: 31319 | BU40: 3.5412689 | BV40: 22.910753 | BW40: 4143 | BX40: 12776 | BY40: 16919 | BZ40: 0.5402152 | CA40: 0.13228392 | CB40: 0.40793129 | CC40: 0.21692902 | CD40: 0.069255085 | CE40: 0 | CF40: 0.17353683 | CG40: 0 | CH40: 6.3858999e-05 | CI40: 2.5155758 | CJ40: 0.49590205 | CK40: 551 | CL40: 967.99 | CM40: =CL40-CK40 -> 416.99 | CN40: 7.05 | CO40: 9.45 | CP40: =CO40-CN40 -> 2.4 | CQ40: 846.56 | CR40: 269.43 | CS40: =CQ40-CR40 -> 577.13 | CT40: No | CU40: 74.59 | CV40: 387 | CW40: 16919 | CX40: =((CW40-CY40)/BT40)*100 -> 52.690092 | CY40: 416.99 | CZ40: =((CW40)/BT40)*100 -> 54.02152 | DA40: =DB40/(CY40+BT40) -> 172.23941 | DB40: 5466188.3 | DC40: =DD40/(CY40+BT40) -> 4.4309883 | DD40: 140621.8 | DE40: 16919 | DF40: 52.795 | DG40: 384.2 | DH40: 54.022 | DI40: 327.43 | DJ40: 10380578 | DK40: 8.389 | DL40: 265961.4 | DM40: 16919 | DN40: 52.831 | DO40: 373 | DP40: 54.022 | DQ40: 324.873 | DR40: 10295876 | DS40: 8.319 | DT40: 263655.8
A41: Noreste | B41: Monterrey | C41: Sucursal Juventud | D41: 704305 | E41: Noreste|Sucursal Juventud|704305 | F41: Activa | G41: Sí | H41: Sí | I41: 12 | J41: 98958.306 | K41: 41947.462 | L41: 140905.77 | M41: 6475539 | N41: 1466941 | O41: 5008598 | P41: 0 | Q41: 14750.656 | R41: 3255.9797 | S41: 12862.529 | T41: 1300.4627 | U41: =IFERROR(INDEX('Rentabilidad datos'!$N$2:$N$61,MATCH($C41,'Rentabilidad datos'!$C$2:$C$61,0)),"") -> 17418.971 | V41: =IFERROR(INDEX('Rentabilidad datos'!$O$2:$O$61,MATCH($C41,'Rentabilidad datos'!$C$2:$C$61,0)),"") -> 1451.5809 | W41: =IFERROR(INDEX('Rentabilidad datos'!$M$2:$M$61,MATCH($C41,'Rentabilidad datos'!$C$2:$C$61,0)),"") -> 3282.4549 | X41: =IFERROR(INDEX('Rentabilidad datos'!$P$2:$P$61,MATCH($C41,'Rentabilidad datos'!$C$2:$C$61,0)),"") -> 0.44222418 | Y41: C2 | Z41: 47.243736 | AA41: 1 | AB41: 0.99982025 | AC41: 0.00017975338 | AD41: =_xlfn.XLOOKUP(Table1[[#This Row],[Ruta]],#REF!,#REF!) -> #REF! | AE41: =_xlfn.XLOOKUP(Table1[[#This Row],[Ruta]],#REF!,#REF!) -> #REF! | AF41: =_xlfn.XLOOKUP(Table1[[#This Row],[Ruta]],#REF!,#REF!) -> #REF! | AG41: =_xlfn.XLOOKUP(Table1[[#This Row],[Ruta]],#REF!,#REF!) -> #REF! | AH41: 0.22653574 | AI41: 0.77346426 | AJ41: 0 | AK41: 20740 | AL41: 17841 | AM41: 0.86022179 | AN41: 0.74419035 | AO41: 0 | AP41: 0 | AQ41: 0.86022179 | AR41: 6475538 | AS41: 0 | AT41: 0 | AU41: 0 | AV41: 0 | AW41: 490 | AX41: 362.95824 | AY41: 366.04512 | AZ41: 3.0868737 | BA41: Sí | BB41: 19349.943 | BC41: 19349.943 | BD41: Sí | BE41: 47.243736 | BF41: 48.897321 | BG41: No | BH41: 0.86022179 | BI41: 0.79215712 | BJ41: Sí | BK41: 320.96986 | BL41: 326.54714 | BM41: No | BN41: 1 | BO41: Verde - Con espacio | BP41: No | BQ41: 0 | BR41: 182 | BS41: 11933 | BT41: 4085 | BU41: 2.921175 | BV41: 22.445055 | BW41: 587 | BX41: 3115 | BY41: 3702 | BZ41: 0.90624235 | CA41: 0.14369645 | CB41: 0.7625459 | CC41: 0.09375765 | CD41: 0 | CE41: 0 | CF41: 0 | CG41: 0 | CH41: 0 | CI41: 1.3408196 | CJ41: 1.0894159 | CK41: 276 | CL41: 728.88 | CM41: =CL41-CK41 -> 452.88 | CN41: 4.54 | CO41: 9.45 | CP41: =CO41-CN41 -> 4.91 | CQ41: 1269.84 | CR41: 320.97 | CS41: =CQ41-CR41 -> 948.87 | CT41: No | CU41: 49.62 | CV41: 298 | CW41: 3702 | CX41: =((CW41-CY41)/BT41)*100 -> 79.537821 | CY41: 452.88 | CZ41: =((CW41)/BT41)*100 -> 90.624235 | DA41: =DB41/(CY41+BT41) -> 1094.775 | DB41: 4967957.8 | DC41: =DD41/(CY41+BT41) -> 23.785032 | DD41: 107933.62 | DE41: 3702 | DF41: 82.785 | DG41: 320.2 | DH41: 90.624 | DI41: 1746.882 | DJ41: 7695438 | DK41: 37.76 | DL41: 166342.2 | DM41: 3702 | DN41: 83.946 | DO41: 272.8 | DP41: 90.624 | DQ41: 1651.421 | DR41: 7196565 | DS41: 35.737 | DT41: 155732.6
A42: Noreste | B42: Monterrey | C42: Sucursal Juventud | D42: 704306 | E42: Noreste|Sucursal Juventud|704306 | F42: Activa | G42: Sí | H42: Sí | I42: 12 | J42: 96753.283 | K42: 38742.464 | L42: 135495.75 | M42: 6219275 | N42: 1397595 | O42: 4821680 | P42: 0 | Q42: 14007.375 | R42: 3255.9797 | S42: 12862.529 | T42: 1300.4627 | U42: =IFERROR(INDEX('Rentabilidad datos'!$N$2:$N$61,MATCH($C42,'Rentabilidad datos'!$C$2:$C$61,0)),"") -> 17418.971 | V42: =IFERROR(INDEX('Rentabilidad datos'!$O$2:$O$61,MATCH($C42,'Rentabilidad datos'!$C$2:$C$61,0)),"") -> 1451.5809 | W42: =IFERROR(INDEX('Rentabilidad datos'!$M$2:$M$61,MATCH($C42,'Rentabilidad datos'!$C$2:$C$61,0)),"") -> 3282.4549 | X42: =IFERROR(INDEX('Rentabilidad datos'!$P$2:$P$61,MATCH($C42,'Rentabilidad datos'!$C$2:$C$61,0)),"") -> 0.44222418 | Y42: C2 | Z42: 42.527027 | AA42: 1 | AB42: 0.99960896 | AC42: 0.00039104236 | AD42: =_xlfn.XLOOKUP(Table1[[#This Row],[Ruta]],#REF!,#REF!) -> #REF! | AE42: =_xlfn.XLOOKUP(Table1[[#This Row],[Ruta]],#REF!,#REF!) -> #REF! | AF42: =_xlfn.XLOOKUP(Table1[[#This Row],[Ruta]],#REF!,#REF!) -> #REF! | AG42: =_xlfn.XLOOKUP(Table1[[#This Row],[Ruta]],#REF!,#REF!) -> #REF! | AH42: 0.22471992 | AI42: 0.77528008 | AJ42: 0 | AK42: 18882 | AL42: 13754 | AM42: 0.7284186 | AN42: 0.74419035 | AO42: 297.80212 | AP42: 148.90106 | AQ42: 0.73630447 | AR42: 6219274.5 | AS42: 67329.982 | AT42: 0.010826019 | AU42: 47312.96 | AV42: 0.00021523113 | AW42: 436 | AX42: 452.17933 | AY42: 366.04512 | AZ42: 0 | BA42: No | BB42: 0 | BC42: 47312.96 | BD42: Sí | BE42: 42.527027 | BF42: 48.897321 | BG42: No | BH42: 0.7284186 | BI42: 0.79215712 | BJ42: No | BK42: 305.1706 | BL42: 326.54714 | BM42: No | BN42: 0 | BO42: Verde - Con espacio | BP42: No | BQ42: 2375.4982 | BR42: 985 | BS42: 53536 | BT42: 16826 | BU42: 3.1817425 | BV42: 17.082234 | BW42: 392 | BX42: 6321 | BY42: 6713 | BZ42: 0.39896589 | CA42: 0.023297278 | CB42: 0.37566861 | CC42: 0.026863188 | CD42: 0 | CE42: 0 | CF42: 0.57417093 | CG42: 0 | CH42: 0 | CI42: 3.6237298 | CJ42: 1.2888524 | CK42: 243 | CL42: 653.58 | CM42: =CL42-CK42 -> 410.58 | CN42: 3.37 | CO42: 9.45 | CP42: =CO42-CN42 -> 6.08 | CQ42: 846.56 | CR42: 305.17 | CS42: =CQ42-CR42 -> 541.39 | CT42: No | CU42: 42.43 | CV42: 228 | CW42: 6713 | CX42: =((CW42-CY42)/BT42)*100 -> 37.456436 | CY42: 410.58 | CZ42: =((CW42)/BT42)*100 -> 39.896589 | DA42: =DB42/(CY42+BT42) -> 230.12621 | DB42: 3966588.8 | DC42: =DD42/(CY42+BT42) -> 5.2879945 | DD42: 91146.94 | DE42: 6713 | DF42: 37.76 | DG42: 359.4 | DH42: 39.897 | DI42: 438.794 | DJ42: 7540857 | DK42: 10.069 | DL42: 173038.7 | DM42: 6713 | DN42: 37.946 | DO42: 328.2 | DP42: 39.897 | DQ42: 424.131 | DR42: 7275626 | DS42: 9.732 | DT42: 166951.8
A43: Noreste | B43: Monterrey | C43: Sucursal Juventud | D43: 704307 | E43: Noreste|Sucursal Juventud|704307 | F43: Activa | G43: Sí | H43: Sí | I43: 12 | J43: 70138.029 | K43: 25486.017 | L43: 95624.046 | M43: 4531528 | N43: 1032825 | O43: 3498665 | P43: 38 | Q43: 10513.892 | R43: 3255.9797 | S43: 12862.529 | T43: 1300.4627 | U43: =IFERROR(INDEX('Rentabilidad datos'!$N$2:$N$61,MATCH($C43,'Rentabilidad datos'!$C$2:$C$61,0)),"") -> 17418.971 | V43: =IFERROR(INDEX('Rentabilidad datos'!$O$2:$O$61,MATCH($C43,'Rentabilidad datos'!$C$2:$C$61,0)),"") -> 1451.5809 | W43: =IFERROR(INDEX('Rentabilidad datos'!$M$2:$M$61,MATCH($C43,'Rentabilidad datos'!$C$2:$C$61,0)),"") -> 3282.4549 | X43: =IFERROR(INDEX('Rentabilidad datos'!$P$2:$P$61,MATCH($C43,'Rentabilidad datos'!$C$2:$C$61,0)),"") -> 0.44222418 | Y43: C2 | Z43: 48.994764 | AA43: 1 | AB43: 0.99720624 | AC43: 0.0027937596 | AD43: =_xlfn.XLOOKUP(Table1[[#This Row],[Ruta]],#REF!,#REF!) -> #REF! | AE43: =_xlfn.XLOOKUP(Table1[[#This Row],[Ruta]],#REF!,#REF!) -> #REF! | AF43: =_xlfn.XLOOKUP(Table1[[#This Row],[Ruta]],#REF!,#REF!) -> #REF! | AG43: =_xlfn.XLOOKUP(Table1[[#This Row],[Ruta]],#REF!,#REF!) -> #REF! | AH43: 0.22791981 | AI43: 0.7720718 | AJ43: 8.3856924e-06 | AK43: 18716 | AL43: 13420 | AM43: 0.61973712 | AN43: 0.74419035 | AO43: 2329.2665 | AP43: 1164.6333 | AQ43: 0.77926017 | AR43: 4531487.5 | AS43: 393257.91 | AT43: 0.086783403 | AU43: 276343.4 | AV43: 0.0012571123 | AW43: 261 | AX43: 337.66673 | AY43: 366.04512 | AZ43: 28.378386 | BA43: Sí | BB43: 133807.92 | BC43: 410151.32 | BD43: Sí | BE43: 48.994764 | BF43: 48.897321 | BG43: Sí | BH43: 0.61973712 | BI43: 0.79215712 | BJ43: No | BK43: 221.86554 | BL43: 326.54714 | BM43: No | BN43: 1 | BO43: Verde - Con espacio | BP43: No | BQ43: 3274.2116 | BR43: 945 | BS43: 47641 | BT43: 14071 | BU43: 3.3857579 | BV43: 14.889947 | BW43: 805 | BX43: 7539 | BY43: 8344 | BZ43: 0.59299268 | CA43: 0.057209864 | CB43: 0.53578282 | CC43: 0.26799801 | CD43: 0.098997939 | CE43: 0.00014213631 | CF43: 0.039798166 | CG43: 0 | CH43: 7.1068154e-05 | CI43: 1.3853613 | CJ43: 1.1124871 | CK43: 321 | CL43: 808.48 | CM43: =CL43-CK43 -> 487.48 | CN43: 4.73 | CO43: 9.45 | CP43: =CO43-CN43 -> 4.72 | CQ43: 634.92 | CR43: 221.87 | CS43: =CQ43-CR43 -> 413.05 | CT43: No | CU43: 51.27 | CV43: 287 | CW43: 8344 | CX43: =((CW43-CY43)/BT43)*100 -> 55.834838 | CY43: 487.48 | CZ43: =((CW43)/BT43)*100 -> 59.299268 | DA43: =DB43/(CY43+BT43) -> 414.39116 | DB43: 6032905.5 | DC43: =DD43/(CY43+BT43) -> 9.369303 | DD43: 136402.81 | DE43: 8344 | DF43: 56.324 | DG43: 418.6 | DH43: 59.299 | DI43: 591.986 | DJ43: 8577652 | DK43: 13.321 | DL43: 193018.3 | DM43: 8344 | DN43: 56.537 | DO43: 388.7 | DP43: 59.299 | DQ43: 577.351 | DR43: 8348314 | DS43: 12.961 | DT43: 187410.1
A44: Noreste | B44: Monterrey | C44: Sucursal Juventud | D44: 704308 | E44: Noreste|Sucursal Juventud|704308 | F44: Activa | G44: Sí | H44: Sí | I44: 12 | J44: 66259.866 | K44: 20478.736 | L44: 86738.602 | M44: 3681027 | N44: 960726 | O44: 2720301 | P44: 0 | Q44: 8590.2832 | R44: 3255.9797 | S44: 12862.529 | T44: 1300.4627 | U44: =IFERROR(INDEX('Rentabilidad datos'!$N$2:$N$61,MATCH($C44,'Rentabilidad datos'!$C$2:$C$61,0)),"") -> 17418.971 | V44: =IFERROR(INDEX('Rentabilidad datos'!$O$2:$O$61,MATCH($C44,'Rentabilidad datos'!$C$2:$C$61,0)),"") -> 1451.5809 | W44: =IFERROR(INDEX('Rentabilidad datos'!$M$2:$M$61,MATCH($C44,'Rentabilidad datos'!$C$2:$C$61,0)),"") -> 3282.4549 | X44: =IFERROR(INDEX('Rentabilidad datos'!$P$2:$P$61,MATCH($C44,'Rentabilidad datos'!$C$2:$C$61,0)),"") -> 0.44222418 | Y44: C2 | Z44: 45.925926 | AA44: 1 | AB44: 0.99939962 | AC44: 0.00060037593 | AD44: =_xlfn.XLOOKUP(Table1[[#This Row],[Ruta]],#REF!,#REF!) -> #REF! | AE44: =_xlfn.XLOOKUP(Table1[[#This Row],[Ruta]],#REF!,#REF!) -> #REF! | AF44: =_xlfn.XLOOKUP(Table1[[#This Row],[Ruta]],#REF!,#REF!) -> #REF! | AG44: =_xlfn.XLOOKUP(Table1[[#This Row],[Ruta]],#REF!,#REF!) -> #REF! | AH44: 0.26099401 | AI44: 0.73900599 | AJ44: 0 | AK44: 16120 | AL44: 11042 | AM44: 0.54565757 | AN44: 0.74419035 | AO44: 3200.3484 | AP44: 1600.1742 | AQ44: 0.78425398 | AR44: 3676641.2 | AS44: 532808.04 | AT44: 0.14491706 | AU44: 374405.65 | AV44: 0.0017032067 | AW44: 202 | AX44: 332.96877 | AY44: 366.04512 | AZ44: 33.076344 | BA44: Sí | BB44: 128323.7 | BC44: 502729.35 | BD44: Sí | BE44: 45.925926 | BF44: 48.897321 | BG44: No | BH44: 0.54565757 | BI44: 0.79215712 | BJ44: No | BK44: 202.66029 | BL44: 326.54714 | BM44: No | BN44: 0 | BO44: Verde - Con espacio | BP44: No | BQ44: 4234.5491 | BR44: 1046 | BS44: 100907 | BT44: 28947 | BU44: 3.4859225 | BV44: 27.673996 | BW44: 8697 | BX44: 7464 | BY44: 16161 | BZ44: 0.5582962 | CA44: 0.30044564 | CB44: 0.25785055 | CC44: 0.30510934 | CD44: 0.060558953 | CE44: 0 | CF44: 0.076035513 | CG44: 0 | CH44: 0 | CI44: 1.8730118 | CJ44: 0.59460692 | CK44: 319 | CL44: 824.33 | CM44: =CL44-CK44 -> 505.33 | CN44: 3.99 | CO44: 9.45 | CP44: =CO44-CN44 -> 5.46 | CQ44: 634.92 | CR44: 202.66 | CS44: =CQ44-CR44 -> 432.26 | CT44: No | CU44: 42.51 | CV44: 414 | CW44: 16161 | CX44: =((CW44-CY44)/BT44)*100 -> 54.083912 | CY44: 505.33 | CZ44: =((CW44)/BT44)*100 -> 55.82962 | DA44: =DB44/(CY44+BT44) -> 158.6706 | DB44: 4673219 | DC44: =DD44/(CY44+BT44) -> 4.0576851 | DD44: 119508.28 | DE44: 16161 | DF44: 54.34 | DG44: 431.3 | DH44: 55.83 | DI44: 272.684 | DJ44: 8011004 | DK44: 6.912 | DL44: 203069.5 | DM44: 16161 | DN44: 54.427 | DO44: 406.1 | DP44: 55.83 | DQ44: 266.472 | DR44: 7821780 | DS44: 6.751 | DT44: 198155.3
A45: Noreste | B45: Monterrey | C45: Sucursal Juventud | D45: 704309 | E45: Noreste|Sucursal Juventud|704309 | F45: Activa | G45: Sí | H45: Sí | I45: 12 | J45: 63068.572 | K45: 31975.405 | L45: 95043.977 | M45: 5259200 | N45: 947418 | O45: 4311782 | P45: 0 | Q45: 12007.302 | R45: 3255.9797 | S45: 12862.529 | T45: 1300.4627 | U45: =IFERROR(INDEX('Rentabilidad datos'!$N$2:$N$61,MATCH($C45,'Rentabilidad datos'!$C$2:$C$61,0)),"") -> 17418.971 | V45: =IFERROR(INDEX('Rentabilidad datos'!$O$2:$O$61,MATCH($C45,'Rentabilidad datos'!$C$2:$C$61,0)),"") -> 1451.5809 | W45: =IFERROR(INDEX('Rentabilidad datos'!$M$2:$M$61,MATCH($C45,'Rentabilidad datos'!$C$2:$C$61,0)),"") -> 3282.4549 | X45: =IFERROR(INDEX('Rentabilidad datos'!$P$2:$P$61,MATCH($C45,'Rentabilidad datos'!$C$2:$C$61,0)),"") -> 0.44222418 | Y45: C2 | Z45: 38.703226 | AA45: 1 | AB45: 1 | AC45: 0 | AD45: =_xlfn.XLOOKUP(Table1[[#This Row],[Ruta]],#REF!,#REF!) -> #REF! | AE45: =_xlfn.XLOOKUP(Table1[[#This Row],[Ruta]],#REF!,#REF!) -> #REF! | AF45: =_xlfn.XLOOKUP(Table1[[#This Row],[Ruta]],#REF!,#REF!) -> #REF! | AG45: =_xlfn.XLOOKUP(Table1[[#This Row],[Ruta]],#REF!,#REF!) -> #REF! | AH45: 0.18014489 | AI45: 0.81985511 | AJ45: 0 | AK45: 11998 | AL45: 11051 | AM45: 0.69786631 | AN45: 0.74419035 | AO45: 555.79578 | AP45: 277.89789 | AQ45: 0.9442322 | AR45: 5259198.1 | AS45: 132252.29 | AT45: 0.025146854 | AU45: 92934.04 | AV45: 0.00042276574 | AW45: 397 | AX45: 475.90246 | AY45: 366.04512 | AZ45: 0 | BA45: No | BB45: 0 | BC45: 92934.04 | BD45: Sí | BE45: 38.703226 | BF45: 48.897321 | BG45: No | BH45: 0.69786631 | BI45: 0.79215712 | BJ45: No | BK45: 216.99538 | BL45: 326.54714 | BM45: No | BN45: 0 | BO45: Verde - Con espacio | BP45: No | BQ45: 2135.2559 | BR45: 905 | BS45: 25849 | BT45: 9691 | BU45: 2.6673202 | BV45: 10.708287 | BW45: 758 | BX45: 7170 | BY45: 7928 | BZ45: 0.81807863 | CA45: 0.078216902 | CB45: 0.73986173 | CC45: 0.099267361 | CD45: 0.046641213 | CE45: 0 | CF45: 0.036012795 | CG45: 0 | CH45: 0 | CI45: 5.3386978 | CJ45: 6.3445394 | CK45: 229 | CL45: 702.82 | CM45: =CL45-CK45 -> 473.82 | CN45: 3.55 | CO45: 9.45 | CP45: =CO45-CN45 -> 5.9 | CQ45: 1481.48 | CR45: 217 | CS45: =CQ45-CR45 -> 1264.48 | CT45: No | CU45: 37.67 | CV45: 379 | CW45: 7928 | CX45: =((CW45-CY45)/BT45)*100 -> 76.918584 | CY45: 473.82 | CZ45: =((CW45)/BT45)*100 -> 81.807863 | DA45: =DB45/(CY45+BT45) -> 501.37558 | DB45: 5096392.5 | DC45: =DD45/(CY45+BT45) -> 12.39078 | DD45: 125950.05 | DE45: 7928 | DF45: 78.786 | DG45: 292.8 | DH45: 81.808 | DI45: 821.648 | DJ45: 8203196 | DK45: 20.019 | DL45: 199863.6 | DM45: 7928 | DN45: 79.309 | DO45: 242.1 | DP45: 81.808 | DQ45: 781.332 | DR45: 7761061 | DS45: 19.085 | DT45: 189569.8
A46: Noreste | B46: Monterrey | C46: Sucursal Juventud | D46: 704310 | E46: Noreste|Sucursal Juventud|704310 | F46: Activa | G46: Sí | H46: Sí | I46: 12 | J46: 69606.006 | K46: 18157.13 | L46: 87763.136 | M46: 3214267 | N46: 1045622 | O46: 2168612 | P46: 33 | Q46: 7321.7152 | R46: 3255.9797 | S46: 12862.529 | T46: 1300.4627 | U46: =IFERROR(INDEX('Rentabilidad datos'!$N$2:$N$61,MATCH($C46,'Rentabilidad datos'!$C$2:$C$61,0)),"") -> 17418.971 | V46: =IFERROR(INDEX('Rentabilidad datos'!$O$2:$O$61,MATCH($C46,'Rentabilidad datos'!$C$2:$C$61,0)),"") -> 1451.5809 | W46: =IFERROR(INDEX('Rentabilidad datos'!$M$2:$M$61,MATCH($C46,'Rentabilidad datos'!$C$2:$C$61,0)),"") -> 3282.4549 | X46: =IFERROR(INDEX('Rentabilidad datos'!$P$2:$P$61,MATCH($C46,'Rentabilidad datos'!$C$2:$C$61,0)),"") -> 0.44222418 | Y46: C2 | Z46: 43.225 | AA46: 1 | AB46: 0.98992554 | AC46: 0.010074459 | AD46: =_xlfn.XLOOKUP(Table1[[#This Row],[Ruta]],#REF!,#REF!) -> #REF! | AE46: =_xlfn.XLOOKUP(Table1[[#This Row],[Ruta]],#REF!,#REF!) -> #REF! | AF46: =_xlfn.XLOOKUP(Table1[[#This Row],[Ruta]],#REF!,#REF!) -> #REF! | AG46: =_xlfn.XLOOKUP(Table1[[#This Row],[Ruta]],#REF!,#REF!) -> #REF! | AH46: 0.32530652 | AI46: 0.67468322 | AJ46: 1.0266726e-05 | AK46: 12103 | AL46: 13244 | AM46: 0.75782864 | AN46: 0.74419035 | AO46: 0 | AP46: 0 | AQ46: 1.0942741 | AR46: 3214233 | AS46: 0 | AT46: 0 | AU46: 0 | AV46: 0 | AW46: 490 | AX46: 242.69352 | AY46: 366.04512 | AZ46: 123.3516 | BA46: Sí | BB46: 573991.65 | BC46: 573991.65 | BD46: Sí | BE46: 43.225 | BF46: 48.897321 | BG46: No | BH46: 0.75782864 | BI46: 0.79215712 | BJ46: No | BK46: 199.91603 | BL46: 326.54714 | BM46: No | BN46: 0 | BO46: Verde - Con espacio | BP46: No | BQ46: 850.07885 | BR46: 677 | BS46: 56363 | BT46: 15885 | BU46: 3.5481901 | BV46: 23.463811 | BW46: 647 | BX46: 3044 | BY46: 3691 | BZ46: 0.23235757 | CA46: 0.040730249 | CB46: 0.19162732 | CC46: 0.085426503 | CD46: 0.2011961 | CE46: 0 | CF46: 0.48101983 | CG46: 0 | CH46: 0 | CI46: 3.5129429 | CJ46: 0.40806912 | CK46: 227 | CL46: 434.73 | CM46: =CL46-CK46 -> 207.73 | CN46: 4.77 | CO46: 9.45 | CP46: =CO46-CN46 -> 4.68 | CQ46: 634.92 | CR46: 199.92 | CS46: =CQ46-CR46 -> 435 | CT46: No | CU46: 51.84 | CV46: 178 | CW46: 3691 | CX46: =((CW46-CY46)/BT46)*100 -> 21.928045 | CY46: 207.73 | CZ46: =((CW46)/BT46)*100 -> 23.235757 | DA46: =DB46/(CY46+BT46) -> 163.44554 | DB46: 2630285 | DC46: =DD46/(CY46+BT46) -> 3.6779844 | DD46: 59188.81 | DE46: 3691 | DF46: 22.113 | DG46: 178.3 | DH46: 23.236 | DI46: 508.846 | DJ46: 8173753 | DK46: 11.407 | DL46: 183235.7 | DM46: 3691 | DN46: 22.219 | DO46: 161.4 | DP46: 23.236 | DQ46: 500.687 | DR46: 8034243 | DS46: 11.211 | DT46: 179896.7
A47: Noreste | B47: Monterrey | C47: Sucursal Juventud | D47: 704311 | E47: Noreste|Sucursal Juventud|704311 | F47: Activa | G47: Sí | H47: Sí | I47: 12 | J47: 18841.318 | K47: 8740.107 | L47: 27581.425 | M47: 1376585 | N47: 296391 | O47: 1080150 | P47: 44 | Q47: 4664.5577 | R47: 3255.9797 | S47: 12862.529 | T47: 1300.4627 | U47: =IFERROR(INDEX('Rentabilidad datos'!$N$2:$N$61,MATCH($C47,'Rentabilidad datos'!$C$2:$C$61,0)),"") -> 17418.971 | V47: =IFERROR(INDEX('Rentabilidad datos'!$O$2:$O$61,MATCH($C47,'Rentabilidad datos'!$C$2:$C$61,0)),"") -> 1451.5809 | W47: =IFERROR(INDEX('Rentabilidad datos'!$M$2:$M$61,MATCH($C47,'Rentabilidad datos'!$C$2:$C$61,0)),"") -> 3282.4549 | X47: =IFERROR(INDEX('Rentabilidad datos'!$P$2:$P$61,MATCH($C47,'Rentabilidad datos'!$C$2:$C$61,0)),"") -> 0.44222418 | Y47: C2 | Z47: 45.931373 | AA47: 1 | AB47: 0.99874254 | AC47: 0.0012574596 | AD47: =_xlfn.XLOOKUP(Table1[[#This Row],[Ruta]],#REF!,#REF!) -> #REF! | AE47: =_xlfn.XLOOKUP(Table1[[#This Row],[Ruta]],#REF!,#REF!) -> #REF! | AF47: =_xlfn.XLOOKUP(Table1[[#This Row],[Ruta]],#REF!,#REF!) -> #REF! | AG47: =_xlfn.XLOOKUP(Table1[[#This Row],[Ruta]],#REF!,#REF!) -> #REF! | AH47: 0.2153089 | AI47: 0.78465914 | AJ47: 3.1963155e-05 | AK47: 9370 | AL47: 4162 | AM47: 0.41344717 | AN47: 0.74419035 | AO47: 3099.0635 | AP47: 1549.5318 | AQ47: 0.60955515 | AR47: 1376044.5 | AS47: 512307.72 | AT47: 0.37230461 | AU47: 360000.02 | AV47: 0.0016376741 | AW47: 206 | AX47: 330.62098 | AY47: 366.04512 | AZ47: 35.424135 | BA47: Sí | BB47: 51801.575 | BC47: 411801.59 | BD47: Sí | BE47: 45.931373 | BF47: 48.897321 | BG47: No | BH47: 0.41344717 | BI47: 0.79215712 | BJ47: No | BK47: 93.496355 | BL47: 326.54714 | BM47: No | BN47: 0 | BO47: Verde - Con espacio | BP47: No | BQ47: 4328.4101 | BR47: #N/A | BS47: #N/A | BT47: #N/A | BU47: #N/A | BV47: #N/A | BW47: #N/A | BX47: #N/A | BY47: #N/A | BZ47: #N/A | CA47: #N/A | CB47: #N/A | CC47: #N/A | CD47: #N/A | CE47: #N/A | CF47: #N/A | CG47: #N/A | CH47: #N/A | CI47: #N/A | CJ47: #N/A | CM47: =CL47-CK47 -> 0 | CP47: =CO47-CN47 -> 0 | CS47: =CQ47-CR47 -> 0 | CX47: =((CW47-CY47)/BT47)*100 -> #N/A | CZ47: =((CW47)/BT47)*100 -> #N/A | DA47: =DB47/(CY47+BT47) -> #N/A | DC47: =DD47/(CY47+BT47) -> #N/A
A48: Noreste | B48: Monterrey | C48: Sucursal Lincoln | D48: 705300 | E48: Noreste|Sucursal Lincoln|705300 | F48: Activa | G48: Sí | H48: Sí | I48: 27 | J48: 35142.985 | K48: 9592.7506 | L48: 44735.735 | M48: 1658582 | N48: 494162 | O48: 1164331 | P48: 89 | Q48: 4064.9272 | R48: 5020.3885 | S48: 27731.476 | T48: 2817.6692 | U48: =IFERROR(INDEX('Rentabilidad datos'!$N$2:$N$61,MATCH($C48,'Rentabilidad datos'!$C$2:$C$61,0)),"") -> 35569.534 | V48: =IFERROR(INDEX('Rentabilidad datos'!$O$2:$O$61,MATCH($C48,'Rentabilidad datos'!$C$2:$C$61,0)),"") -> 1368.059 | W48: =IFERROR(INDEX('Rentabilidad datos'!$M$2:$M$61,MATCH($C48,'Rentabilidad datos'!$C$2:$C$61,0)),"") -> 2318.2873 | X48: =IFERROR(INDEX('Rentabilidad datos'!$P$2:$P$61,MATCH($C48,'Rentabilidad datos'!$C$2:$C$61,0)),"") -> 0.59011623 | Y48: C1 | Z48: 85.376176 | AA48: 1 | AB48: 0.9974231 | AC48: 0.0025769 | AD48: =_xlfn.XLOOKUP(Table1[[#This Row],[Ruta]],#REF!,#REF!) -> #REF! | AE48: =_xlfn.XLOOKUP(Table1[[#This Row],[Ruta]],#REF!,#REF!) -> #REF! | AF48: =_xlfn.XLOOKUP(Table1[[#This Row],[Ruta]],#REF!,#REF!) -> #REF! | AG48: =_xlfn.XLOOKUP(Table1[[#This Row],[Ruta]],#REF!,#REF!) -> #REF! | AH48: 0.29794246 | AI48: 0.70200388 | AJ48: 5.3660295e-05 | AK48: 27235 | AL48: 9390 | AM48: 0.29058197 | AN48: 0.59461304 | AO48: 8280.2862 | AP48: 4140.1431 | AQ48: 0.49679248 | AR48: 1658490.3 | AS48: 731244.64 | AT48: 0.44090981 | AU48: 513847.58 | AV48: 0.0023375413 | AW48: 142 | AX48: 176.62303 | AY48: 377.06407 | AZ48: 200.44104 | BA48: Sí | BB48: 661292.91 | BC48: 1175140.5 | BD48: Sí | BE48: 85.376176 | BF48: 48.897321 | BG48: Sí | BH48: 0.29058197 | BI48: 0.79215712 | BJ48: No | BK48: 109.64641 | BL48: 326.54714 | BM48: No | BN48: 1 | BO48: Verde - Con espacio | BP48: No | BQ48: 1977.3388 | BR48: 1408 | BS48: 129165 | BT48: 35474 | BU48: 3.6411174 | BV48: 25.194602 | BW48: 852 | BX48: 11540 | BY48: 12392 | BZ48: 0.34932627 | CA48: 0.02401759 | CB48: 0.32530868 | CC48: 0.45213396 | CD48: 0.10492191 | CE48: 0 | CF48: 0.093617861 | CG48: 0 | CH48: 0 | CI48: 2.841327 | CJ48: 0.3948438 | CK48: 491 | CL48: 1144.06 | CM48: =CL48-CK48 -> 653.06 | CN48: 13.65 | CO48: 9.45 | CP48: =CO48-CN48 -> -4.2 | CQ48: 634.92 | CR48: 109.65 | CS48: =CQ48-CR48 -> 525.27 | CT48: Sí | CU48: 144.41 | CV48: 377 | CW48: 12392 | CX48: =((CW48-CY48)/BT48)*100 -> 33.091673 | CY48: 653.06 | CZ48: =((CW48)/BT48)*100 -> 34.932627 | DA48: =DB48/(CY48+BT48) -> 176.38037 | DB48: 6372104.3 | DC48: =DD48/(CY48+BT48) -> 5.2336384 | DD48: 189075.97 | DE48: 12392 | DF48: 33.092 | DG48: 653.1 | DH48: 34.933 | DI48: 225.605 | DJ48: 8150457 | DK48: 6.762 | DL48: 244275.1 | DM48: 12392 | DN48: 33.092 | DO48: 653.1 | DP48: 34.933 | DQ48: 225.605 | DR48: 8150457 | DS48: 6.762 | DT48: 244275.1
A49: Noreste | B49: Monterrey | C49: Sucursal Lincoln | D49: 705301 | E49: Noreste|Sucursal Lincoln|705301 | F49: Activa | G49: Sí | H49: Sí | I49: 27 | J49: 73104.03 | K49: 31546.921 | L49: 104650.95 | M49: 4892051 | N49: 1100522 | O49: 3791529 | P49: 0 | Q49: 11143.624 | R49: 5020.3885 | S49: 27731.476 | T49: 2817.6692 | U49: =IFERROR(INDEX('Rentabilidad datos'!$N$2:$N$61,MATCH($C49,'Rentabilidad datos'!$C$2:$C$61,0)),"") -> 35569.534 | V49: =IFERROR(INDEX('Rentabilidad datos'!$O$2:$O$61,MATCH($C49,'Rentabilidad datos'!$C$2:$C$61,0)),"") -> 1368.059 | W49: =IFERROR(INDEX('Rentabilidad datos'!$M$2:$M$61,MATCH($C49,'Rentabilidad datos'!$C$2:$C$61,0)),"") -> 2318.2873 | X49: =IFERROR(INDEX('Rentabilidad datos'!$P$2:$P$61,MATCH($C49,'Rentabilidad datos'!$C$2:$C$61,0)),"") -> 0.59011623 | Y49: C1 | Z49: 59.369021 | AA49: 1 | AB49: 1 | AC49: 0 | AD49: =_xlfn.XLOOKUP(Table1[[#This Row],[Ruta]],#REF!,#REF!) -> #REF! | AE49: =_xlfn.XLOOKUP(Table1[[#This Row],[Ruta]],#REF!,#REF!) -> #REF! | AF49: =_xlfn.XLOOKUP(Table1[[#This Row],[Ruta]],#REF!,#REF!) -> #REF! | AG49: =_xlfn.XLOOKUP(Table1[[#This Row],[Ruta]],#REF!,#REF!) -> #REF! | AH49: 0.22496127 | AI49: 0.77503873 | AJ49: 0 | AK49: 26063 | AL49: 16948 | AM49: 0.6502705 | AN49: 0.59461304 | AO49: 0 | AP49: 0 | AQ49: 0.6502705 | AR49: 4892050.8 | AS49: 0 | AT49: 0 | AU49: 0 | AV49: 0 | AW49: 490 | AX49: 288.65063 | AY49: 377.06407 | AZ49: 88.413445 | BA49: Sí | BB49: 526475.78 | BC49: 526475.78 | BD49: Sí | BE49: 59.369021 | BF49: 48.897321 | BG49: Sí | BH49: 0.6502705 | BI49: 0.79215712 | BJ49: No | BK49: 238.38485 | BL49: 326.54714 | BM49: No | BN49: 1 | BO49: Verde - Con espacio | BP49: No | BQ49: 460.61743 | BR49: 225 | BS49: 14045 | BT49: 4537 | BU49: 3.0956579 | BV49: 20.164444 | BW49: 3202 | BX49: 898 | BY49: 4100 | BZ49: 0.90368085 | CA49: 0.7057527 | CB49: 0.19792815 | CC49: 0.096319154 | CD49: 0 | CE49: 0 | CF49: 0 | CG49: 0 | CH49: 0 | CI49: 1.1391954 | CJ49: 0.9255963 | CK49: 292 | CL49: 728.75 | CM49: =CL49-CK49 -> 436.75 | CN49: 4.13 | CO49: 9.45 | CP49: =CO49-CN49 -> 5.32 | CQ49: 634.92 | CR49: 238.38 | CS49: =CQ49-CR49 -> 396.54 | CT49: No | CU49: 45.89 | CV49: 295 | CW49: 4100 | CX49: =((CW49-CY49)/BT49)*100 -> 80.74168 | CY49: 436.75 | CZ49: =((CW49)/BT49)*100 -> 90.368085 | DA49: =DB49/(CY49+BT49) -> 739.96448 | DB49: 3680398.3 | DC49: =DD49/(CY49+BT49) -> 16.32188 | DD49: 81180.95 | DE49: 4100 | DF49: 82.961 | DG49: 336.1 | DH49: 90.368 | DI49: 1391.428 | DJ49: 6780508 | DK49: 30.116 | DL49: 146756.3 | DM49: 4100 | DN49: 83.905 | DO49: 293.2 | DP49: 90.368 | DQ49: 1334.384 | DR49: 6445406 | DS49: 28.784 | DT49: 139035.6
A50: Noreste | B50: Monterrey | C50: Sucursal Lincoln | D50: 705302 | E50: Noreste|Sucursal Lincoln|705302 | F50: Activa | G50: Sí | H50: Sí | I50: 27 | J50: 18658.153 | K50: 4179.4081 | L50: 22837.561 | M50: 739807 | N50: 265084 | O50: 474442 | P50: 281 | Q50: 1889.4016 | R50: 5020.3885 | S50: 27731.476 | T50: 2817.6692 | U50: =IFERROR(INDEX('Rentabilidad datos'!$N$2:$N$61,MATCH($C50,'Rentabilidad datos'!$C$2:$C$61,0)),"") -> 35569.534 | V50: =IFERROR(INDEX('Rentabilidad datos'!$O$2:$O$61,MATCH($C50,'Rentabilidad datos'!$C$2:$C$61,0)),"") -> 1368.059 | W50: =IFERROR(INDEX('Rentabilidad datos'!$M$2:$M$61,MATCH($C50,'Rentabilidad datos'!$C$2:$C$61,0)),"") -> 2318.2873 | X50: =IFERROR(INDEX('Rentabilidad datos'!$P$2:$P$61,MATCH($C50,'Rentabilidad datos'!$C$2:$C$61,0)),"") -> 0.59011623 | Y50: C1 | Z50: 51.376667 | AA50: 1 | AB50: 0.8223807 | AC50: 0.1776193 | AD50: =_xlfn.XLOOKUP(Table1[[#This Row],[Ruta]],#REF!,#REF!) -> #REF! | AE50: =_xlfn.XLOOKUP(Table1[[#This Row],[Ruta]],#REF!,#REF!) -> #REF! | AF50: =_xlfn.XLOOKUP(Table1[[#This Row],[Ruta]],#REF!,#REF!) -> #REF! | AG50: =_xlfn.XLOOKUP(Table1[[#This Row],[Ruta]],#REF!,#REF!) -> #REF! | AH50: 0.35831507 | AI50: 0.6413051 | AJ50: 0.00037982879 | AK50: 15413 | AL50: 2184 | AM50: 0.11840654 | AN50: 0.59461304 | AO50: 7339.7708 | AP50: 3669.8854 | AQ50: 0.37980182 | AR50: 738756.02 | AS50: 1241369 | AT50: 1.6803505 | AU50: 872313.37 | AV50: 0.0039682361 | AW50: 62 | AX50: 338.25825 | AY50: 377.06407 | AZ50: 38.805822 | BA50: Sí | BB50: 29777.7 | BC50: 902091.07 | BD50: Sí | BE50: 51.376667 | BF50: 48.897321 | BG50: Sí | BH50: 0.11840654 | BI50: 0.79215712 | BJ50: No | BK50: 58.408084 | BL50: 326.54714 | BM50: No | BN50: 1 | BO50: Verde - Con espacio | BP50: No | BQ50: 6996.2124 | BR50: 2372 | BS50: 234591 | BT50: 66319 | BU50: 3.5373121 | BV50: 27.959106 | BW50: 0 | BX50: 7 | BY50: 7 | BZ50: 0.00010555045 | CA50: 0 | CB50: 0.00010555045 | CC50: 0.032841267 | CD50: 0.13335545 | CE50: 0.047377071 | CF50: 0.78609448 | CG50: 0.00022617953 | CH50: 0 | CI50: 4.9149371 | CJ50: 0.35380726 | CK50: 325 | CL50: 372.73 | CM50: =CL50-CK50 -> 47.73 | CN50: 5.48 | CO50: 9.45 | CP50: =CO50-CN50 -> 3.97 | CQ50: 662.01 | CR50: 58.41 | CS50: =CQ50-CR50 -> 603.6 | CT50: No | CU50: 57.95 | CV50: 0 | CW50: 7 | CX50: =((CW50-CY50)/BT50)*100 -> -0.061415281 | CY50: 47.73 | CZ50: =((CW50)/BT50)*100 -> 0.010555045 | DA50: =DB50/(CY50+BT50) -> 4.7009169 | DB50: 311984.48 | DC50: =DD50/(CY50+BT50) -> 0.1627231 | DD50: 10799.4 | DE50: 7 | DF50: -0.039 | DG50: 32.8 | DH50: 0.011 | DI50: 20.213 | DJ50: 1341181 | DK50: 0.609 | DL50: 40433.3 | DM50: 7 | DN50: -0.03 | DO50: 27.1 | DP50: 0.011 | DQ50: 19.835 | DR50: 1315998 | DS50: 0.596 | DT50: 39561.6
A51: Noreste | B51: Monterrey | C51: Sucursal Lincoln | D51: 705303 | E51: Noreste|Sucursal Lincoln|705303 | F51: Activa | G51: Sí | H51: Sí | I51: 27 | J51: 57471.478 | K51: 27857.362 | L51: 85328.84 | M51: 4570959 | N51: 795333 | O51: 3775570 | P51: 56 | Q51: 10459.734 | R51: 5020.3885 | S51: 27731.476 | T51: 2817.6692 | U51: =IFERROR(INDEX('Rentabilidad datos'!$N$2:$N$61,MATCH($C51,'Rentabilidad datos'!$C$2:$C$61,0)),"") -> 35569.534 | V51: =IFERROR(INDEX('Rentabilidad datos'!$O$2:$O$61,MATCH($C51,'Rentabilidad datos'!$C$2:$C$61,0)),"") -> 1368.059 | W51: =IFERROR(INDEX('Rentabilidad datos'!$M$2:$M$61,MATCH($C51,'Rentabilidad datos'!$C$2:$C$61,0)),"") -> 2318.2873 | X51: =IFERROR(INDEX('Rentabilidad datos'!$P$2:$P$61,MATCH($C51,'Rentabilidad datos'!$C$2:$C$61,0)),"") -> 0.59011623 | Y51: C1 | Z51: 73.688787 | AA51: 1 | AB51: 0.99701288 | AC51: 0.0029871193 | AD51: =_xlfn.XLOOKUP(Table1[[#This Row],[Ruta]],#REF!,#REF!) -> #REF! | AE51: =_xlfn.XLOOKUP(Table1[[#This Row],[Ruta]],#REF!,#REF!) -> #REF! | AF51: =_xlfn.XLOOKUP(Table1[[#This Row],[Ruta]],#REF!,#REF!) -> #REF! | AG51: =_xlfn.XLOOKUP(Table1[[#This Row],[Ruta]],#REF!,#REF!) -> #REF! | AH51: 0.17399697 | AI51: 0.82599078 | AJ51: 1.2251258e-05 | AK51: 32202 | AL51: 17766 | AM51: 0.55170486 | AN51: 0.59461304 | AO51: 1381.7292 | AP51: 690.8646 | AQ51: 0.57315895 | AR51: 4570903.9 | AS51: 177748.27 | AT51: 0.038886896 | AU51: 124904.19 | AV51: 0.00056820097 | AW51: 374 | AX51: 257.28379 | AY51: 377.06407 | AZ51: 119.78028 | BA51: Sí | BB51: 747681.45 | BC51: 872585.64 | BD51: Sí | BE51: 73.688787 | BF51: 48.897321 | BG51: Sí | BH51: 0.55170486 | BI51: 0.79215712 | BJ51: No | BK51: 195.2605 | BL51: 326.54714 | BM51: No | BN51: 1 | BO51: Verde - Con espacio | BP51: No | BQ51: 0 | BR51: 637 | BS51: 48970 | BT51: 15208 | BU51: 3.2200158 | BV51: 23.874411 | BW51: 4551 | BX51: 4001 | BY51: 8552 | BZ51: 0.56233561 | CA51: 0.29925039 | CB51: 0.26308522 | CC51: 0.12605208 | CD51: 0.2000263 | CE51: 0 | CF51: 0.11158601 | CG51: 0 | CH51: 0 | CI51: 2.4096386 | CJ51: 0.59219931 | CK51: 338 | CL51: 765.66 | CM51: =CL51-CK51 -> 427.66 | CN51: 4.75 | CO51: 9.45 | CP51: =CO51-CN51 -> 4.7 | CQ51: 634.92 | CR51: 195.26 | CS51: =CQ51-CR51 -> 439.66 | CT51: No | CU51: 51.36 | CV51: 378 | CW51: 8552 | CX51: =((CW51-CY51)/BT51)*100 -> 53.421489 | CY51: 427.66 | CZ51: =((CW51)/BT51)*100 -> 56.233561 | DA51: =DB51/(CY51+BT51) -> 285.61837 | DB51: 4465831.8 | DC51: =DD51/(CY51+BT51) -> 6.1032972 | DD51: 95429.08 | DE51: 8552 | DF51: 54.054 | DG51: 331.4 | DH51: 56.234 | DI51: 481.325 | DJ51: 7479498 | DK51: 10.196 | DL51: 158432.6 | DM51: 8552 | DN51: 54.12 | DO51: 321.4 | DP51: 56.234 | DQ51: 477.407 | DR51: 7413828 | DS51: 10.1 | DT51: 156848.2
A52: Noreste | B52: Monterrey | C52: Sucursal Lincoln | D52: 705304 | E52: Noreste|Sucursal Lincoln|705304 | F52: Activa | G52: Sí | H52: Sí | I52: 27 | J52: 78884.148 | K52: 22573.002 | L52: 101457.15 | M52: 4208126 | N52: 1171264 | O52: 3036134 | P52: 728 | Q52: 9720.0851 | R52: 5020.3885 | S52: 27731.476 | T52: 2817.6692 | U52: =IFERROR(INDEX('Rentabilidad datos'!$N$2:$N$61,MATCH($C52,'Rentabilidad datos'!$C$2:$C$61,0)),"") -> 35569.534 | V52: =IFERROR(INDEX('Rentabilidad datos'!$O$2:$O$61,MATCH($C52,'Rentabilidad datos'!$C$2:$C$61,0)),"") -> 1368.059 | W52: =IFERROR(INDEX('Rentabilidad datos'!$M$2:$M$61,MATCH($C52,'Rentabilidad datos'!$C$2:$C$61,0)),"") -> 2318.2873 | X52: =IFERROR(INDEX('Rentabilidad datos'!$P$2:$P$61,MATCH($C52,'Rentabilidad datos'!$C$2:$C$61,0)),"") -> 0.59011623 | Y52: C1 | Z52: 45.867314 | AA52: 1 | AB52: 0.99961147 | AC52: 0.00038853399 | AD52: =_xlfn.XLOOKUP(Table1[[#This Row],[Ruta]],#REF!,#REF!) -> #REF! | AE52: =_xlfn.XLOOKUP(Table1[[#This Row],[Ruta]],#REF!,#REF!) -> #REF! | AF52: =_xlfn.XLOOKUP(Table1[[#This Row],[Ruta]],#REF!,#REF!) -> #REF! | AG52: =_xlfn.XLOOKUP(Table1[[#This Row],[Ruta]],#REF!,#REF!) -> #REF! | AH52: 0.27833387 | AI52: 0.72149313 | AJ52: 0.00017299862 | AK52: 14173 | AL52: 10364 | AM52: 0.49721301 | AN52: 0.59461304 | AO52: 1380.4507 | AP52: 690.22533 | AQ52: 0.77994958 | AR52: 4208796.8 | AS52: 280298.94 | AT52: 0.066598353 | AU52: 196966.82 | AV52: 0.0008960207 | AW52: 314 | AX52: 406.09773 | AY52: 377.06407 | AZ52: 0 | BA52: No | BB52: 0 | BC52: 196966.82 | BD52: Sí | BE52: 45.867314 | BF52: 48.897321 | BG52: No | BH52: 0.49721301 | BI52: 0.79215712 | BJ52: No | BK52: 234.31212 | BL52: 326.54714 | BM52: No | BN52: 0 | BO52: Verde - Con espacio | BP52: No | BQ52: 2089.0536 | BR52: 186 | BS52: 16460 | BT52: 5072 | BU52: 3.2452681 | BV52: 27.268817 | BW52: 4905 | BX52: 167 | BY52: 5072 | BZ52: 1 | CA52: 0.96707413 | CB52: 0.032925868 | CC52: 0 | CD52: 0 | CE52: 0 | CF52: 0 | CG52: 0 | CH52: 0 | CI52: 0.24301337 | CJ52: 0.97205346 | CK52: 261 | CL52: 564.75 | CM52: =CL52-CK52 -> 303.75 | CN52: 4.68 | CO52: 9.45 | CP52: =CO52-CN52 -> 4.77 | CQ52: 634.92 | CR52: 234.31 | CS52: =CQ52-CR52 -> 400.61 | CT52: No | CU52: 52.33 | CV52: 374 | CW52: 4905 | CX52: =((CW52-CY52)/BT52)*100 -> 90.718651 | CY52: 303.75 | CZ52: =((CW52)/BT52)*100 -> 96.707413 | DA52: =DB52/(CY52+BT52) -> 485.49427 | DB52: 2609895.8 | DC52: =DD52/(CY52+BT52) -> 12.371833 | DD52: 66507.88 | DE52: 4905 | DF52: 91.939 | DG52: 241.9 | DH52: 96.707 | DI52: 1071.071 | DJ52: 5691538 | DK52: 27.165 | DL52: 144352.4 | DM52: 4905 | DN52: 92.677 | DO52: 204.4 | DP52: 96.707 | DQ52: 1027.599 | DR52: 5422072 | DS52: 26.078 | DT52: 137601.5
A53: Noreste | B53: Monterrey | C53: Sucursal Lincoln | D53: 705305 | E53: Noreste|Sucursal Lincoln|705305 | F53: Activa | G53: Sí | H53: Sí | I53: 27 | J53: 54516.185 | K53: 17950.061 | L53: 72466.246 | M53: 3195045 | N53: 787725 | O53: 2407165 | P53: 155 | Q53: 7246.4627 | R53: 5020.3885 | S53: 27731.476 | T53: 2817.6692 | U53: =IFERROR(INDEX('Rentabilidad datos'!$N$2:$N$61,MATCH($C53,'Rentabilidad datos'!$C$2:$C$61,0)),"") -> 35569.534 | V53: =IFERROR(INDEX('Rentabilidad datos'!$O$2:$O$61,MATCH($C53,'Rentabilidad datos'!$C$2:$C$61,0)),"") -> 1368.059 | W53: =IFERROR(INDEX('Rentabilidad datos'!$M$2:$M$61,MATCH($C53,'Rentabilidad datos'!$C$2:$C$61,0)),"") -> 2318.2873 | X53: =IFERROR(INDEX('Rentabilidad datos'!$P$2:$P$61,MATCH($C53,'Rentabilidad datos'!$C$2:$C$61,0)),"") -> 0.59011623 | Y53: C1 | Z53: 69.974943 | AA53: 1 | AB53: 0.99802851 | AC53: 0.0019714902 | AD53: =_xlfn.XLOOKUP(Table1[[#This Row],[Ruta]],#REF!,#REF!) -> #REF! | AE53: =_xlfn.XLOOKUP(Table1[[#This Row],[Ruta]],#REF!,#REF!) -> #REF! | AF53: =_xlfn.XLOOKUP(Table1[[#This Row],[Ruta]],#REF!,#REF!) -> #REF! | AG53: =_xlfn.XLOOKUP(Table1[[#This Row],[Ruta]],#REF!,#REF!) -> #REF! | AH53: 0.24654582 | AI53: 0.75340566 | AJ53: 4.8512619e-05 | AK53: 30719 | AL53: 7324 | AM53: 0.23841922 | AN53: 0.59461304 | AO53: 10941.918 | AP53: 5470.959 | AQ53: 0.41651613 | AR53: 3181197.1 | AS53: 2376324.3 | AT53: 0.74699058 | AU53: 1669849.5 | AV53: 0.0075963034 | AW53: 11 | AX53: 434.35242 | AY53: 377.06407 | AZ53: 0 | BA53: No | BB53: 0 | BC53: 1669849.5 | BD53: Sí | BE53: 69.974943 | BF53: 48.897321 | BG53: Sí | BH53: 0.23841922 | BI53: 0.79215712 | BJ53: No | BK53: 165.07117 | BL53: 326.54714 | BM53: No | BN53: 1 | BO53: Verde - Con espacio | BP53: No | BQ53: 10553.832 | BR53: 867 | BS53: 52549 | BT53: 16152 | BU53: 3.2534052 | BV53: 18.629758 | BW53: 276 | BX53: 2193 | BY53: 2469 | BZ53: 0.15286033 | CA53: 0.017087667 | CB53: 0.13577266 | CC53: 0.058940069 | CD53: 0.0055101535 | CE53: 0 | CF53: 0.78268945 | CG53: 0 | CH53: 0 | CI53: 3.8440313 | CJ53: 1.2369408 | CK53: 206 | CL53: 298.28 | CM53: =CL53-CK53 -> 92.28 | CN53: 8.43 | CO53: 9.45 | CP53: =CO53-CN53 -> 1.02 | CQ53: 846.56 | CR53: 165.07 | CS53: =CQ53-CR53 -> 681.49 | CT53: No | CU53: 89.33 | CV53: 217 | CW53: 2469 | CX53: =((CW53-CY53)/BT53)*100 -> 14.71471 | CY53: 92.28 | CZ53: =((CW53)/BT53)*100 -> 15.286033 | DA53: =DB53/(CY53+BT53) -> 83.58579 | DB53: 1357791 | DC53: =DD53/(CY53+BT53) -> 2.619101 | DD53: 42545.41 | DE53: 2469 | DF53: 14.887 | DG53: 64.5 | DH53: 15.286 | DI53: 202.609 | DJ53: 3285606 | DK53: 6.079 | DL53: 98585.3 | DM53: 2469 | DN53: 14.957 | DO53: 53.1 | DP53: 15.286 | DQ53: 198.231 | DR53: 3212344 | DS53: 5.973 | DT53: 96794.6
A54: Noreste | B54: Monterrey | C54: Sucursal Lincoln | D54: 705306 | E54: Noreste|Sucursal Lincoln|705306 | F54: Activa | G54: Sí | H54: Sí | I54: 27 | J54: 45114.899 | K54: 26497.196 | L54: 71612.095 | M54: 4085503 | N54: 631751 | O54: 3453752 | P54: 0 | Q54: 9330.2167 | R54: 5020.3885 | S54: 27731.476 | T54: 2817.6692 | U54: =IFERROR(INDEX('Rentabilidad datos'!$N$2:$N$61,MATCH($C54,'Rentabilidad datos'!$C$2:$C$61,0)),"") -> 35569.534 | V54: =IFERROR(INDEX('Rentabilidad datos'!$O$2:$O$61,MATCH($C54,'Rentabilidad datos'!$C$2:$C$61,0)),"") -> 1368.059 | W54: =IFERROR(INDEX('Rentabilidad datos'!$M$2:$M$61,MATCH($C54,'Rentabilidad datos'!$C$2:$C$61,0)),"") -> 2318.2873 | X54: =IFERROR(INDEX('Rentabilidad datos'!$P$2:$P$61,MATCH($C54,'Rentabilidad datos'!$C$2:$C$61,0)),"") -> 0.59011623 | Y54: C1 | Z54: 54.586758 | AA54: 1 | AB54: 0.99777922 | AC54: 0.0022207792 | AD54: =_xlfn.XLOOKUP(Table1[[#This Row],[Ruta]],#REF!,#REF!) -> #REF! | AE54: =_xlfn.XLOOKUP(Table1[[#This Row],[Ruta]],#REF!,#REF!) -> #REF! | AF54: =_xlfn.XLOOKUP(Table1[[#This Row],[Ruta]],#REF!,#REF!) -> #REF! | AG54: =_xlfn.XLOOKUP(Table1[[#This Row],[Ruta]],#REF!,#REF!) -> #REF! | AH54: 0.15463237 | AI54: 0.84536763 | AJ54: 0 | AK54: 23909 | AL54: 11220 | AM54: 0.46927935 | AN54: 0.59461304 | AO54: 2996.6032 | AP54: 1498.3016 | AQ54: 0.5319462 | AR54: 4086634.9 | AS54: 545722.97 | AT54: 0.13353847 | AU54: 383481 | AV54: 0.0017444914 | AW54: 197 | AX54: 364.22771 | AY54: 377.06407 | AZ54: 12.836363 | BA54: Sí | BB54: 50603.024 | BC54: 434084.03 | BD54: Sí | BE54: 54.586758 | BF54: 48.897321 | BG54: Sí | BH54: 0.46927935 | BI54: 0.79215712 | BJ54: No | BK54: 163.49793 | BL54: 326.54714 | BM54: No | BN54: 1 | BO54: Verde - Con espacio | BP54: No | BQ54: 4147.735 | BR54: 532 | BS54: 39765 | BT54: 11391 | BU54: 3.4909139 | BV54: 21.411654 | BW54: 3115 | BX54: 2902 | BY54: 6017 | BZ54: 0.52822404 | CA54: 0.2734615 | CB54: 0.25476253 | CC54: 0.065402511 | CD54: 0 | CE54: 0 | CF54: 0.40637345 | CG54: 0 | CH54: 0 | CI54: 3.5458318 | CJ54: 0.5281026 | CK54: 179 | CL54: 500.65 | CM54: =CL54-CK54 -> 321.65 | CN54: 3.37 | CO54: 9.45 | CP54: =CO54-CN54 -> 6.08 | CQ54: 634.92 | CR54: 163.5 | CS54: =CQ54-CR54 -> 471.42 | CT54: No | CU54: 35.78 | CV54: 218 | CW54: 4879 | CX54: =((CW54-CY54)/BT54)*100 -> 40.00834 | CY54: 321.65 | CZ54: =((CW54)/BT54)*100 -> 42.83206 | DA54: =DB54/(CY54+BT54) -> 258.08173 | DB54: 3022821 | DC54: =DD54/(CY54+BT54) -> 4.9720644 | DD54: 58236.05 | DE54: 4879 | DF54: 40.686 | DG54: 244.5 | DH54: 42.832 | DI54: 521.578 | DJ54: 6068811 | DK54: 9.952 | DL54: 115797.6 | DM54: 4879 | DN54: 40.811 | DO54: 230.3 | DP54: 42.832 | DQ54: 511.565 | DR54: 5945030 | DS54: 9.766 | DT54: 113494.4
A55: Noreste | B55: Monterrey | C55: Sucursal Lincoln | D55: 705307 | E55: Noreste|Sucursal Lincoln|705307 | F55: Activa | G55: Sí | H55: Sí | I55: 27 | J55: 87443.58 | K55: 38090.267 | L55: 125533.85 | M55: 6374281 | N55: 1292789 | O55: 5081308 | P55: 184 | Q55: 14486.573 | R55: 5020.3885 | S55: 27731.476 | T55: 2817.6692 | U55: =IFERROR(INDEX('Rentabilidad datos'!$N$2:$N$61,MATCH($C55,'Rentabilidad datos'!$C$2:$C$61,0)),"") -> 35569.534 | V55: =IFERROR(INDEX('Rentabilidad datos'!$O$2:$O$61,MATCH($C55,'Rentabilidad datos'!$C$2:$C$61,0)),"") -> 1368.059 | W55: =IFERROR(INDEX('Rentabilidad datos'!$M$2:$M$61,MATCH($C55,'Rentabilidad datos'!$C$2:$C$61,0)),"") -> 2318.2873 | X55: =IFERROR(INDEX('Rentabilidad datos'!$P$2:$P$61,MATCH($C55,'Rentabilidad datos'!$C$2:$C$61,0)),"") -> 0.59011623 | Y55: C1 | Z55: 41.996785 | AA55: 1 | AB55: 0.98964448 | AC55: 0.010355521 | AD55: =_xlfn.XLOOKUP(Table1[[#This Row],[Ruta]],#REF!,#REF!) -> #REF! | AE55: =_xlfn.XLOOKUP(Table1[[#This Row],[Ruta]],#REF!,#REF!) -> #REF! | AF55: =_xlfn.XLOOKUP(Table1[[#This Row],[Ruta]],#REF!,#REF!) -> #REF! | AG55: =_xlfn.XLOOKUP(Table1[[#This Row],[Ruta]],#REF!,#REF!) -> #REF! | AH55: 0.20281331 | AI55: 0.79715783 | AJ55: 2.8866001e-05 | AK55: 13061 | AL55: 16348 | AM55: 0.84411607 | AN55: 0.59461304 | AO55: 0 | AP55: 0 | AQ55: 1.2516653 | AR55: 6374092.3 | AS55: 0 | AT55: 0 | AU55: 0 | AV55: 0 | AW55: 490 | AX55: 389.90044 | AY55: 377.06407 | AZ55: 0 | BA55: No | BB55: 0 | BC55: 0 | BD55: Sí | BE55: 41.996785 | BF55: 48.897321 | BG55: No | BH55: 0.84411607 | BI55: 0.79215712 | BJ55: Sí | BK55: 285.3042 | BL55: 326.54714 | BM55: No | BN55: 1 | BO55: Verde - Con espacio | BP55: No | BQ55: 0 | BR55: 184 | BS55: 12240 | BT55: 4324 | BU55: 2.8307123 | BV55: 23.5 | BW55: 2698 | BX55: 1626 | BY55: 4324 | BZ55: 1 | CA55: 0.6239593 | CB55: 0.3760407 | CC55: 0 | CD55: 0 | CE55: 0 | CF55: 0 | CG55: 0 | CH55: 0 | CI55: 0.81699346 | CJ55: 1.6339869 | CK55: 228 | CL55: 702.54 | CM55: =CL55-CK55 -> 474.54 | CN55: 3.49 | CO55: 9.45 | CP55: =CO55-CN55 -> 5.96 | CQ55: 1481.48 | CR55: 285.3 | CS55: =CQ55-CR55 -> 1196.18 | CT55: No | CU55: 37.32 | CV55: 354 | CW55: 4324 | CX55: =((CW55-CY55)/BT55)*100 -> 89.025439 | CY55: 474.54 | CZ55: =((CW55)/BT55)*100 -> 100 | DA55: =DB55/(CY55+BT55) -> 811.49792 | DB55: 3894005.2 | DC55: =DD55/(CY55+BT55) -> 17.981015 | DD55: 86282.62 | DE55: 4324 | DF55: 92.796 | DG55: 311.5 | DH55: 100 | DI55: 1530.216 | DJ55: 7093299 | DK55: 33.805 | DL55: 156703.3 | DM55: 4324 | DN55: 93.947 | DO55: 261.7 | DP55: 100 | DQ55: 1459.532 | DR55: 6693037 | DS55: 32.215 | DT55: 147731.4
A56: Noreste | B56: Monterrey | C56: Sucursal Lincoln | D56: 705308 | E56: Noreste|Sucursal Lincoln|705308 | F56: Activa | G56: Sí | H56: Sí | I56: 27 | J56: 44671.077 | K56: 23088.305 | L56: 67759.381 | M56: 3867134 | N56: 688574 | O56: 3178560 | P56: 0 | Q56: 8890.7723 | R56: 5020.3885 | S56: 27731.476 | T56: 2817.6692 | U56: =IFERROR(INDEX('Rentabilidad datos'!$N$2:$N$61,MATCH($C56,'Rentabilidad datos'!$C$2:$C$61,0)),"") -> 35569.534 | V56: =IFERROR(INDEX('Rentabilidad datos'!$O$2:$O$61,MATCH($C56,'Rentabilidad datos'!$C$2:$C$61,0)),"") -> 1368.059 | W56: =IFERROR(INDEX('Rentabilidad datos'!$M$2:$M$61,MATCH($C56,'Rentabilidad datos'!$C$2:$C$61,0)),"") -> 2318.2873 | X56: =IFERROR(INDEX('Rentabilidad datos'!$P$2:$P$61,MATCH($C56,'Rentabilidad datos'!$C$2:$C$61,0)),"") -> 0.59011623 | Y56: C1 | Z56: 49.227586 | AA56: 1 | AB56: 0.99954902 | AC56: 0.00045097998 | AD56: =_xlfn.XLOOKUP(Table1[[#This Row],[Ruta]],#REF!,#REF!) -> #REF! | AE56: =_xlfn.XLOOKUP(Table1[[#This Row],[Ruta]],#REF!,#REF!) -> #REF! | AF56: =_xlfn.XLOOKUP(Table1[[#This Row],[Ruta]],#REF!,#REF!) -> #REF! | AG56: =_xlfn.XLOOKUP(Table1[[#This Row],[Ruta]],#REF!,#REF!) -> #REF! | AH56: 0.17805796 | AI56: 0.82194204 | AJ56: 0 | AK56: 21414 | AL56: 12637 | AM56: 0.59012795 | AN56: 0.59461304 | AO56: 96.043698 | AP56: 48.021849 | AQ56: 0.5923705 | AR56: 3867486 | AS56: 14696.829 | AT56: 0.0038000988 | AU56: 10327.501 | AV56: 4.6980781e-05 | AW56: 472 | AX56: 306.04463 | AY56: 377.06407 | AZ56: 71.019445 | BA56: Sí | BB56: 315328.25 | BC56: 325655.76 | BD56: Sí | BE56: 49.227586 | BF56: 48.897321 | BG56: Sí | BH56: 0.59012795 | BI56: 0.79215712 | BJ56: No | BK56: 155.76869 | BL56: 326.54714 | BM56: No | BN56: 1 | BO56: Verde - Con espacio | BP56: No | BQ56: 4295.5568 | BR56: 682 | BS56: 44725 | BT56: 14732 | BU56: 3.0359082 | BV56: 21.601173 | BW56: 765 | BX56: 8636 | BY56: 9401 | BZ56: 0.63813467 | CA56: 0.051927776 | CB56: 0.5862069 | CC56: 0.12150421 | CD56: 0 | CE56: 0.0039370079 | CF56: 0.23642411 | CG56: 0 | CH56: 0 | CI56: 2.4147568 | CJ56: 1.4533259 | CK56: 222 | CL56: 608.22 | CM56: =CL56-CK56 -> 386.22 | CN56: 3.83 | CO56: 9.45 | CP56: =CO56-CN56 -> 5.62 | CQ56: 634.92 | CR56: 155.77 | CS56: =CQ56-CR56 -> 479.15 | CT56: No | CU56: 41.21 | CV56: 357 | CW56: 6796 | CX56: =((CW56-CY56)/BT56)*100 -> 43.509232 | CY56: 386.22 | CZ56: =((CW56)/BT56)*100 -> 46.130872 | DA56: =DB56/(CY56+BT56) -> 247.29368 | DB56: 3738640.2 | DC56: =DD56/(CY56+BT56) -> 5.5297376 | DD56: 83599.79 | DE56: 6796 | DF56: 44.271 | DG56: 274 | DH56: 46.131 | DI56: 391.657 | DJ56: 5877215 | DK56: 8.877 | DL56: 133212.2 | DM56: 6796 | DN56: 44.397 | DO56: 255.5 | DP56: 46.131 | DQ56: 382.308 | DR56: 5729838 | DS56: 8.677 | DT56: 130049.5
A57: Noreste | B57: Monterrey | C57: Sucursal Lincoln | D57: 705309 | E57: Noreste|Sucursal Lincoln|705309 | F57: Activa | G57: Sí | H57: Sí | I57: 27 | J57: 49852.527 | K57: 15067.109 | L57: 64919.636 | M57: 2861926 | N57: 748252 | O57: 2112909 | P57: 765 | Q57: 6716.3393 | R57: 5020.3885 | S57: 27731.476 | T57: 2817.6692 | U57: =IFERROR(INDEX('Rentabilidad datos'!$N$2:$N$61,MATCH($C57,'Rentabilidad datos'!$C$2:$C$61,0)),"") -> 35569.534 | V57: =IFERROR(INDEX('Rentabilidad datos'!$O$2:$O$61,MATCH($C57,'Rentabilidad datos'!$C$2:$C$61,0)),"") -> 1368.059 | W57: =IFERROR(INDEX('Rentabilidad datos'!$M$2:$M$61,MATCH($C57,'Rentabilidad datos'!$C$2:$C$61,0)),"") -> 2318.2873 | X57: =IFERROR(INDEX('Rentabilidad datos'!$P$2:$P$61,MATCH($C57,'Rentabilidad datos'!$C$2:$C$61,0)),"") -> 0.59011623 | Y57: C1 | Z57: 41.894531 | AA57: 1 | AB57: 0.99967574 | AC57: 0.00032425716 | AD57: =_xlfn.XLOOKUP(Table1[[#This Row],[Ruta]],#REF!,#REF!) -> #REF! | AE57: =_xlfn.XLOOKUP(Table1[[#This Row],[Ruta]],#REF!,#REF!) -> #REF! | AF57: =_xlfn.XLOOKUP(Table1[[#This Row],[Ruta]],#REF!,#REF!) -> #REF! | AG57: =_xlfn.XLOOKUP(Table1[[#This Row],[Ruta]],#REF!,#REF!) -> #REF! | AH57: 0.26145051 | AI57: 0.73828219 | AJ57: 0.00026730251 | AK57: 10725 | AL57: 10296 | AM57: 0.66965035 | AN57: 0.59461304 | AO57: 0 | AP57: 0 | AQ57: 0.96 | AR57: 2861160.6 | AS57: 0 | AT57: 0 | AU57: 0 | AV57: 0 | AW57: 490 | AX57: 277.8905 | AY57: 377.06407 | AZ57: 99.173576 | BA57: Sí | BB57: 358761.75 | BC57: 358761.75 | BD57: Sí | BE57: 41.894531 | BF57: 48.897321 | BG57: No | BH57: 0.66965035 | BI57: 0.79215712 | BJ57: No | BK57: 152.39351 | BL57: 326.54714 | BM57: No | BN57: 0 | BO57: Verde - Con espacio | BP57: No | BQ57: 446.34772 | BR57: 93 | BS57: 10843 | BT57: 3546 | BU57: 3.0578116 | BV57: 38.129032 | BW57: 3430 | BX57: 116 | BY57: 3546 | BZ57: 1 | CA57: 0.96728708 | CB57: 0.032712916 | CC57: 0 | CD57: 0 | CE57: 0 | CF57: 0 | CG57: 0 | CH57: 0 | CI57: 0.1844508 | CJ57: 0.73780319 | CK57: 217 | CL57: 703.83 | CM57: =CL57-CK57 -> 486.83 | CN57: 3.28 | CO57: 9.45 | CP57: =CO57-CN57 -> 6.17 | CQ57: 846.56 | CR57: 152.39 | CS57: =CQ57-CR57 -> 694.17 | CT57: No | CU57: 35.27 | CV57: 284 | CW57: 3546 | CX57: =((CW57-CY57)/BT57)*100 -> 86.27101 | CY57: 486.83 | CZ57: =((CW57)/BT57)*100 -> 100 | DA57: =DB57/(CY57+BT57) -> 1054.6818 | DB57: 4253352.4 | DC57: =DD57/(CY57+BT57) -> 23.596122 | DD57: 95159.15 | DE57: 3546 | DF57: 90.893 | DG57: 322.9 | DH57: 100 | DI57: 1354.259 | DJ57: 5239522 | DK57: 31.835 | DL57: 123166.8 | DM57: 3546 | DN57: 92.378 | DO57: 270.3 | DP57: 100 | DQ57: 1262.112 | DR57: 4816547 | DS57: 29.786 | DT57: 113669.4
A58: Noreste | B58: Monterrey | C58: Sucursal Lincoln | D58: 705310 | E58: Noreste|Sucursal Lincoln|705310 | F58: Activa | G58: Sí | H58: Sí | I58: 27 | J58: 28115.797 | K58: 22642.21 | L58: 50758.007 | M58: 3297794 | N58: 396877 | O58: 2900917 | P58: 0 | Q58: 8861.0942 | R58: 5020.3885 | S58: 27731.476 | T58: 2817.6692 | U58: =IFERROR(INDEX('Rentabilidad datos'!$N$2:$N$61,MATCH($C58,'Rentabilidad datos'!$C$2:$C$61,0)),"") -> 35569.534 | V58: =IFERROR(INDEX('Rentabilidad datos'!$O$2:$O$61,MATCH($C58,'Rentabilidad datos'!$C$2:$C$61,0)),"") -> 1368.059 | W58: =IFERROR(INDEX('Rentabilidad datos'!$M$2:$M$61,MATCH($C58,'Rentabilidad datos'!$C$2:$C$61,0)),"") -> 2318.2873 | X58: =IFERROR(INDEX('Rentabilidad datos'!$P$2:$P$61,MATCH($C58,'Rentabilidad datos'!$C$2:$C$61,0)),"") -> 0.59011623 | Y58: C1 | Z58: 37.054187 | AA58: 1 | AB58: 0.99954212 | AC58: 0.00045788184 | AD58: =_xlfn.XLOOKUP(Table1[[#This Row],[Ruta]],#REF!,#REF!) -> #REF! | AE58: =_xlfn.XLOOKUP(Table1[[#This Row],[Ruta]],#REF!,#REF!) -> #REF! | AF58: =_xlfn.XLOOKUP(Table1[[#This Row],[Ruta]],#REF!,#REF!) -> #REF! | AG58: =_xlfn.XLOOKUP(Table1[[#This Row],[Ruta]],#REF!,#REF!) -> #REF! | AH58: 0.12034621 | AI58: 0.87965379 | AJ58: 0 | AK58: 7522 | AL58: 7985 | AM58: 0.5269875 | AN58: 0.59461304 | AO58: 508.67931 | AP58: 254.33965 | AQ58: 1.0953655 | AR58: 3314049.2 | AS58: 105559.69 | AT58: 0.03185218 | AU58: 74177.08 | AV58: 0.00033743856 | AW58: 413 | AX58: 415.03434 | AY58: 377.06407 | AZ58: 0 | BA58: No | BB58: 0 | BC58: 74177.08 | BD58: Sí | BE58: 37.054187 | BF58: 48.897321 | BG58: No | BH58: 0.5269875 | BI58: 0.79215712 | BJ58: No | BK58: 135.7166 | BL58: 326.54714 | BM58: No | BN58: 0 | BO58: Verde - Con espacio | BP58: No | BQ58: 3789.006 | BR58: 288 | BS58: 9302 | BT58: 2984 | BU58: 3.1172922 | BV58: 10.361111 | BW58: 1460 | BX58: 1115 | BY58: 2575 | BZ58: 0.86293566 | CA58: 0.48927614 | CB58: 0.37365952 | CC58: 0.0023458445 | CD58: 0 | CE58: 0 | CF58: 0.1347185 | CG58: 0 | CH58: 0 | CI58: 4.085143 | CJ58: 2.4725865 | CK58: 173 | CL58: 577.5 | CM58: =CL58-CK58 -> 404.5 | CN58: 3.24 | CO58: 9.45 | CP58: =CO58-CN58 -> 6.21 | CQ58: 634.92 | CR58: 135.72 | CS58: =CQ58-CR58 -> 499.2 | CT58: No | CU58: 34.9 | CV58: 204 | CW58: 1667 | CX58: =((CW58-CY58)/BT58)*100 -> 42.308981 | CY58: 404.5 | CZ58: =((CW58)/BT58)*100 -> 55.864611 | DA58: =DB58/(CY58+BT58) -> 1388.3745 | DB58: 4704506.8 | DC58: =DD58/(CY58+BT58) -> 22.219968 | DD58: 75292.36 | DE58: 1667 | DF58: 47.174 | DG58: 259.3 | DH58: 55.865 | DI58: 2119.996 | DJ58: 6875852 | DK58: 34.226 | DL58: 111005.6 | DM58: 1667 | DN58: 48.671 | DO58: 214.7 | DP58: 55.865 | DQ58: 1991.554 | DR58: 6370301 | DS58: 32.185 | DT58: 102948.4
A59: Noreste | B59: Monterrey | C59: Sucursal Lincoln | D59: 705311 | E59: Noreste|Sucursal Lincoln|705311 | F59: Activa | G59: Sí | H59: Sí | I59: 27 | J59: 41772.142 | K59: 14968.307 | L59: 56740.449 | M59: 2618365 | N59: 580482 | O59: 2037883 | P59: 0 | Q59: 5989.093 | R59: 5020.3885 | S59: 27731.476 | T59: 2817.6692 | U59: =IFERROR(INDEX('Rentabilidad datos'!$N$2:$N$61,MATCH($C59,'Rentabilidad datos'!$C$2:$C$61,0)),"") -> 35569.534 | V59: =IFERROR(INDEX('Rentabilidad datos'!$O$2:$O$61,MATCH($C59,'Rentabilidad datos'!$C$2:$C$61,0)),"") -> 1368.059 | W59: =IFERROR(INDEX('Rentabilidad datos'!$M$2:$M$61,MATCH($C59,'Rentabilidad datos'!$C$2:$C$61,0)),"") -> 2318.2873 | X59: =IFERROR(INDEX('Rentabilidad datos'!$P$2:$P$61,MATCH($C59,'Rentabilidad datos'!$C$2:$C$61,0)),"") -> 0.59011623 | Y59: C1 | Z59: 73.533181 | AA59: 1 | AB59: 0.99357729 | AC59: 0.0064227104 | AD59: =_xlfn.XLOOKUP(Table1[[#This Row],[Ruta]],#REF!,#REF!) -> #REF! | AE59: =_xlfn.XLOOKUP(Table1[[#This Row],[Ruta]],#REF!,#REF!) -> #REF! | AF59: =_xlfn.XLOOKUP(Table1[[#This Row],[Ruta]],#REF!,#REF!) -> #REF! | AG59: =_xlfn.XLOOKUP(Table1[[#This Row],[Ruta]],#REF!,#REF!) -> #REF! | AH59: 0.22169636 | AI59: 0.77830364 | AJ59: 0 | AK59: 32134 | AL59: 14386 | AM59: 0.44768781 | AN59: 0.59461304 | AO59: 4721.2955 | AP59: 2360.6478 | AQ59: 0.52115043 | AR59: 2617233.6 | AS59: 429470.79 | AT59: 0.16409341 | AU59: 301790.28 | AV59: 0.0013728726 | AW59: 240 | AX59: 181.92921 | AY59: 377.06407 | AZ59: 195.13486 | BA59: Sí | BB59: 986317.06 | BC59: 1288107.3 | BD59: Sí | BE59: 73.533181 | BF59: 48.897321 | BG59: Sí | BH59: 0.44768781 | BI59: 0.79215712 | BJ59: No | BK59: 129.84084 | BL59: 326.54714 | BM59: No | BN59: 1 | BO59: Verde - Con espacio | BP59: No | BQ59: 0 | BR59: 1249 | BS59: 87389 | BT59: 25386 | BU59: 3.4424092 | BV59: 20.32506 | BW59: 748 | BX59: 11480 | BY59: 12228 | BZ59: 0.48168282 | CA59: 0.029465059 | CB59: 0.45221776 | CC59: 0.33002442 | CD59: 0.046324746 | CE59: 0 | CF59: 0.14192862 | CG59: 0 | CH59: 3.9391791e-05 | CI59: 3.0553044 | CJ59: 0.62936983 | CK59: 530 | CL59: 1095.79 | CM59: =CL59-CK59 -> 565.79 | CN59: 13.33 | CO59: 9.45 | CP59: =CO59-CN59 -> -3.88 | CQ59: 634.92 | CR59: 129.84 | CS59: =CQ59-CR59 -> 505.08 | CT59: Sí | CU59: 141.03 | CV59: 399 | CW59: 12228 | CX59: =((CW59-CY59)/BT59)*100 -> 45.939534 | CY59: 565.79 | CZ59: =((CW59)/BT59)*100 -> 48.168282 | DA59: =DB59/(CY59+BT59) -> 242.51663 | DB59: 6293740.7 | DC59: =DD59/(CY59+BT59) -> 5.6833147 | DD59: 147492.19 | DE59: 12228 | DF59: 46.098 | DG59: 525.6 | DH59: 48.168 | DI59: 335.927 | DJ59: 8704389 | DK59: 7.935 | DL59: 205617.6 | DM59: 12228 | DN59: 46.117 | DO59: 520.7 | DP59: 48.168 | DQ59: 334.698 | DR59: 8670916 | DS59: 7.906 | DT59: 204806
... A66: Noreste | B66: Monterrey | C66: Sucursal Lincoln | D66: 705318 | E66: Noreste|Sucursal Lincoln|705318 | F66: Activa | G66: Sí | H66: Sí | I66: 27 | J66: 60282.354 | K66: 32288.907 | L66: 92571.261 | M66: 4771255 | N66: 878509 | O66: 3892624 | P66: 122 | Q66: 10917.924 | R66: 5020.3885 | S66: 27731.476 | T66: 2817.6692 | U66: =IFERROR(INDEX('Rentabilidad datos'!$N$2:$N$61,MATCH($C66,'Rentabilidad datos'!$C$2:$C$61,0)),"") -> 35569.534 | V66: =IFERROR(INDEX('Rentabilidad datos'!$O$2:$O$61,MATCH($C66,'Rentabilidad datos'!$C$2:$C$61,0)),"") -> 1368.059 | W66: =IFERROR(INDEX('Rentabilidad datos'!$M$2:$M$61,MATCH($C66,'Rentabilidad datos'!$C$2:$C$61,0)),"") -> 2318.2873 | X66: =IFERROR(INDEX('Rentabilidad datos'!$P$2:$P$61,MATCH($C66,'Rentabilidad datos'!$C$2:$C$61,0)),"") -> 0.59011623 | Y66: C1 | Z66: 57.141876 | AA66: 1 | AB66: 0.99875358 | AC66: 0.0012464226 | AD66: =_xlfn.XLOOKUP(Table1[[#This Row],[Ruta]],#REF!,#REF!) -> #REF! | AE66: =_xlfn.XLOOKUP(Table1[[#This Row],[Ruta]],#REF!,#REF!) -> #REF! | AF66: =_xlfn.XLOOKUP(Table1[[#This Row],[Ruta]],#REF!,#REF!) -> #REF! | AG66: =_xlfn.XLOOKUP(Table1[[#This Row],[Ruta]],#REF!,#REF!) -> #REF! | AH66: 0.18412535 | AI66: 0.81584908 | AJ66: 2.5569792e-05 | AK66: 24971 | AL66: 16116 | AM66: 0.64538865 | AN66: 0.59461304 | AO66: 0 | AP66: 0 | AQ66: 0.64538865 | AR66: 4771132.8 | AS66: 0 | AT66: 0 | AU66: 0 | AV66: 0 | AW66: 490 | AX66: 296.04944 | AY66: 377.06407 | AZ66: 81.014632 | BA66: Sí | BB66: 458735.5 | BC66: 458735.5 | BD66: Sí | BE66: 57.141876 | BF66: 48.897321 | BG66: Sí | BH66: 0.64538865 | BI66: 0.79215712 | BJ66: No | BK66: 211.83355 | BL66: 326.54714 | BM66: No | BN66: 1 | BO66: Verde - Con espacio | BP66: No | BQ66: 0 | BR66: 267 | BS66: 13395 | BT66: 4349 | BU66: 3.0800184 | BV66: 16.28839 | BW66: 1020 | BX66: 1375 | BY66: 2395 | BZ66: 0.55070131 | CA66: 0.23453668 | CB66: 0.31616464 | CC66: 0.063232927 | CD66: 0 | CE66: 0 | CF66: 0.38606576 | CG66: 0 | CH66: 0 | CI66: 2.1649869 | CJ66: 2.3889511 | CK66: 151 | CL66: 380.51 | CM66: =CL66-CK66 -> 229.51 | CN66: 4 | CO66: 9.45 | CP66: =CO66-CN66 -> 5.45 | CQ66: 846.56 | CR66: 211.83 | CS66: =CQ66-CR66 -> 634.73 | CT66: No | CU66: 42.37 | CV66: 78 | CW66: 2395 | CX66: =((CW66-CY66)/BT66)*100 -> 49.792826 | CY66: 229.51 | CZ66: =((CW66)/BT66)*100 -> 55.070131 | DA66: =DB66/(CY66+BT66) -> 421.82931 | DB66: 1931349.7 | DC66: =DD66/(CY66+BT66) -> 8.5251927 | DD66: 39032.68 | DE66: 2395 | DF66: 50.837 | DG66: 184.1 | DH66: 55.07 | DI66: 720.587 | DJ66: 3266504 | DK66: 14.733 | DL66: 66785.7 | DM66: 2395 | DN66: 51.148 | DO66: 170.6 | DP66: 55.07 | DQ66: 698.836 | DR66: 3158447 | DS66: 14.318 | DT66: 64711.5
A67: Noreste | B67: Monterrey | C67: Sucursal Lincoln | D67: 705319 | E67: Noreste|Sucursal Lincoln|705319 | F67: Activa | G67: Sí | H67: Sí | I67: 27 | J67: 1482.9304 | K67: 711.49238 | L67: 2194.4228 | M67: 108389 | N67: 23279 | O67: 85110 | P67: 0 | Q67: 1693.5858 | R67: 5020.3885 | S67: 27731.476 | T67: 2817.6692 | U67: =IFERROR(INDEX('Rentabilidad datos'!$N$2:$N$61,MATCH($C67,'Rentabilidad datos'!$C$2:$C$61,0)),"") -> 35569.534 | V67: =IFERROR(INDEX('Rentabilidad datos'!$O$2:$O$61,MATCH($C67,'Rentabilidad datos'!$C$2:$C$61,0)),"") -> 1368.059 | W67: =IFERROR(INDEX('Rentabilidad datos'!$M$2:$M$61,MATCH($C67,'Rentabilidad datos'!$C$2:$C$61,0)),"") -> 2318.2873 | X67: =IFERROR(INDEX('Rentabilidad datos'!$P$2:$P$61,MATCH($C67,'Rentabilidad datos'!$C$2:$C$61,0)),"") -> 0.59011623 | Y67: C1 | Z67: 5.7966102 | AA67: 1 | AB67: 0.99750897 | AC67: 0.0024910277 | AD67: =_xlfn.XLOOKUP(Table1[[#This Row],[Ruta]],#REF!,#REF!) -> #REF! | AE67: =_xlfn.XLOOKUP(Table1[[#This Row],[Ruta]],#REF!,#REF!) -> #REF! | AF67: =_xlfn.XLOOKUP(Table1[[#This Row],[Ruta]],#REF!,#REF!) -> #REF! | AG67: =_xlfn.XLOOKUP(Table1[[#This Row],[Ruta]],#REF!,#REF!) -> #REF! | AH67: 0.21477272 | AI67: 0.78522728 | AJ67: 0 | AK67: 342 | AL67: 39 | AM67: 0.10233918 | AN67: 0.59461304 | AO67: 168.35766 | AP67: 84.17883 | AQ67: 0.36017202 | AR67: 108389.49 | AS67: 233951.29 | AT67: 2.1584315 | AU67: 164398.21 | AV67: 0.000747863 | AW67: 340 | AX67: 2779.2177 | AY67: 377.06407 | AZ67: 0 | BA67: No | BB67: 0 | BC67: 164398.21 | BD67: Sí | BE67: 5.7966102 | BF67: 48.897321 | BG67: No | BH67: 0.10233918 | BI67: 0.79215712 | BJ67: No | BK67: 34.287856 | BL67: 326.54714 | BM67: No | BN67: 0 | BO67: Verde - Con espacio | BP67: No | BQ67: 1469.5322 | BR67: #N/A | BS67: #N/A | BT67: #N/A | BU67: #N/A | BV67: #N/A | BW67: #N/A | BX67: #N/A | BY67: #N/A | BZ67: #N/A | CA67: #N/A | CB67: #N/A | CC67: #N/A | CD67: #N/A | CE67: #N/A | CF67: #N/A | CG67: #N/A | CH67: #N/A | CI67: #N/A | CJ67: #N/A | CM67: =CL67-CK67 -> 0 | CP67: =CO67-CN67 -> 0 | CS67: =CQ67-CR67 -> 0 | CX67: =((CW67-CY67)/BT67)*100 -> #N/A | CZ67: =((CW67)/BT67)*100 -> #N/A | DA67: =DB67/(CY67+BT67) -> #N/A | DC67: =DD67/(CY67+BT67) -> #N/A
A68: Noreste | B68: Monterrey | C68: Sucursal Lincoln | D68: 705320 | E68: Noreste|Sucursal Lincoln|705320 | F68: Activa | G68: Sí | H68: Sí | I68: 27 | J68: 95661.339 | K68: 16854.534 | L68: 112515.87 | M68: 3828752 | N68: 1471638 | O68: 2357114 | P68: 0 | Q68: 8924.8251 | R68: 5020.3885 | S68: 27731.476 | T68: 2817.6692 | U68: =IFERROR(INDEX('Rentabilidad datos'!$N$2:$N$61,MATCH($C68,'Rentabilidad datos'!$C$2:$C$61,0)),"") -> 35569.534 | V68: =IFERROR(INDEX('Rentabilidad datos'!$O$2:$O$61,MATCH($C68,'Rentabilidad datos'!$C$2:$C$61,0)),"") -> 1368.059 | W68: =IFERROR(INDEX('Rentabilidad datos'!$M$2:$M$61,MATCH($C68,'Rentabilidad datos'!$C$2:$C$61,0)),"") -> 2318.2873 | X68: =IFERROR(INDEX('Rentabilidad datos'!$P$2:$P$61,MATCH($C68,'Rentabilidad datos'!$C$2:$C$61,0)),"") -> 0.59011623 | Y68: C1 | Z68: 56.144522 | AA68: 1 | AB68: 0.99760784 | AC68: 0.0023921633 | AD68: =_xlfn.XLOOKUP(Table1[[#This Row],[Ruta]],#REF!,#REF!) -> #REF! | AE68: =_xlfn.XLOOKUP(Table1[[#This Row],[Ruta]],#REF!,#REF!) -> #REF! | AF68: =_xlfn.XLOOKUP(Table1[[#This Row],[Ruta]],#REF!,#REF!) -> #REF! | AG68: =_xlfn.XLOOKUP(Table1[[#This Row],[Ruta]],#REF!,#REF!) -> #REF! | AH68: 0.38436493 | AI68: 0.61563507 | AJ68: 0 | AK68: 24086 | AL68: 14431 | AM68: 0.59914473 | AN68: 0.59461304 | AO68: 0 | AP68: 0 | AQ68: 0.59914473 | AR68: 3828750 | AS68: 0 | AT68: 0 | AU68: 0 | AV68: 0 | AW68: 490 | AX68: 265.31425 | AY68: 377.06407 | AZ68: 111.74982 | BA68: Sí | BB68: 566610.85 | BC68: 566610.85 | BD68: Sí | BE68: 56.144522 | BF68: 48.897321 | BG68: Sí | BH68: 0.59914473 | BI68: 0.79215712 | BJ68: No | BK68: 262.27476 | BL68: 326.54714 | BM68: No | BN68: 1 | BO68: Verde - Con espacio | BP68: No | BQ68: 0 | BR68: 456 | BS68: 37291 | BT68: 11383 | BU68: 3.2760257 | BV68: 24.962719 | BW68: 11142 | BX68: 241 | BY68: 11383 | BZ68: 1 | CA68: 0.97882808 | CB68: 0.021171923 | CC68: 0 | CD68: 0 | CE68: 0 | CF68: 0 | CG68: 0 | CH68: 0 | CI68: 0.21452897 | CJ68: 0.8581159 | CK68: 305 | CL68: 812.61 | CM68: =CL68-CK68 -> 507.61 | CN68: 4.81 | CO68: 9.45 | CP68: =CO68-CN68 -> 4.64 | CQ68: 634.92 | CR68: 262.27 | CS68: =CQ68-CR68 -> 372.65 | CT68: No | CU68: 55.51 | CV68: 528 | CW68: 11383 | CX68: =((CW68-CY68)/BT68)*100 -> 95.540631 | CY68: 507.61 | CZ68: =((CW68)/BT68)*100 -> 100 | DA68: =DB68/(CY68+BT68) -> 276.37186 | DB68: 3286230 | DC68: =DD68/(CY68+BT68) -> 8.313941 | DD68: 98857.83 | DE68: 11383 | DF68: 95.775 | DG68: 481 | DH68: 100 | DI68: 577.419 | DJ68: 6850487 | DK68: 17.516 | DL68: 207804.9 | DM68: 11383 | DN68: 95.947 | DO68: 461.3 | DP68: 100 | DQ68: 568.714 | DR68: 6736021 | DS68: 17.245 | DT68: 204259
A69: Noreste | B69: Monterrey | C69: Sucursal Lincoln | D69: 705322 | E69: Noreste|Sucursal Lincoln|705322 | F69: Activa | G69: Sí | H69: Sí | I69: 27 | J69: 62187.972 | K69: 10500.525 | L69: 72688.497 | M69: 2429097 | N69: 930014 | O69: 1499083 | P69: 0 | Q69: 5584.1308 | R69: 5020.3885 | S69: 27731.476 | T69: 2817.6692 | U69: =IFERROR(INDEX('Rentabilidad datos'!$N$2:$N$61,MATCH($C69,'Rentabilidad datos'!$C$2:$C$61,0)),"") -> 35569.534 | V69: =IFERROR(INDEX('Rentabilidad datos'!$O$2:$O$61,MATCH($C69,'Rentabilidad datos'!$C$2:$C$61,0)),"") -> 1368.059 | W69: =IFERROR(INDEX('Rentabilidad datos'!$M$2:$M$61,MATCH($C69,'Rentabilidad datos'!$C$2:$C$61,0)),"") -> 2318.2873 | X69: =IFERROR(INDEX('Rentabilidad datos'!$P$2:$P$61,MATCH($C69,'Rentabilidad datos'!$C$2:$C$61,0)),"") -> 0.59011623 | Y69: C1 | Z69: 90.048276 | AA69: 1 | AB69: 0.99552879 | AC69: 0.0044712088 | AD69: =_xlfn.XLOOKUP(Table1[[#This Row],[Ruta]],#REF!,#REF!) -> #REF! | AE69: =_xlfn.XLOOKUP(Table1[[#This Row],[Ruta]],#REF!,#REF!) -> #REF! | AF69: =_xlfn.XLOOKUP(Table1[[#This Row],[Ruta]],#REF!,#REF!) -> #REF! | AG69: =_xlfn.XLOOKUP(Table1[[#This Row],[Ruta]],#REF!,#REF!) -> #REF! | AH69: 0.38286408 | AI69: 0.61713592 | AJ69: 0 | AK69: 39171 | AL69: 9877 | AM69: 0.25215083 | AN69: 0.59461304 | AO69: 13414.587 | AP69: 6707.2937 | AQ69: 0.42338193 | AR69: 2429096.9 | AS69: 1649556.2 | AT69: 0.67908208 | AU69: 1159147.6 | AV69: 0.0052730721 | AW69: 28 | AX69: 245.93469 | AY69: 377.06407 | AZ69: 131.12939 | BA69: Sí | BB69: 455057.96 | BC69: 1614205.5 | BD69: Sí | BE69: 90.048276 | BF69: 48.897321 | BG69: Sí | BH69: 0.25215083 | BI69: 0.79215712 | BJ69: No | BK69: 167.09999 | BL69: 326.54714 | BM69: No | BN69: 1 | BO69: Verde - Con espacio | BP69: No | BQ69: 5764.215 | BR69: 550 | BS69: 27703 | BT69: 8879 | BU69: 3.1200586 | BV69: 16.143636 | BW69: 4962 | BX69: 3916 | BY69: 8878 | BZ69: 0.99988737 | CA69: 0.55884672 | CB69: 0.44104066 | CC69: 0 | CD69: 0 | CE69: 0 | CF69: 0 | CG69: 0 | CH69: 0.0001126253 | CI69: 0.036097174 | CJ69: 0.75804065 | CK69: 504 | CL69: 908.12 | CM69: =CL69-CK69 -> 404.12 | CN69: 8.15 | CO69: 9.45 | CP69: =CO69-CN69 -> 1.3 | CQ69: 634.92 | CR69: 167.1 | CS69: =CQ69-CR69 -> 467.82 | CT69: No | CU69: 86.57 | CV69: 445 | CW69: 8878 | CX69: =((CW69-CY69)/BT69)*100 -> 95.437324 | CY69: 404.12 | CZ69: =((CW69)/BT69)*100 -> 99.988737 | DA69: =DB69/(CY69+BT69) -> 421.05137 | DB69: 3908670.4 | DC69: =DD69/(CY69+BT69) -> 12.967161 | DD69: 120375.71 | DE69: 8878 | DF69: 95.955 | DG69: 358.2 | DH69: 99.989 | DI69: 732.249 | DJ69: 6763893 | DK69: 22.612 | DL69: 208873.2 | DM69: 8878 | DN69: 96.051 | DO69: 349.7 | DP69: 99.989 | DQ69: 727.452 | DR69: 6713414 | DS69: 22.467 | DT69: 207343
A70: Noreste | B70: Monterrey | C70: Sucursal Lincoln | D70: 705323 | E70: Noreste|Sucursal Lincoln|705323 | F70: Activa | G70: Sí | H70: Sí | I70: 27 | J70: 42462.532 | K70: 19330.686 | L70: 61793.218 | M70: 3230007 | N70: 600295 | O70: 2629712 | P70: 0 | Q70: 7745.8202 | R70: 5020.3885 | S70: 27731.476 | T70: 2817.6692 | U70: =IFERROR(INDEX('Rentabilidad datos'!$N$2:$N$61,MATCH($C70,'Rentabilidad datos'!$C$2:$C$61,0)),"") -> 35569.534 | V70: =IFERROR(INDEX('Rentabilidad datos'!$O$2:$O$61,MATCH($C70,'Rentabilidad datos'!$C$2:$C$61,0)),"") -> 1368.059 | W70: =IFERROR(INDEX('Rentabilidad datos'!$M$2:$M$61,MATCH($C70,'Rentabilidad datos'!$C$2:$C$61,0)),"") -> 2318.2873 | X70: =IFERROR(INDEX('Rentabilidad datos'!$P$2:$P$61,MATCH($C70,'Rentabilidad datos'!$C$2:$C$61,0)),"") -> 0.59011623 | Y70: C1 | Z70: 41.676471 | AA70: 1 | AB70: 0.9998257 | AC70: 0.00017430303 | AD70: =_xlfn.XLOOKUP(Table1[[#This Row],[Ruta]],#REF!,#REF!) -> #REF! | AE70: =_xlfn.XLOOKUP(Table1[[#This Row],[Ruta]],#REF!,#REF!) -> #REF! | AF70: =_xlfn.XLOOKUP(Table1[[#This Row],[Ruta]],#REF!,#REF!) -> #REF! | AG70: =_xlfn.XLOOKUP(Table1[[#This Row],[Ruta]],#REF!,#REF!) -> #REF! | AH70: 0.18584944 | AI70: 0.81415056 | AJ70: 0 | AK70: 14170 | AL70: 12739 | AM70: 0.82575865 | AN70: 0.59461304 | AO70: 0 | AP70: 0 | AQ70: 0.899012 | AR70: 3230007 | AS70: 0 | AT70: 0 | AU70: 0 | AV70: 0 | AW70: 490 | AX70: 253.55264 | AY70: 377.06407 | AZ70: 123.51144 | BA70: Sí | BB70: 552820.51 | BC70: 552820.51 | BD70: Sí | BE70: 41.676471 | BF70: 48.897321 | BG70: No | BH70: 0.82575865 | BI70: 0.79215712 | BJ70: Sí | BK70: 148.18518 | BL70: 326.54714 | BM70: No | BN70: 1 | BO70: Verde - Con espacio | BP70: No | BQ70: 0 | BR70: 255 | BS70: 14836 | BT70: 4955 | BU70: 2.9941473 | BV70: 19.431373 | BW70: 988 | BX70: 2855 | BY70: 3843 | BZ70: 0.77558022 | CA70: 0.19939455 | CB70: 0.57618567 | CC70: 0 | CD70: 0 | CE70: 0 | CF70: 0.22441978 | CG70: 0 | CH70: 0 | CI70: 1.9547048 | CJ70: 1.7524939 | CK70: 222 | CL70: 603.04 | CM70: =CL70-CK70 -> 381.04 | CN70: 3.57 | CO70: 9.45 | CP70: =CO70-CN70 -> 5.88 | CQ70: 634.92 | CR70: 148.19 | CS70: =CQ70-CR70 -> 486.73 | CT70: No | CU70: 38.35 | CV70: 234 | CW70: 3843 | CX70: =((CW70-CY70)/BT70)*100 -> 69.868012 | CY70: 381.04 | CZ70: =((CW70)/BT70)*100 -> 77.558022 | DA70: =DB70/(CY70+BT70) -> 660.70047 | DB70: 3525524.1 | DC70: =DD70/(CY70+BT70) -> 14.083851 | DD70: 75151.99 | DE70: 3843 | DF70: 72.147 | DG70: 268.1 | DH70: 77.558 | DI70: 1019.889 | DJ70: 5327015 | DK70: 21.088 | DL70: 110147.9 | DM70: 3843 | DN70: 72.86 | DO70: 232.8 | DP70: 77.558 | DQ70: 972.96 | DR70: 5047499 | DS70: 20.056 | DT70: 104047.8
A71: Noreste | B71: Monterrey | C71: Sucursal Lincoln | D71: 705324 | E71: Noreste|Sucursal Lincoln|705324 | F71: Activa | G71: Sí | H71: Sí | I71: 27 | J71: 53015.642 | K71: 14924.05 | L71: 67939.692 | M71: 2697849 | N71: 756056 | O71: 1941793 | P71: 0 | Q71: 6230.5967 | R71: 5020.3885 | S71: 27731.476 | T71: 2817.6692 | U71: =IFERROR(INDEX('Rentabilidad datos'!$N$2:$N$61,MATCH($C71,'Rentabilidad datos'!$C$2:$C$61,0)),"") -> 35569.534 | V71: =IFERROR(INDEX('Rentabilidad datos'!$O$2:$O$61,MATCH($C71,'Rentabilidad datos'!$C$2:$C$61,0)),"") -> 1368.059 | W71: =IFERROR(INDEX('Rentabilidad datos'!$M$2:$M$61,MATCH($C71,'Rentabilidad datos'!$C$2:$C$61,0)),"") -> 2318.2873 | X71: =IFERROR(INDEX('Rentabilidad datos'!$P$2:$P$61,MATCH($C71,'Rentabilidad datos'!$C$2:$C$61,0)),"") -> 0.59011623 | Y71: C1 | Z71: 60.553398 | AA71: 1 | AB71: 0.99969383 | AC71: 0.00030616984 | AD71: =_xlfn.XLOOKUP(Table1[[#This Row],[Ruta]],#REF!,#REF!) -> #REF! | AE71: =_xlfn.XLOOKUP(Table1[[#This Row],[Ruta]],#REF!,#REF!) -> #REF! | AF71: =_xlfn.XLOOKUP(Table1[[#This Row],[Ruta]],#REF!,#REF!) -> #REF! | AG71: =_xlfn.XLOOKUP(Table1[[#This Row],[Ruta]],#REF!,#REF!) -> #REF! | AH71: 0.280244 | AI71: 0.719756 | AJ71: 0 | AK71: 24948 | AL71: 13145 | AM71: 0.51198493 | AN71: 0.59461304 | AO71: 2061.4062 | AP71: 1030.7031 | AQ71: 0.56821 | AR71: 2697848.4 | AS71: 211539.04 | AT71: 0.078410277 | AU71: 148649.05 | AV71: 0.00067621862 | AW71: 353 | AX71: 205.23761 | AY71: 377.06407 | AZ71: 171.82646 | BA71: Sí | BB71: 793582.84 | BC71: 942231.9 | BD71: Sí | BE71: 60.553398 | BF71: 48.897321 | BG71: Sí | BH71: 0.51198493 | BI71: 0.79215712 | BJ71: No | BK71: 156.9046 | BL71: 326.54714 | BM71: No | BN71: 1 | BO71: Verde - Con espacio | BP71: No | BQ71: 123.58964 | BR71: 436 | BS71: 39123 | BT71: 12033 | BU71: 3.2513089 | BV71: 27.598624 | BW71: 3653 | BX71: 4388 | BY71: 8041 | BZ71: 0.66824566 | CA71: 0.30358182 | CB71: 0.36466384 | CC71: 0.15823153 | CD71: 0.061746863 | CE71: 0 | CF71: 0.11177595 | CG71: 0 | CH71: 0 | CI71: 1.4058227 | CJ71: 0.40896659 | CK71: 326 | CL71: 788.32 | CM71: =CL71-CK71 -> 462.32 | CN71: 4.33 | CO71: 9.45 | CP71: =CO71-CN71 -> 5.12 | CQ71: 634.92 | CR71: 156.9 | CS71: =CQ71-CR71 -> 478.02 | CT71: No | CU71: 46.45 | CV71: 445 | CW71: 8041 | CX71: =((CW71-CY71)/BT71)*100 -> 62.982465 | CY71: 462.32 | CZ71: =((CW71)/BT71)*100 -> 66.824566 | DA71: =DB71/(CY71+BT71) -> 371.93904 | DB71: 4647497.3 | DC71: =DD71/(CY71+BT71) -> 9.7785811 | DD71: 122186.5 | DE71: 8041 | DF71: 63.463 | DG71: 404.5 | DH71: 66.825 | DI71: 556.527 | DJ71: 6921813 | DK71: 15.014 | DL71: 186740.4 | DM71: 8041 | DN71: 63.688 | DO71: 377.4 | DP71: 66.825 | DQ71: 542.483 | DR71: 6732444 | DS71: 14.653 | DT71: 181855.9
A72: Noreste | B72: Monterrey | C72: Sucursal Lincoln | D72: 705325 | E72: Noreste|Sucursal Lincoln|705325 | F72: Activa | G72: Sí | H72: Sí | I72: 27 | J72: 71032.718 | K72: 13711.388 | L72: 84744.106 | M72: 2979177 | N72: 1028926 | O72: 1950160 | P72: 91 | Q72: 6944.2512 | R72: 5020.3885 | S72: 27731.476 | T72: 2817.6692 | U72: =IFERROR(INDEX('Rentabilidad datos'!$N$2:$N$61,MATCH($C72,'Rentabilidad datos'!$C$2:$C$61,0)),"") -> 35569.534 | V72: =IFERROR(INDEX('Rentabilidad datos'!$O$2:$O$61,MATCH($C72,'Rentabilidad datos'!$C$2:$C$61,0)),"") -> 1368.059 | W72: =IFERROR(INDEX('Rentabilidad datos'!$M$2:$M$61,MATCH($C72,'Rentabilidad datos'!$C$2:$C$61,0)),"") -> 2318.2873 | X72: =IFERROR(INDEX('Rentabilidad datos'!$P$2:$P$61,MATCH($C72,'Rentabilidad datos'!$C$2:$C$61,0)),"") -> 0.59011623 | Y72: C1 | Z72: 64.991045 | AA72: 1 | AB72: 0.99525137 | AC72: 0.0047486269 | AD72: =_xlfn.XLOOKUP(Table1[[#This Row],[Ruta]],#REF!,#REF!) -> #REF! | AE72: =_xlfn.XLOOKUP(Table1[[#This Row],[Ruta]],#REF!,#REF!) -> #REF! | AF72: =_xlfn.XLOOKUP(Table1[[#This Row],[Ruta]],#REF!,#REF!) -> #REF! | AG72: =_xlfn.XLOOKUP(Table1[[#This Row],[Ruta]],#REF!,#REF!) -> #REF! | AH72: 0.34537256 | AI72: 0.65459689 | AJ72: 3.0545349e-05 | AK72: 21772 | AL72: 8797 | AM72: 0.31834466 | AN72: 0.59461304 | AO72: 6014.9152 | AP72: 3007.4576 | AQ72: 0.54218526 | AR72: 2979083.8 | AS72: 1018468.6 | AT72: 0.34187309 | AU72: 715680.62 | AV72: 0.0032556989 | AW72: 91 | AX72: 338.64769 | AY72: 377.06407 | AZ72: 38.416381 | BA72: Sí | BB72: 118738.8 | BC72: 834419.42 | BD72: Sí | BE72: 64.991045 | BF72: 48.897321 | BG72: Sí | BH72: 0.31834466 | BI72: 0.79215712 | BJ72: No | BK72: 197.53871 | BL72: 326.54714 | BM72: No | BN72: 1 | BO72: Verde - Con espacio | BP72: No | BQ72: 3563.0011 | BR72: 323 | BS72: 11414 | BT72: 3374 | BU72: 3.3829283 | BV72: 10.44582 | BW72: 3210 | BX72: 158 | BY72: 3368 | BZ72: 0.9982217 | CA72: 0.95139301 | CB72: 0.04682869 | CC72: 0 | CD72: 0 | CE72: 0 | CF72: 0 | CG72: 0.0014819206 | CH72: 0.00029638411 | CI72: 0.087611705 | CJ72: 1.3141756 | CK72: 400 | CL72: 637.76 | CM72: =CL72-CK72 -> 237.76 | CN72: 6.55 | CO72: 9.45 | CP72: =CO72-CN72 -> 2.9 | CQ72: 634.92 | CR72: 197.54 | CS72: =CQ72-CR72 -> 437.38 | CT72: No | CU72: 69.39 | CV72: 349 | CW72: 3368 | CX72: =((CW72-CY72)/BT72)*100 -> 92.775341 | CY72: 237.76 | CZ72: =((CW72)/BT72)*100 -> 99.82217 | DA72: =DB72/(CY72+BT72) -> 565.57534 | DB72: 2042722.4 | DC72: =DD72/(CY72+BT72) -> 15.843741 | DD72: 57223.79 | DE72: 3368 | DF72: 94.121 | DG72: 192.3 | DH72: 99.822 | DI72: 1249.864 | DJ72: 4457446 | DK72: 35.482 | DL72: 126541.7 | DM72: 3368 | DN72: 94.871 | DO72: 167 | DP72: 99.822 | DQ72: 1210.706 | DR72: 4287159 | DS72: 34.461 | DT72: 122026
A73: Noreste | B73: Monterrey | C73: Sucursal Lincoln | D73: 705326 | E73: Noreste|Sucursal Lincoln|705326 | F73: Activa | G73: Sí | H73: Sí | I73: 27 | J73: 63897.428 | K73: 13147.16 | L73: 77044.588 | M73: 2438142 | N73: 943874 | O73: 1494268 | P73: 0 | Q73: 5558.2495 | R73: 5020.3885 | S73: 27731.476 | T73: 2817.6692 | U73: =IFERROR(INDEX('Rentabilidad datos'!$N$2:$N$61,MATCH($C73,'Rentabilidad datos'!$C$2:$C$61,0)),"") -> 35569.534 | V73: =IFERROR(INDEX('Rentabilidad datos'!$O$2:$O$61,MATCH($C73,'Rentabilidad datos'!$C$2:$C$61,0)),"") -> 1368.059 | W73: =IFERROR(INDEX('Rentabilidad datos'!$M$2:$M$61,MATCH($C73,'Rentabilidad datos'!$C$2:$C$61,0)),"") -> 2318.2873 | X73: =IFERROR(INDEX('Rentabilidad datos'!$P$2:$P$61,MATCH($C73,'Rentabilidad datos'!$C$2:$C$61,0)),"") -> 0.59011623 | Y73: C1 | Z73: 87.199085 | AA73: 1 | AB73: 0.87850503 | AC73: 0.12149497 | AD73: =_xlfn.XLOOKUP(Table1[[#This Row],[Ruta]],#REF!,#REF!) -> #REF! | AE73: =_xlfn.XLOOKUP(Table1[[#This Row],[Ruta]],#REF!,#REF!) -> #REF! | AF73: =_xlfn.XLOOKUP(Table1[[#This Row],[Ruta]],#REF!,#REF!) -> #REF! | AG73: =_xlfn.XLOOKUP(Table1[[#This Row],[Ruta]],#REF!,#REF!) -> #REF! | AH73: 0.3871284 | AI73: 0.6128716 | AJ73: 0 | AK73: 38106 | AL73: 10231 | AM73: 0.2684879 | AN73: 0.59461304 | AO73: 12427.325 | AP73: 6213.6623 | AQ73: 0.43155047 | AR73: 2428955 | AS73: 1475193.7 | AT73: 0.60733675 | AU73: 1036622.6 | AV73: 0.0047156942 | AW73: 38 | AX73: 237.4113 | AY73: 377.06407 | AZ73: 139.65277 | BA73: Sí | BB73: 502006.42 | BC73: 1538629 | BD73: Sí | BE73: 87.199085 | BF73: 48.897321 | BG73: Sí | BH73: 0.2684879 | BI73: 0.79215712 | BJ73: No | BK73: 176.30341 | BL73: 326.54714 | BM73: No | BN73: 1 | BO73: Verde - Con espacio | BP73: No | BQ73: 3345.3106 | BR73: 2433 | BS73: 234843 | BT73: 66070 | BU73: 3.5544574 | BV73: 27.155775 | BW73: 0 | BX73: 4184 | BY73: 4184 | BZ73: 0.063326775 | CA73: 0 | CB73: 0.063326775 | CC73: 0.12226427 | CD73: 0.15058272 | CE73: 0.10290601 | CF73: 0.5609051 | CG73: 0 | CH73: 1.5135462e-05 | CI73: 4.1942915 | CJ73: 0.26826433 | CK73: 726 | CL73: 931.64 | CM73: =CL73-CK73 -> 205.64 | CN73: 26.91 | CO73: 9.45 | CP73: =CO73-CN73 -> -17.46 | CQ73: 634.92 | CR73: 176.3 | CS73: =CQ73-CR73 -> 458.62 | CT73: Sí | CU73: 284.8 | CV73: 190 | CW73: 4184 | CX73: =((CW73-CY73)/BT73)*100 -> 6.0214318 | CY73: 205.64 | CZ73: =((CW73)/BT73)*100 -> 6.3326775 | DA73: =DB73/(CY73+BT73) -> 47.259737 | DB73: 3132169.3 | DC73: =DD73/(CY73+BT73) -> 1.5804861 | DD73: 104747.73 | DE73: 4184 | DF73: 6.049 | DG73: 187.4 | DH73: 6.333 | DI73: 76.282 | DJ73: 5054250 | DK73: 2.592 | DL73: 171738.6 | DM73: 4184 | DN73: 6.049 | DO73: 187.4 | DP73: 6.333 | DQ73: 76.282 | DR73: 5054250 | DS73: 2.592 | DT73: 171738.6
A74: Noreste | B74: Monterrey | C74: Sucursal Lincoln | D74: 705327 | E74: Noreste|Sucursal Lincoln|705327 | F74: Activa | G74: Sí | H74: Sí | I74: 27 | J74: 31222.554 | K74: 7308.4381 | L74: 38530.992 | M74: 1381730 | N74: 465257 | O74: 916473 | P74: 0 | Q74: 3282.9247 | R74: 5020.3885 | S74: 27731.476 | T74: 2817.6692 | U74: =IFERROR(INDEX('Rentabilidad datos'!$N$2:$N$61,MATCH($C74,'Rentabilidad datos'!$C$2:$C$61,0)),"") -> 35569.534 | V74: =IFERROR(INDEX('Rentabilidad datos'!$O$2:$O$61,MATCH($C74,'Rentabilidad datos'!$C$2:$C$61,0)),"") -> 1368.059 | W74: =IFERROR(INDEX('Rentabilidad datos'!$M$2:$M$61,MATCH($C74,'Rentabilidad datos'!$C$2:$C$61,0)),"") -> 2318.2873 | X74: =IFERROR(INDEX('Rentabilidad datos'!$P$2:$P$61,MATCH($C74,'Rentabilidad datos'!$C$2:$C$61,0)),"") -> 0.59011623 | Y74: C1 | Z74: 66.173684 | AA74: 1 | AB74: 0.98711398 | AC74: 0.01288602 | AD74: =_xlfn.XLOOKUP(Table1[[#This Row],[Ruta]],#REF!,#REF!) -> #REF! | AE74: =_xlfn.XLOOKUP(Table1[[#This Row],[Ruta]],#REF!,#REF!) -> #REF! | AF74: =_xlfn.XLOOKUP(Table1[[#This Row],[Ruta]],#REF!,#REF!) -> #REF! | AG74: =_xlfn.XLOOKUP(Table1[[#This Row],[Ruta]],#REF!,#REF!) -> #REF! | AH74: 0.33672063 | AI74: 0.66327937 | AJ74: 0 | AK74: 25146 | AL74: 11401 | AM74: 0.43708741 | AN74: 0.59461304 | AO74: 3961.1396 | AP74: 1980.5698 | AQ74: 0.53215501 | AR74: 1378828.4 | AS74: 239528.62 | AT74: 0.17371895 | AU74: 168317.41 | AV74: 0.00076569184 | AW74: 336 | AX74: 120.93925 | AY74: 377.06407 | AZ74: 256.12482 | BA74: Sí | BB74: 1025973.7 | BC74: 1194291.2 | BD74: Sí | BE74: 66.173684 | BF74: 48.897321 | BG74: Sí | BH74: 0.43708741 | BI74: 0.79215712 | BJ74: No | BK74: 91.740456 | BL74: 326.54714 | BM74: No | BN74: 1 | BO74: Verde - Con espacio | BP74: No | BQ74: 0 | BR74: 3145 | BS74: 305707 | BT74: 77515 | BU74: 3.9438431 | BV74: 24.647059 | BW74: 0 | BX74: 6174 | BY74: 6174 | BZ74: 0.0796491 | CA74: 0 | CB74: 0.0796491 | CC74: 0.14239825 | CD74: 0.15763401 | CE74: 0.004760369 | CF74: 0.61551958 | CG74: 3.8702187e-05 | CH74: 0 | CI74: 4.8379658 | CJ74: 0.22897742 | CK74: 188 | CL74: 485.24 | CM74: =CL74-CK74 -> 297.24 | CN74: 8.06 | CO74: 9.45 | CP74: =CO74-CN74 -> 1.39 | CQ74: 634.92 | CR74: 91.74 | CS74: =CQ74-CR74 -> 543.18 | CT74: No | CU74: 85.57 | CV74: 93 | CW74: 4063 | CX74: =((CW74-CY74)/BT74)*100 -> 4.8581049 | CY74: 297.24 | CZ74: =((CW74)/BT74)*100 -> 5.2415661 | DA74: =DB74/(CY74+BT74) -> 25.730249 | DB74: 2002128.3 | DC74: =DD74/(CY74+BT74) -> 0.70357813 | DD74: 54746.99 | DE74: 4063 | DF74: 4.932 | DG74: 239.8 | DH74: 5.242 | DI74: 40.194 | DJ74: 3125304 | DK74: 1.051 | DL74: 81701 | DM74: 4063 | DN74: 4.941 | DO74: 233.3 | DP74: 5.242 | DQ74: 39.827 | DR74: 3096444 | DS74: 1.038 | DT74: 80698.3
A75: Noreste | B75: Monterrey | C75: Sucursal Santa Catarina | D75: 712300 | E75: Noreste|Sucursal Santa Catarina|712300 | F75: Activa | G75: Sí | H75: Sí | I75: 18 | J75: 29133.77 | K75: 6832.2914 | L75: 35966.062 | M75: 1328005 | N75: 438026 | O75: 889979 | P75: 0 | Q75: 3306.8037 | R75: 5698.9829 | S75: 19312.021 | T75: 1950.6941 | U75: =IFERROR(INDEX('Rentabilidad datos'!$N$2:$N$61,MATCH($C75,'Rentabilidad datos'!$C$2:$C$61,0)),"") -> 26961.698 | V75: =IFERROR(INDEX('Rentabilidad datos'!$O$2:$O$61,MATCH($C75,'Rentabilidad datos'!$C$2:$C$61,0)),"") -> 1497.8721 | W75: =IFERROR(INDEX('Rentabilidad datos'!$M$2:$M$61,MATCH($C75,'Rentabilidad datos'!$C$2:$C$61,0)),"") -> 3467.2961 | X75: =IFERROR(INDEX('Rentabilidad datos'!$P$2:$P$61,MATCH($C75,'Rentabilidad datos'!$C$2:$C$61,0)),"") -> 0.43200005 | Y75: C2 | Z75: 80.632653 | AA75: 1 | AB75: 0.99851356 | AC75: 0.0014864402 | AD75: =_xlfn.XLOOKUP(Table1[[#This Row],[Ruta]],#REF!,#REF!) -> #REF! | AE75: =_xlfn.XLOOKUP(Table1[[#This Row],[Ruta]],#REF!,#REF!) -> #REF! | AF75: =_xlfn.XLOOKUP(Table1[[#This Row],[Ruta]],#REF!,#REF!) -> #REF! | AG75: =_xlfn.XLOOKUP(Table1[[#This Row],[Ruta]],#REF!,#REF!) -> #REF! | AH75: 0.32983761 | AI75: 0.67016239 | AJ75: 0 | AK75: 15804 | AL75: 8871 | AM75: 0.44900025 | AN75: 0.83144613 | AO75: 6044.1747 | AP75: 3022.0874 | AQ75: 0.75253653 | AR75: 1292960.2 | AS75: 440473.32 | AT75: 0.34067043 | AU75: 309521.79 | AV75: 0.0014080439 | AW75: 234 | AX75: 145.75135 | AY75: 377.8548 | AZ75: 232.10345 | BA75: Sí | BB75: 723428.81 | BC75: 1032950.6 | BD75: Sí | BE75: 80.632653 | BF75: 48.897321 | BG75: Sí | BH75: 0.44900025 | BI75: 0.79215712 | BJ75: No | BK75: 91.984813 | BL75: 326.54714 | BM75: No | BN75: 1 | BO75: Verde - Con espacio | BP75: No | BQ75: 0 | BR75: 815 | BS75: 67628 | BT75: 18138 | BU75: 3.7285257 | BV75: 22.255215 | BW75: 0 | BX75: 3816 | BY75: 3816 | BZ75: 0.21038703 | CA75: 0 | CB75: 0.21038703 | CC75: 0.55689712 | CD75: 0.10695777 | CE75: 0 | CF75: 0.12520675 | CG75: 0.00049619583 | CH75: 5.513287e-05 | CI75: 2.8982078 | CJ75: 0.48796357 | CK75: 612 | CL75: 797.55 | CM75: =CL75-CK75 -> 185.55 | CN75: 7.45 | CO75: 9.45 | CP75: =CO75-CN75 -> 2 | CQ75: 634.92 | CR75: 91.98 | CS75: =CQ75-CR75 -> 542.94 | CT75: No | CU75: 78.88 | CV75: 207 | CW75: 3816 | CX75: =((CW75-CY75)/BT75)*100 -> 20.015713 | CY75: 185.55 | CZ75: =((CW75)/BT75)*100 -> 21.038703 | DA75: =DB75/(CY75+BT75) -> 222.99524 | DB75: 4086064.4 | DC75: =DD75/(CY75+BT75) -> 5.6949543 | DD75: 104351.78 | DE75: 3816 | DF75: 20.231 | DG75: 146.5 | DH75: 21.039 | DI75: 322.083 | DJ75: 5889132 | DK75: 8.239 | DL75: 150637.2 | DM75: 3816 | DN75: 20.346 | DO75: 125.7 | DP75: 21.039 | DQ75: 318.751 | DR75: 5821576 | DS75: 8.147 | DT75: 148792.8
A76: Noreste | B76: Monterrey | C76: Sucursal Santa Catarina | D76: 712302 | E76: Noreste|Sucursal Santa Catarina|712302 | F76: Activa | G76: Sí | H76: Sí | I76: 18 | J76: 72142.274 | K76: 11684.571 | L76: 83826.845 | M76: 2719495 | N76: 1105850 | O76: 1613645 | P76: 0 | Q76: 6266.1136 | R76: 5698.9829 | S76: 19312.021 | T76: 1950.6941 | U76: =IFERROR(INDEX('Rentabilidad datos'!$N$2:$N$61,MATCH($C76,'Rentabilidad datos'!$C$2:$C$61,0)),"") -> 26961.698 | V76: =IFERROR(INDEX('Rentabilidad datos'!$O$2:$O$61,MATCH($C76,'Rentabilidad datos'!$C$2:$C$61,0)),"") -> 1497.8721 | W76: =IFERROR(INDEX('Rentabilidad datos'!$M$2:$M$61,MATCH($C76,'Rentabilidad datos'!$C$2:$C$61,0)),"") -> 3467.2961 | X76: =IFERROR(INDEX('Rentabilidad datos'!$P$2:$P$61,MATCH($C76,'Rentabilidad datos'!$C$2:$C$61,0)),"") -> 0.43200005 | Y76: C2 | Z76: 39.502392 | AA76: 1 | AB76: 0.99722301 | AC76: 0.0027769862 | AD76: =_xlfn.XLOOKUP(Table1[[#This Row],[Ruta]],#REF!,#REF!) -> #REF! | AE76: =_xlfn.XLOOKUP(Table1[[#This Row],[Ruta]],#REF!,#REF!) -> #REF! | AF76: =_xlfn.XLOOKUP(Table1[[#This Row],[Ruta]],#REF!,#REF!) -> #REF! | AG76: =_xlfn.XLOOKUP(Table1[[#This Row],[Ruta]],#REF!,#REF!) -> #REF! | AH76: 0.406638 | AI76: 0.593362 | AJ76: 0 | AK76: 8256 | AL76: 9230 | AM76: 0.73946221 | AN76: 0.83144613 | AO76: 759.41929 | AP76: 379.70964 | AQ76: 1.1639668 | AR76: 2719493.3 | AS76: 111876.25 | AT76: 0.04113864 | AU76: 78615.746 | AV76: 0.00035763047 | AW76: 409 | AX76: 294.63633 | AY76: 377.8548 | AZ76: 83.218474 | BA76: Sí | BB76: 269875.26 | BC76: 348491.01 | BD76: Sí | BE76: 39.502392 | BF76: 48.897321 | BG76: No | BH76: 0.73946221 | BI76: 0.79215712 | BJ76: No | BK76: 193.14941 | BL76: 326.54714 | BM76: No | BN76: 0 | BO76: Verde - Con espacio | BP76: No | BQ76: 2544.6377 | BR76: 243 | BS76: 20624 | BT76: 5629 | BU76: 3.6638835 | BV76: 23.164609 | BW76: 2586 | BX76: 0 | BY76: 2586 | BZ76: 0.45940664 | CA76: 0.45940664 | CB76: 0 | CC76: 0.073903002 | CD76: 0 | CE76: 0 | CF76: 0.46669035 | CG76: 0 | CH76: 0 | CI76: 3.1031808 | CJ76: 0.53335919 | CK76: 436 | CL76: 603.99 | CM76: =CL76-CK76 -> 167.99 | CN76: 7.62 | CO76: 9.45 | CP76: =CO76-CN76 -> 1.83 | CQ76: 634.92 | CR76: 193.15 | CS76: =CQ76-CR76 -> 441.77 | CT76: No | CU76: 80.58 | CV76: 431 | CW76: 2586 | CX76: =((CW76-CY76)/BT76)*100 -> 42.956298 | CY76: 167.99 | CZ76: =((CW76)/BT76)*100 -> 45.940664 | DA76: =DB76/(CY76+BT76) -> 623.75399 | DB76: 3615895.7 | DC76: =DD76/(CY76+BT76) -> 19.308013 | DD76: 111928.36 | DE76: 2586 | DF76: 43.296 | DG76: 148.9 | DH76: 45.941 | DI76: 1138.67 | DJ76: 6579106 | DK76: 34.994 | DL76: 202189.4 | DM76: 2586 | DN76: 43.726 | DO76: 124.7 | DP76: 45.941 | DQ76: 1106.217 | DR76: 6364810 | DS76: 33.982 | DT76: 195521.4
A77: Noreste | B77: Monterrey | C77: Sucursal Santa Catarina | D77: 712303 | E77: Noreste|Sucursal Santa Catarina|712303 | F77: Activa | G77: Sí | H77: Sí | I77: 18 | J77: 56471.117 | K77: 16169.557 | L77: 72640.674 | M77: 2941446 | N77: 827193 | O77: 2114220 | P77: 33 | Q77: 6493.6067 | R77: 5698.9829 | S77: 19312.021 | T77: 1950.6941 | U77: =IFERROR(INDEX('Rentabilidad datos'!$N$2:$N$61,MATCH($C77,'Rentabilidad datos'!$C$2:$C$61,0)),"") -> 26961.698 | V77: =IFERROR(INDEX('Rentabilidad datos'!$O$2:$O$61,MATCH($C77,'Rentabilidad datos'!$C$2:$C$61,0)),"") -> 1497.8721 | W77: =IFERROR(INDEX('Rentabilidad datos'!$M$2:$M$61,MATCH($C77,'Rentabilidad datos'!$C$2:$C$61,0)),"") -> 3467.2961 | X77: =IFERROR(INDEX('Rentabilidad datos'!$P$2:$P$61,MATCH($C77,'Rentabilidad datos'!$C$2:$C$61,0)),"") -> 0.43200005 | Y77: C2 | Z77: 47 | AA77: 1 | AB77: 0.99859185 | AC77: 0.001408151 | AD77: =_xlfn.XLOOKUP(Table1[[#This Row],[Ruta]],#REF!,#REF!) -> #REF! | AE77: =_xlfn.XLOOKUP(Table1[[#This Row],[Ruta]],#REF!,#REF!) -> #REF! | AF77: =_xlfn.XLOOKUP(Table1[[#This Row],[Ruta]],#REF!,#REF!) -> #REF! | AG77: =_xlfn.XLOOKUP(Table1[[#This Row],[Ruta]],#REF!,#REF!) -> #REF! | AH77: 0.28121985 | AI77: 0.71876893 | AJ77: 1.1218972e-05 | AK77: 14570 | AL77: 11865 | AM77: 0.68949897 | AN77: 0.83144613 | AO77: 2068.1702 | AP77: 1034.0851 | AQ77: 0.88531813 | AR77: 2831212.5 | AS77: 246752.18 | AT77: 0.087154243 | AU77: 173393.43 | AV77: 0.0007887831 | AW77: 333 | AX77: 238.61884 | AY77: 377.8548 | AZ77: 139.23596 | BA77: Sí | BB77: 580444.62 | BC77: 753838.05 | BD77: Sí | BE77: 47 | BF77: 48.897321 | BG77: No | BH77: 0.68949897 | BI77: 0.79215712 | BJ77: No | BK77: 166.60705 | BL77: 326.54714 | BM77: No | BN77: 0 | BO77: Verde - Con espacio | BP77: No | BQ77: 1699.7664 | BR77: 534 | BS77: 42623 | BT77: 11893 | BU77: 3.5838729 | BV77: 22.271536 | BW77: 2381 | BX77: 1742 | BY77: 4123 | BZ77: 0.34667451 | CA77: 0.2002018 | CB77: 0.14647272 | CC77: 0.24333642 | CD77: 0.19406373 | CE77: 0 | CF77: 0.21592533 | CG77: 0 | CH77: 0 | CI77: 2.7215353 | CJ77: 0.35192267 | CK77: 409 | CL77: 769.03 | CM77: =CL77-CK77 -> 360.03 | CN77: 5.54 | CO77: 9.45 | CP77: =CO77-CN77 -> 3.91 | CQ77: 634.92 | CR77: 166.61 | CS77: =CQ77-CR77 -> 468.31 | CT77: No | CU77: 58.91 | CV77: 213 | CW77: 4123 | CX77: =((CW77-CY77)/BT77)*100 -> 31.640209 | CY77: 360.03 | CZ77: =((CW77)/BT77)*100 -> 34.667451 | DA77: =DB77/(CY77+BT77) -> 372.48286 | DB77: 4564043.6 | DC77: =DD77/(CY77+BT77) -> 8.8404713 | DD77: 108322.56 | DE77: 4123 | DF77: 32.309 | DG77: 280.5 | DH77: 34.667 | DI77: 575.531 | DJ77: 7006209 | DK77: 13.719 | DL77: 167002.9 | DM77: 4123 | DN77: 32.585 | DO77: 247.6 | DP77: 34.667 | DQ77: 561.289 | DR77: 6814407 | DS77: 13.373 | DT77: 162351
A78: Noreste | B78: Monterrey | C78: Sucursal Santa Catarina | D78: 712304 | E78: Noreste|Sucursal Santa Catarina|712304 | F78: Activa | G78: Sí | H78: Sí | I78: 18 | J78: 18591.227 | K78: 6240.8518 | L78: 24832.079 | M78: 907512 | N78: 250119 | O78: 657393 | P78: 0 | Q78: 2680.4811 | R78: 5698.9829 | S78: 19312.021 | T78: 1950.6941 | U78: =IFERROR(INDEX('Rentabilidad datos'!$N$2:$N$61,MATCH($C78,'Rentabilidad datos'!$C$2:$C$61,0)),"") -> 26961.698 | V78: =IFERROR(INDEX('Rentabilidad datos'!$O$2:$O$61,MATCH($C78,'Rentabilidad datos'!$C$2:$C$61,0)),"") -> 1497.8721 | W78: =IFERROR(INDEX('Rentabilidad datos'!$M$2:$M$61,MATCH($C78,'Rentabilidad datos'!$C$2:$C$61,0)),"") -> 3467.2961 | X78: =IFERROR(INDEX('Rentabilidad datos'!$P$2:$P$61,MATCH($C78,'Rentabilidad datos'!$C$2:$C$61,0)),"") -> 0.43200005 | Y78: C2 | Z78: 63.97037 | AA78: 1 | AB78: 0.99966502 | AC78: 0.0003349818 | AD78: =_xlfn.XLOOKUP(Table1[[#This Row],[Ruta]],#REF!,#REF!) -> #REF! | AE78: =_xlfn.XLOOKUP(Table1[[#This Row],[Ruta]],#REF!,#REF!) -> #REF! | AF78: =_xlfn.XLOOKUP(Table1[[#This Row],[Ruta]],#REF!,#REF!) -> #REF! | AG78: =_xlfn.XLOOKUP(Table1[[#This Row],[Ruta]],#REF!,#REF!) -> #REF! | AH78: 0.27560958 | AI78: 0.72439042 | AJ78: 0 | AK78: 8636 | AL78: 4566 | AM78: 0.33117184 | AN78: 0.83144613 | AO78: 4320.3688 | AP78: 2160.1844 | AQ78: 0.77885415 | AR78: 986417.05 | AS78: 466676.03 | AT78: 0.47310215 | AU78: 327934.5 | AV78: 0.0014918051 | AW78: 227 | AX78: 216.03527 | AY78: 377.8548 | AZ78: 161.81953 | BA78: Sí | BB78: 259602.26 | BC78: 587536.76 | BD78: Sí | BE78: 63.97037 | BF78: 48.897321 | BG78: Sí | BH78: 0.33117184 | BI78: 0.79215712 | BJ78: No | BK78: 67.478476 | BL78: 326.54714 | BM78: No | BN78: 1 | BO78: Verde - Con espacio | BP78: No | BQ78: 2719.9154 | BR78: 634 | BS78: 66464 | BT78: 17318 | BU78: 3.8378566 | BV78: 27.315457 | BW78: 6 | BX78: 1110 | BY78: 1116 | BZ78: 0.064441621 | CA78: 0.00034646033 | CB78: 0.064095161 | CC78: 0.5476383 | CD78: 0.096777919 | CE78: 0 | CF78: 0.2899873 | CG78: 0.0011548678 | CH78: 0 | CI78: 3.0091478 | CJ78: 0.36109774 | CK78: 565 | CL78: 684.54 | CM78: =CL78-CK78 -> 119.54 | CN78: 6.24 | CO78: 9.45 | CP78: =CO78-CN78 -> 3.21 | CQ78: 634.92 | CR78: 67.48 | CS78: =CQ78-CR78 -> 567.44 | CT78: No | CU78: 66.08 | CV78: 11 | CW78: 1116 | CX78: =((CW78-CY78)/BT78)*100 -> 5.7538977 | CY78: 119.54 | CZ78: =((CW78)/BT78)*100 -> 6.4441621 | DA78: =DB78/(CY78+BT78) -> 131.86339 | DB78: 2299373.1 | DC78: =DD78/(CY78+BT78) -> 3.0260002 | DD78: 52766 | DE78: 1116 | DF78: 5.885 | DG78: 96.8 | DH78: 6.444 | DI78: 231.168 | DJ78: 4025751 | DK78: 5.69 | DL78: 99091.9 | DM78: 1116 | DN78: 5.944 | DO78: 86.6 | DP78: 6.444 | DQ78: 229.293 | DR78: 3990759 | DS78: 5.645 | DT78: 98245.2
A79: Noreste | B79: Monterrey | C79: Sucursal Santa Catarina | D79: 712305 | E79: Noreste|Sucursal Santa Catarina|712305 | F79: Activa | G79: Sí | H79: Sí | I79: 18 | J79: 125851.83 | K79: 22910.322 | L79: 148762.15 | M79: 5106868 | N79: 1874911 | O79: 3231957 | P79: 0 | Q79: 11639.094 | R79: 5698.9829 | S79: 19312.021 | T79: 1950.6941 | U79: =IFERROR(INDEX('Rentabilidad datos'!$N$2:$N$61,MATCH($C79,'Rentabilidad datos'!$C$2:$C$61,0)),"") -> 26961.698 | V79: =IFERROR(INDEX('Rentabilidad datos'!$O$2:$O$61,MATCH($C79,'Rentabilidad datos'!$C$2:$C$61,0)),"") -> 1497.8721 | W79: =IFERROR(INDEX('Rentabilidad datos'!$M$2:$M$61,MATCH($C79,'Rentabilidad datos'!$C$2:$C$61,0)),"") -> 3467.2961 | X79: =IFERROR(INDEX('Rentabilidad datos'!$P$2:$P$61,MATCH($C79,'Rentabilidad datos'!$C$2:$C$61,0)),"") -> 0.43200005 | Y79: C2 | Z79: 96.313043 | AA79: 1 | AB79: 0.99872544 | AC79: 0.0012745581 | AD79: =_xlfn.XLOOKUP(Table1[[#This Row],[Ruta]],#REF!,#REF!) -> #REF! | AE79: =_xlfn.XLOOKUP(Table1[[#This Row],[Ruta]],#REF!,#REF!) -> #REF! | AF79: =_xlfn.XLOOKUP(Table1[[#This Row],[Ruta]],#REF!,#REF!) -> #REF! | AG79: =_xlfn.XLOOKUP(Table1[[#This Row],[Ruta]],#REF!,#REF!) -> #REF! | AH79: 0.3671352 | AI79: 0.6328648 | AJ79: 0 | AK79: 33228 | AL79: 15308 | AM79: 0.42704948 | AN79: 0.83144613 | AO79: 13437.292 | AP79: 6718.6461 | AQ79: 0.66289413 | AR79: 5051366.9 | AS79: 2217033.3 | AT79: 0.43889771 | AU79: 1557915.3 | AV79: 0.0070871042 | AW79: 14 | AX79: 329.98216 | AY79: 377.8548 | AZ79: 47.872642 | BA79: Sí | BB79: 257482.36 | BC79: 1815397.7 | BD79: Sí | BE79: 96.313043 | BF79: 48.897321 | BG79: Sí | BH79: 0.42704948 | BI79: 0.79215712 | BJ79: No | BK79: 342.76993 | BL79: 326.54714 | BM79: Sí | BN79: 2 | BO79: Amarillo - Cerca del tope | BP79: No | BQ79: 4910.1888 | BR79: 1012 | BS79: 104367 | BT79: 27783 | BU79: 3.7565058 | BV79: 27.453557 | BW79: 802 | BX79: 6048 | BY79: 6850 | BZ79: 0.24655365 | CA79: 0.028866573 | CB79: 0.21768707 | CC79: 0.27574416 | CD79: 0.17640284 | CE79: 0 | CF79: 0.30129936 | CG79: 0 | CH79: 0 | CI79: 2.9894507 | CJ79: 0.28744718 | CK79: 818 | CL79: 1162.61 | CM79: =CL79-CK79 -> 344.61 | CN79: 10.06 | CO79: 9.45 | CP79: =CO79-CN79 -> -0.61 | CQ79: 634.92 | CR79: 342.77 | CS79: =CQ79-CR79 -> 292.15 | CT79: Sí | CU79: 106.41 | CV79: 410 | CW79: 6850 | CX79: =((CW79-CY79)/BT79)*100 -> 23.415002 | CY79: 344.61 | CZ79: =((CW79)/BT79)*100 -> 24.655365 | DA79: =DB79/(CY79+BT79) -> 221.41892 | DB79: 6227985.1 | DC79: =DD79/(CY79+BT79) -> 6.8525691 | DD79: 192746.39 | DE79: 6850 | DF79: 23.422 | DG79: 342.7 | DH79: 24.655 | DI79: 339.936 | DJ79: 9560955 | DK79: 10.472 | DL79: 294528.1 | DM79: 6850 | DN79: 23.459 | DO79: 332.5 | DP79: 24.655 | DQ79: 337.986 | DR79: 9502637 | DS79: 10.401 | DT79: 292438.7
... A92: Noreste | B92: Monterrey | C92: Sucursal Santa Catarina | D92: 712319 | E92: Noreste|Sucursal Santa Catarina|712319 | F92: Activa | G92: Sí | H92: Sí | I92: 18 | J92: 57196.731 | K92: 21433.824 | L92: 78630.555 | M92: 3779744 | N92: 841665 | O92: 2938079 | P92: 0 | Q92: 9544.8 | R92: 5698.9829 | S92: 19312.021 | T92: 1950.6941 | U92: =IFERROR(INDEX('Rentabilidad datos'!$N$2:$N$61,MATCH($C92,'Rentabilidad datos'!$C$2:$C$61,0)),"") -> 26961.698 | V92: =IFERROR(INDEX('Rentabilidad datos'!$O$2:$O$61,MATCH($C92,'Rentabilidad datos'!$C$2:$C$61,0)),"") -> 1497.8721 | W92: =IFERROR(INDEX('Rentabilidad datos'!$M$2:$M$61,MATCH($C92,'Rentabilidad datos'!$C$2:$C$61,0)),"") -> 3467.2961 | X92: =IFERROR(INDEX('Rentabilidad datos'!$P$2:$P$61,MATCH($C92,'Rentabilidad datos'!$C$2:$C$61,0)),"") -> 0.43200005 | Y92: C2 | Z92: 50.17341 | AA92: 1 | AB92: 1 | AC92: 0 | AD92: =_xlfn.XLOOKUP(Table1[[#This Row],[Ruta]],#REF!,#REF!) -> #REF! | AE92: =_xlfn.XLOOKUP(Table1[[#This Row],[Ruta]],#REF!,#REF!) -> #REF! | AF92: =_xlfn.XLOOKUP(Table1[[#This Row],[Ruta]],#REF!,#REF!) -> #REF! | AG92: =_xlfn.XLOOKUP(Table1[[#This Row],[Ruta]],#REF!,#REF!) -> #REF! | AH92: 0.22267778 | AI92: 0.77732222 | AJ92: 0 | AK92: 8680 | AL92: 13377 | AM92: 0.92384793 | AN92: 0.83144613 | AO92: 0 | AP92: 0 | AQ92: 1.541129 | AR92: 3779740.8 | AS92: 0 | AT92: 0 | AU92: 0 | AV92: 0 | AW92: 490 | AX92: 282.55519 | AY92: 377.8548 | AZ92: 95.299609 | BA92: Sí | BB92: 447910.74 | BC92: 447910.74 | BD92: Sí | BE92: 50.17341 | BF92: 48.897321 | BG92: Sí | BH92: 0.92384793 | BI92: 0.79215712 | BJ92: Sí | BK92: 198.56201 | BL92: 326.54714 | BM92: No | BN92: 2 | BO92: Amarillo - Cerca del tope | BP92: No | BQ92: 0 | BR92: 55 | BS92: 3058 | BT92: 820 | BU92: 3.7292683 | BV92: 14.909091 | BW92: 820 | BX92: 0 | BY92: 820 | BZ92: 1 | CA92: 1 | CB92: 0 | CC92: 0 | CD92: 0 | CE92: 0 | CF92: 0 | CG92: 0 | CH92: 0 | CI92: 0 | CJ92: 0 | CK92: 337 | CL92: 592.58 | CM92: =CL92-CK92 -> 255.58 | CN92: 5.38 | CO92: 9.45 | CP92: =CO92-CN92 -> 4.07 | CQ92: 634.92 | CR92: 198.56 | CS92: =CQ92-CR92 -> 436.36 | CT92: No | CU92: 56.95 | CV92: 354 | CW92: 820 | CX92: =((CW92-CY92)/BT92)*100 -> 68.831707 | CY92: 255.58 | CZ92: =((CW92)/BT92)*100 -> 100 | DA92: =DB92/(CY92+BT92) -> 6675.982 | DB92: 7180552.7 | DC92: =DD92/(CY92+BT92) -> 130.82049 | DD92: 140707.9 | DE92: 820 | DF92: 75.033 | DG92: 204.7 | DH92: 100 | DI92: 9228.837 | DJ92: 9457073 | DK92: 184.17 | DL92: 188724.4 | DM92: 820 | DN92: 79.439 | DO92: 168.6 | DP92: 100 | DQ92: 9034.372 | DR92: 8931396 | DS92: 180.487 | DT92: 178429.5
A93: Noreste | B93: Monterrey | C93: Sucursal Universidad | D93: 703300 | E93: Noreste|Sucursal Universidad|703300 | F93: Activa | G93: Sí | H93: Sí | I93: 10 | J93: 135154.49 | K93: 27791.659 | L93: 162946.15 | M93: 5012440 | N93: 1894568 | O93: 3104865 | P93: 13007 | Q93: 11466.589 | R93: 3985.3089 | S93: 10709.393 | T93: 1083.7189 | U93: =IFERROR(INDEX('Rentabilidad datos'!$N$2:$N$61,MATCH($C93,'Rentabilidad datos'!$C$2:$C$61,0)),"") -> 15778.421 | V93: =IFERROR(INDEX('Rentabilidad datos'!$O$2:$O$61,MATCH($C93,'Rentabilidad datos'!$C$2:$C$61,0)),"") -> 1577.8421 | W93: =IFERROR(INDEX('Rentabilidad datos'!$M$2:$M$61,MATCH($C93,'Rentabilidad datos'!$C$2:$C$61,0)),"") -> 3111.2207 | X93: =IFERROR(INDEX('Rentabilidad datos'!$P$2:$P$61,MATCH($C93,'Rentabilidad datos'!$C$2:$C$61,0)),"") -> 0.50714566 | Y93: C2 | Z93: 42.33945 | AA93: 1 | AB93: 0.017044394 | AC93: 0.98295561 | AD93: =_xlfn.XLOOKUP(Table1[[#This Row],[Ruta]],#REF!,#REF!) -> #REF! | AE93: =_xlfn.XLOOKUP(Table1[[#This Row],[Ruta]],#REF!,#REF!) -> #REF! | AF93: =_xlfn.XLOOKUP(Table1[[#This Row],[Ruta]],#REF!,#REF!) -> #REF! | AG93: =_xlfn.XLOOKUP(Table1[[#This Row],[Ruta]],#REF!,#REF!) -> #REF! | AH93: 0.3779732 | AI93: 0.61943185 | AJ93: 0.0025949438 | AK93: 18460 | AL93: 11678 | AM93: 0.63261105 | AN93: 0.70449135 | AO93: 1326.9103 | AP93: 663.45517 | AQ93: 0.6685512 | AR93: 4999432.7 | AS93: 284029.75 | AT93: 0.056812396 | AU93: 199588.48 | AV93: 0.00090794686 | AW93: 313 | AX93: 428.10693 | AY93: 445.23273 | AZ93: 17.125804 | BA93: Sí | BB93: 70268.562 | BC93: 269857.04 | BD93: Sí | BE93: 42.33945 | BF93: 48.897321 | BG93: No | BH93: 0.63261105 | BI93: 0.79215712 | BJ93: No | BK93: 373.7297 | BL93: 326.54714 | BM93: Sí | BN93: 1 | BO93: Verde - Con espacio | BP93: No | BQ93: 841.38129 | BR93: 1002 | BS93: 86090 | BT93: 23353 | BU93: 3.6864643 | BV93: 23.306387 | BW93: 0 | BX93: 2778 | BY93: 2778 | BZ93: 0.11895688 | CA93: 0 | CB93: 0.11895688 | CC93: 0.35258853 | CD93: 0.27101443 | CE93: 0 | CF93: 0.25739734 | CG93: 0 | CH93: 4.2821051e-05 | CI93: 3.6473458 | CJ93: 0.48786154 | CM93: =CL93-CK93 -> 0 | CP93: =CO93-CN93 -> 0 | CS93: =CQ93-CR93 -> 0 | CX93: =((CW93-CY93)/BT93)*100 -> 0 | CZ93: =((CW93)/BT93)*100 -> 0 | DA93: =DB93/(CY93+BT93) -> 0 | DC93: =DD93/(CY93+BT93) -> 0
A94: Noreste | B94: Monterrey | C94: Sucursal Universidad | D94: 703301 | E94: Noreste|Sucursal Universidad|703301 | F94: Activa | G94: Sí | H94: Sí | I94: 10 | J94: 163900.79 | K94: 37892.062 | L94: 201792.86 | M94: 6110496 | N94: 2192302 | O94: 3912181 | P94: 6013 | Q94: 15581.414 | R94: 3985.3089 | S94: 10709.393 | T94: 1083.7189 | U94: =IFERROR(INDEX('Rentabilidad datos'!$N$2:$N$61,MATCH($C94,'Rentabilidad datos'!$C$2:$C$61,0)),"") -> 15778.421 | V94: =IFERROR(INDEX('Rentabilidad datos'!$O$2:$O$61,MATCH($C94,'Rentabilidad datos'!$C$2:$C$61,0)),"") -> 1577.8421 | W94: =IFERROR(INDEX('Rentabilidad datos'!$M$2:$M$61,MATCH($C94,'Rentabilidad datos'!$C$2:$C$61,0)),"") -> 3111.2207 | X94: =IFERROR(INDEX('Rentabilidad datos'!$P$2:$P$61,MATCH($C94,'Rentabilidad datos'!$C$2:$C$61,0)),"") -> 0.50714566 | Y94: C2 | Z94: 41.758065 | AA94: 1 | AB94: 0.022937418 | AC94: 0.97706258 | AD94: =_xlfn.XLOOKUP(Table1[[#This Row],[Ruta]],#REF!,#REF!) -> #REF! | AE94: =_xlfn.XLOOKUP(Table1[[#This Row],[Ruta]],#REF!,#REF!) -> #REF! | AF94: =_xlfn.XLOOKUP(Table1[[#This Row],[Ruta]],#REF!,#REF!) -> #REF! | AG94: =_xlfn.XLOOKUP(Table1[[#This Row],[Ruta]],#REF!,#REF!) -> #REF! | AH94: 0.35877644 | AI94: 0.64023952 | AJ94: 0.0009840445 | AK94: 18123 | AL94: 13701 | AM94: 0.75600066 | AN94: 0.70449135 | AO94: 0 | AP94: 0 | AQ94: 0.75600066 | AR94: 6762333.9 | AS94: 0 | AT94: 0 | AU94: 0 | AV94: 0 | AW94: 490 | AX94: 493.56499 | AY94: 445.23273 | AZ94: 0 | BA94: No | BB94: 0 | BC94: 0 | BD94: Sí | BE94: 41.758065 | BF94: 48.897321 | BG94: No | BH94: 0.75600066 | BI94: 0.79215712 | BJ94: No | BK94: 464.9605 | BL94: 326.54714 | BM94: Sí | BN94: 1 | BO94: Verde - Con espacio | BP94: No | BQ94: 0 | BR94: 23 | BS94: 94 | BT94: 23 | BU94: 4.0869565 | BV94: 1 | BW94: 0 | BX94: 0 | BY94: 0 | BZ94: 0 | CA94: 0 | CB94: 0 | CC94: 0 | CD94: 0 | CE94: 0 | CF94: 1 | CG94: 0 | CH94: 0 | CI94: 0 | CJ94: 0 | CM94: =CL94-CK94 -> 0 | CP94: =CO94-CN94 -> 0 | CS94: =CQ94-CR94 -> 0 | CX94: =((CW94-CY94)/BT94)*100 -> 0 | CZ94: =((CW94)/BT94)*100 -> 0 | DA94: =DB94/(CY94+BT94) -> 0 | DC94: =DD94/(CY94+BT94) -> 0
A95: Noreste | B95: Monterrey | C95: Sucursal Universidad | D95: 703302 | E95: Noreste|Sucursal Universidad|703302 | F95: Activa | G95: Sí | H95: Sí | I95: 10 | J95: 208339.39 | K95: 38429.11 | L95: 246768.5 | M95: 7523765 | N95: 2925596 | O95: 4582788 | P95: 15381 | Q95: 17411.257 | R95: 3985.3089 | S95: 10709.393 | T95: 1083.7189 | U95: =IFERROR(INDEX('Rentabilidad datos'!$N$2:$N$61,MATCH($C95,'Rentabilidad datos'!$C$2:$C$61,0)),"") -> 15778.421 | V95: =IFERROR(INDEX('Rentabilidad datos'!$O$2:$O$61,MATCH($C95,'Rentabilidad datos'!$C$2:$C$61,0)),"") -> 1577.8421 | W95: =IFERROR(INDEX('Rentabilidad datos'!$M$2:$M$61,MATCH($C95,'Rentabilidad datos'!$C$2:$C$61,0)),"") -> 3111.2207 | X95: =IFERROR(INDEX('Rentabilidad datos'!$P$2:$P$61,MATCH($C95,'Rentabilidad datos'!$C$2:$C$61,0)),"") -> 0.50714566 | Y95: C2 | Z95: 50.116705 | AA95: 1 | AB95: 0.024634475 | AC95: 0.97536553 | AD95: =_xlfn.XLOOKUP(Table1[[#This Row],[Ruta]],#REF!,#REF!) -> #REF! | AE95: =_xlfn.XLOOKUP(Table1[[#This Row],[Ruta]],#REF!,#REF!) -> #REF! | AF95: =_xlfn.XLOOKUP(Table1[[#This Row],[Ruta]],#REF!,#REF!) -> #REF! | AG95: =_xlfn.XLOOKUP(Table1[[#This Row],[Ruta]],#REF!,#REF!) -> #REF! | AH95: 0.38884734 | AI95: 0.60910834 | AJ95: 0.0020443222 | AK95: 21901 | AL95: 20549 | AM95: 0.93826766 | AN95: 0.70449135 | AO95: 0 | AP95: 0 | AQ95: 0.93826766 | AR95: 7608719.4 | AS95: 0 | AT95: 0 | AU95: 0 | AV95: 0 | AW95: 490 | AX95: 370.272 | AY95: 445.23273 | AZ95: 74.96073 | BA95: Sí | BB95: 541210.39 | BC95: 541210.39 | BD95: Sí | BE95: 50.116705 | BF95: 48.897321 | BG95: Sí | BH95: 0.93826766 | BI95: 0.79215712 | BJ95: Sí | BK95: 564.68765 | BL95: 326.54714 | BM95: Sí | BN95: 3 | BO95: Rojo - Saturada | BP95: Sí | BQ95: 0 | BR95: 1 | BS95: 0 | BT95: 0 | BV95: 0 | BW95: 0 | BX95: 0 | BY95: 0 | CM95: =CL95-CK95 -> 0 | CP95: =CO95-CN95 -> 0 | CS95: =CQ95-CR95 -> 0 | CX95: =((CW95-CY95)/BT95)*100 -> #DIV/0! | CZ95: =((CW95)/BT95)*100 -> #DIV/0! | DA95: =DB95/(CY95+BT95) -> #DIV/0! | DC95: =DD95/(CY95+BT95) -> #DIV/0!
A96: Noreste | B96: Monterrey | C96: Sucursal Universidad | D96: 703303 | E96: Noreste|Sucursal Universidad|703303 | F96: Activa | G96: Sí | H96: Sí | I96: 10 | J96: 100596.22 | K96: 20274.968 | L96: 120871.19 | M96: 2814482 | N96: 1243901 | O96: 1565728 | P96: 4853 | Q96: 8539.058 | R96: 3985.3089 | S96: 10709.393 | T96: 1083.7189 | U96: =IFERROR(INDEX('Rentabilidad datos'!$N$2:$N$61,MATCH($C96,'Rentabilidad datos'!$C$2:$C$61,0)),"") -> 15778.421 | V96: =IFERROR(INDEX('Rentabilidad datos'!$O$2:$O$61,MATCH($C96,'Rentabilidad datos'!$C$2:$C$61,0)),"") -> 1577.8421 | W96: =IFERROR(INDEX('Rentabilidad datos'!$M$2:$M$61,MATCH($C96,'Rentabilidad datos'!$C$2:$C$61,0)),"") -> 3111.2207 | X96: =IFERROR(INDEX('Rentabilidad datos'!$P$2:$P$61,MATCH($C96,'Rentabilidad datos'!$C$2:$C$61,0)),"") -> 0.50714566 | Y96: C2 | Z96: 40.960784 | AA96: 1 | AB96: 0.055135901 | AC96: 0.9448641 | AD96: =_xlfn.XLOOKUP(Table1[[#This Row],[Ruta]],#REF!,#REF!) -> #REF! | AE96: =_xlfn.XLOOKUP(Table1[[#This Row],[Ruta]],#REF!,#REF!) -> #REF! | AF96: =_xlfn.XLOOKUP(Table1[[#This Row],[Ruta]],#REF!,#REF!) -> #REF! | AG96: =_xlfn.XLOOKUP(Table1[[#This Row],[Ruta]],#REF!,#REF!) -> #REF! | AH96: 0.44196445 | AI96: 0.55631125 | AJ96: 0.001724296 | AK96: 16712 | AL96: 8294 | AM96: 0.44848013 | AN96: 0.70449135 | AO96: 4278.4595 | AP96: 2139.2297 | AQ96: 0.6242957 | AR96: 3740107.4 | AS96: 964667.1 | AT96: 0.25792497 | AU96: 677874.18 | AV96: 0.0030837138 | AW96: 100 | AX96: 450.94133 | AY96: 445.23273 | AZ96: 0 | BA96: No | BB96: 0 | BC96: 677874.18 | BD96: Sí | BE96: 40.960784 | BF96: 48.897321 | BG96: No | BH96: 0.44848013 | BI96: 0.79215712 | BJ96: No | BK96: 275.96162 | BL96: 326.54714 | BM96: No | BN96: 0 | BO96: Verde - Con espacio | BP96: No | BQ96: 3360.3153 | BR96: 13 | BS96: 141 | BT96: 56 | BU96: 2.5178571 | BV96: 4.3076923 | BW96: 0 | BX96: 0 | BY96: 0 | BZ96: 0 | CA96: 0 | CB96: 0 | CC96: 0 | CD96: 0 | CE96: 0 | CF96: 1 | CG96: 0 | CH96: 0 | CI96: 0 | CJ96: 0 | CM96: =CL96-CK96 -> 0 | CP96: =CO96-CN96 -> 0 | CS96: =CQ96-CR96 -> 0 | CX96: =((CW96-CY96)/BT96)*100 -> 0 | CZ96: =((CW96)/BT96)*100 -> 0 | DA96: =DB96/(CY96+BT96) -> 0 | DC96: =DD96/(CY96+BT96) -> 0
A97: Noreste | B97: Monterrey | C97: Sucursal Universidad | D97: 703304 | E97: Noreste|Sucursal Universidad|703304 | F97: Activa | G97: Sí | H97: Sí | I97: 10 | J97: 116602.01 | K97: 25466.311 | L97: 142068.32 | M97: 3199810 | N97: 1277559 | O97: 1919088 | P97: 3163 | Q97: 10467.346 | R97: 3985.3089 | S97: 10709.393 | T97: 1083.7189 | U97: =IFERROR(INDEX('Rentabilidad datos'!$N$2:$N$61,MATCH($C97,'Rentabilidad datos'!$C$2:$C$61,0)),"") -> 15778.421 | V97: =IFERROR(INDEX('Rentabilidad datos'!$O$2:$O$61,MATCH($C97,'Rentabilidad datos'!$C$2:$C$61,0)),"") -> 1577.8421 | W97: =IFERROR(INDEX('Rentabilidad datos'!$M$2:$M$61,MATCH($C97,'Rentabilidad datos'!$C$2:$C$61,0)),"") -> 3111.2207 | X97: =IFERROR(INDEX('Rentabilidad datos'!$P$2:$P$61,MATCH($C97,'Rentabilidad datos'!$C$2:$C$61,0)),"") -> 0.50714566 | Y97: C2 | Z97: 41.931663 | AA97: 1 | AB97: 0.05238436 | AC97: 0.94761564 | AD97: =_xlfn.XLOOKUP(Table1[[#This Row],[Ruta]],#REF!,#REF!) -> #REF! | AE97: =_xlfn.XLOOKUP(Table1[[#This Row],[Ruta]],#REF!,#REF!) -> #REF! | AF97: =_xlfn.XLOOKUP(Table1[[#This Row],[Ruta]],#REF!,#REF!) -> #REF! | AG97: =_xlfn.XLOOKUP(Table1[[#This Row],[Ruta]],#REF!,#REF!) -> #REF! | AH97: 0.39926089 | AI97: 0.59975061 | AJ97: 0.00098849619 | AK97: 18408 | AL97: 10167 | AM97: 0.55231421 | AN97: 0.70449135 | AO97: 2801.2768 | AP97: 1400.6384 | AQ97: 0.62840278 | AR97: 4595165 | AS97: 633044.61 | AT97: 0.13776319 | AU97: 444842.16 | AV97: 0.0020236291 | AW97: 167 | AX97: 451.96863 | AY97: 445.23273 | AZ97: 0 | BA97: No | BB97: 0 | BC97: 444842.16 | BD97: Sí | BE97: 41.931663 | BF97: 48.897321 | BG97: No | BH97: 0.55231421 | BI97: 0.79215712 | BJ97: No | BK97: 323.61804 | BL97: 326.54714 | BM97: No | BN97: 0 | BO97: Verde - Con espacio | BP97: No | BQ97: 4323.4719 | BR97: 193 | BS97: 6460 | BT97: 1796 | BU97: 3.596882 | BV97: 9.3056995 | BW97: 1 | BX97: 14 | BY97: 15 | BZ97: 0.0083518931 | CA97: 0.00055679287 | CB97: 0.0077951002 | CC97: 0.30734967 | CD97: 0.017817372 | CE97: 0 | CF97: 0.6636971 | CG97: 0.0027839644 | CH97: 0 | CI97: 3.0959752 | CJ97: 1.7027864 | CM97: =CL97-CK97 -> 0 | CP97: =CO97-CN97 -> 0 | CS97: =CQ97-CR97 -> 0 | CX97: =((CW97-CY97)/BT97)*100 -> 0 | CZ97: =((CW97)/BT97)*100 -> 0 | DA97: =DB97/(CY97+BT97) -> 0 | DC97: =DD97/(CY97+BT97) -> 0
A98: Noreste | B98: Monterrey | C98: Sucursal Universidad | D98: 703305 | E98: Noreste|Sucursal Universidad|703305 | F98: Activa | G98: Sí | H98: Sí | I98: 10 | J98: 55875.831 | K98: 8874.2431 | L98: 64750.074 | M98: 6234311 | N98: 1784179 | O98: 4436962 | P98: 13170 | Q98: 4103.941 | R98: 3985.3089 | S98: 10709.393 | T98: 1083.7189 | U98: =IFERROR(INDEX('Rentabilidad datos'!$N$2:$N$61,MATCH($C98,'Rentabilidad datos'!$C$2:$C$61,0)),"") -> 15778.421 | V98: =IFERROR(INDEX('Rentabilidad datos'!$O$2:$O$61,MATCH($C98,'Rentabilidad datos'!$C$2:$C$61,0)),"") -> 1577.8421 | W98: =IFERROR(INDEX('Rentabilidad datos'!$M$2:$M$61,MATCH($C98,'Rentabilidad datos'!$C$2:$C$61,0)),"") -> 3111.2207 | X98: =IFERROR(INDEX('Rentabilidad datos'!$P$2:$P$61,MATCH($C98,'Rentabilidad datos'!$C$2:$C$61,0)),"") -> 0.50714566 | Y98: C2 | Z98: 39.208723 | AA98: 1 | AB98: 0.04518286 | AC98: 0.95481714 | AD98: =_xlfn.XLOOKUP(Table1[[#This Row],[Ruta]],#REF!,#REF!) -> #REF! | AE98: =_xlfn.XLOOKUP(Table1[[#This Row],[Ruta]],#REF!,#REF!) -> #REF! | AF98: =_xlfn.XLOOKUP(Table1[[#This Row],[Ruta]],#REF!,#REF!) -> #REF! | AG98: =_xlfn.XLOOKUP(Table1[[#This Row],[Ruta]],#REF!,#REF!) -> #REF! | AH98: 0.28618704 | AI98: 0.71170046 | AJ98: 0.0021125029 | AK98: 12586 | AL98: 4834 | AM98: 0.29032258 | AN98: 0.70449135 | AO98: 5212.7281 | AP98: 2606.3641 | AQ98: 0.59116193 | AR98: 1785214.3 | AS98: 962540.03 | AT98: 0.53917337 | AU98: 676379.48 | AV98: 0.0030769143 | AW98: 101 | AX98: 369.30375 | AY98: 445.23273 | AZ98: 75.928982 | BA98: Sí | BB98: 128960.25 | BC98: 805339.72 | BD98: Sí | BE98: 39.208723 | BF98: 48.897321 | BG98: No | BH98: 0.29032258 | BI98: 0.79215712 | BJ98: No | BK98: 148.85075 | BL98: 326.54714 | BM98: No | BN98: 0 | BO98: Verde - Con espacio | BP98: No | BQ98: 5552.4869 | BR98: #N/A | BS98: #N/A | BT98: #N/A | BU98: #N/A | BV98: #N/A | BW98: #N/A | BX98: #N/A | BY98: #N/A | BZ98: #N/A | CA98: #N/A | CB98: #N/A | CC98: #N/A | CD98: #N/A | CE98: #N/A | CF98: #N/A | CG98: #N/A | CH98: #N/A | CI98: #N/A | CJ98: #N/A | CM98: =CL98-CK98 -> 0 | CP98: =CO98-CN98 -> 0 | CS98: =CQ98-CR98 -> 0 | CX98: =((CW98-CY98)/BT98)*100 -> #N/A | CZ98: =((CW98)/BT98)*100 -> #N/A | DA98: =DB98/(CY98+BT98) -> #N/A | DC98: =DD98/(CY98+BT98) -> #N/A
